Workbook
Name S_Paper_Production_2019: 'P Data_Inventory'!$D$2

Sheet Content
A1: LAB 1 — ESG Data Quality Assessment Workbook
A2: WORKBOOK CONTENTS
A3: Sheet | B3: Purpose
A4: Data Inventory | B4: Core data entry: 30+ ESG KPIs with quality scoring (your main deliverable)
A5: KPI Checklist | B5: Track which ESG KPIs are available/missing by pillar
A6: Cross-Source Compare | B6: Compare the same 3 KPIs across 3 different sources and compute variance
A7: Summary Dashboard | B7: Auto-calculated summary metrics, heatmap, and quality overview
A8: Rubric | B8: Emission factors, quality scoring rubric, and framework reference
A10: HOW TO START
A11: Step 1 | B11: Start with KPI Checklist — mark which data points you can find for your company
A12: Step 2 | B12: Enter data in Data Inventory. Formulas calculate quality scores automatically.
A13: Step 3 | B13: Complete the Cross-Source Compare sheet for 3 KPIs (one E, one S, one G)
A14: Step 4 | B14: Summary Dashboard — it updates automatically from your data
A15: Step 5 | B15: Write your 150-word data gap analysis in the text box on the Summary sheet
A17: COLOR CODING IN THIS WORKBOOK
A18: Blue text | B18: Hardcoded inputs — cells YOU should fill in
A19: Black text | B19: Formulas — do not edit these
A20: Green text | B20: Cross-sheet references — do not edit these
A21: Yellow background | B21: Cells requiring your attention / inputs
A23: QUALITY SCORE INTERPRETATION
A24: 80 – 100 | B24: HIGH QUALITY — Use with full confidence in analysis
A25: 60 – 79 | B25: ACCEPTABLE — Use with appropriate caveats in report
A26: 40 – 59 | B26: USE WITH CAUTION — Flag as estimated in methodology
A27: 0 – 39 | B27: INSUFFICIENT — Seek alternative source or disclose gap

Sheet 1_Dictionary_Checklist
A1: DATA DICTIONARY -ESG KPI AVAILABILITY- CHECKLIST | G1: CAPSTONE PROJECT
A2: KPI Name | B2: Description | C2: Calculation Logic | D2: Unit | E2: Framework | F2: KPI Source | G2: Availability (✓/P/✗) | H2: Company KPI source | I2: Assurance | J2: Notes
A3: Scope 1 GHG Emissions (tCO₂e) | B3: Direct (Scope 1) greenhouse gas (GHG) emissions. | C3: Activity-level fuel data × emissions factors. Includes natural gas, coal, oil #2, oil #4, oil #6, shale oil, propane, diesel, and biogenic CH4 and N2O; gases included are CO2, CH4 and N2O. | D3: ktonnes CO2e in report; converted to tCO2e in Data Inventory | E3: GRI 305-1; GHG Protocol Corporate Accounting and Reporting Standard | F3: Smurfit Westrock Sustainability Report 2024 | G3: P | H3: 2024 Sustainability Report p.125 and EY schedule p.169: WestRock Scope 1 direct emissions = 5,674 ktonnes CO2e | I3: Limited assurance (EY, legacy WestRock only)
A4: Scope 2 GHG Emissions - Market Based (tCO₂e) | B4: Indirect (Scope 2) market-based greenhouse gas emissions. | C4: Activity-level purchased electricity and steam data × emissions factors under the market-based method; adjusts for renewable energy attributes generated and sold where applicable. | D4: ktonnes CO2e in report; converted to tCO2e in Data Inventory | E4: GRI 305-2; GHG Protocol Scope 2 Guidance | F4: Smurfit Westrock Sustainability Report 2024 | G4: P | H4: 2024 Sustainability Report p.125 and EY schedule p.169: WestRock Scope 2 market-based = 2,300 ktonnes CO2e | I4: Limited assurance (EY, legacy WestRock only)
A5: Scope 2 GHG Emissions - Location Based (tCO₂e) | B5: Indirect (Scope 2) location-based greenhouse gas emissions. | C5: Reported by legacy WestRock in the supporting-data table using the location-based method for purchased energy. The supporting-data table discloses the value directly. | D5: ktonnes CO2e in report; converted to tCO2e in Data Inventory | E5: GRI 305-2; GHG Protocol Scope 2 Guidance | F5: Smurfit Westrock Sustainability Report 2024 | G5: P | H5: 2024 Sustainability Report p.125: WestRock Scope 2 location-based = 1,746 ktonnes CO2e | I5: Self-reported (legacy WestRock table)
A6: Scope 3 GHG Emissions - Total (tCO₂e) | B6: Other indirect (Scope 3) greenhouse gas emissions for relevant categories. | C6: Sum of relevant Scope 3 categories 1, 2, 3, 4, 9, 10 and 12 under the GHG Protocol Corporate Value Chain (Scope 3) Accounting and Reporting Standard. | D6: ktonnes CO2e in report; converted to tCO2e in Data Inventory | E6: GRI 305-3; GHG Protocol Corporate Value Chain (Scope 3) | F6: Smurfit Westrock Sustainability Report 2024 | G6: P | H6: 2024 Sustainability Report p.125 and EY schedule p.171: WestRock Scope 3 relevant categories = 9,452 ktonnes CO2e | I6: Limited assurance (EY, legacy WestRock relevant categories)
A7: Carbon Intensity (tCO₂e per $M revenue) | B7: Template asks for carbon intensity per $M revenue; the report discloses GHG emissions intensity per ton, not per revenue. | C7: Not disclosed on a revenue basis. WestRock reports GHG emissions intensity of 0.55 tCO2e/ton in the supporting-data table. | D7: tCO2e/$M requested by template; report provides tCO2e/ton | E7: GRI 305-4 | F7: Smurfit Westrock Sustainability Report 2024 | G7: ✗ | H7: No directly disclosed carbon intensity per $M revenue in the 2024 Sustainability Report; WestRock instead reports 0.55 tCO2e/ton GHG emissions intensity on p.125 | I7: Not disclosed for revenue basis
A8: Total Energy Consumption (GWh) | B8: Energy consumption within the organization. | C8: Total direct energy consumption + total indirect energy consumption; direct = renewable + non-renewable fuel consumption, indirect = purchased electricity + purchased steam − electricity sold − steam sold. | D8: MMBtu in report; converted to GWh in Data Inventory | E8: GRI 302-1; SASB RR-PP-130a.1 | F8: Smurfit Westrock Sustainability Report 2024 | G8: P | H8: 2024 Sustainability Report p.125 and EY schedule p.175: WestRock total energy used = 284,911,157 MMBtu; converted to GWh for this template | I8: Limited assurance (EY, legacy WestRock energy data)
A9: Renewable Energy Percentage (%) | B9: Share of total energy mix from renewable sources. | C9: Fuel consumption from renewable sources ÷ total energy consumption. | D9: % | E9: GRI 302-1; SASB RR-PP-130a.1 | F9: Smurfit Westrock Sustainability Report 2024 | G9: P | H9: 2024 Sustainability Report p.125 and EY schedule p.175: WestRock energy mix = 60% renewable | I9: Directly disclosed in legacy WestRock energy table
A10: Energy Intensity (GJ per unit of output) | B10: Purchased fuel efficiency / energy intensity for mills. | C10: Purchased energy for mills ÷ tons of paperboard and containerboard produced. Purchased energy includes purchased fuel, electricity, and steam, net of sold electricity where applicable. | D10: MMBtu/ton in report; converted to GJ/ton in Data Inventory | E10: GRI 302-3; DOE Energy Intensity and Baselining Guidance | F10: Smurfit Westrock Sustainability Report 2024 | G10: P | H10: 2024 Sustainability Report p.125 and EY schedule p.175: purchased fuel energy efficiency = 12.62 MMBtu/ton; used as proxy | I10: Proxy from limited-assured WestRock purchased fuel efficiency
A11: Total Water Withdrawal (Megalitres) | B11: Mill water withdrawal from all sources. | C11: Total water intake from surface water, groundwater, and third-party water for mills manufacturing paperboard and containerboard. | D11: Megalitres | E11: GRI 303-3; SASB RR-PP-140a.1 | F11: Smurfit Westrock Sustainability Report 2024 | G11: P | H11: 2024 Sustainability Report p.127 and EY schedule p.175: WestRock mill water withdrawal = 470,201 megalitres | I11: Limited assurance (EY, legacy WestRock mills)
A12: Water Recycled / Reused (%) | B12: Quantitative recycled / reused water percentage. | C12: Not disclosed in the 2024 Sustainability Report. | D12: % | E12: Not disclosed in report | F12: Smurfit Westrock Sustainability Report 2024 | G12: ✗ | H12: No quantitative recycled / reused water percentage disclosed in the 2024 Sustainability Report | I12: Not disclosed
A13: Total Waste Generated (Metric Tonnes) | B13: Mill waste generated across landfill, waste-to-energy, and beneficial-use streams. | C13: Landfill + waste-to-energy + beneficial use. The report gives U.S. short tons; Data Inventory converts to metric tonnes for the template. | D13: U.S. short tons in report; converted to metric tonnes in Data Inventory | E13: GRI 306-3; GRI 306-4; GRI 306-5 | F13: Smurfit Westrock Sustainability Report 2024 | G13: P | H13: 2024 Sustainability Report p.127: WestRock mill waste streams (landfill, waste-to-energy, beneficial use) converted from short tons to metric tonnes | I13: Self-reported / derived (legacy WestRock mills)
A14: Waste Diversion Rate (% not to landfill) | B14: Share of disclosed mill waste not sent to landfill. | C14: (Waste-to-energy + beneficial use) ÷ (landfill + waste-to-energy + beneficial use). Derived from the WestRock mill waste table. | D14: % | E14: GRI 306-4; GRI 306-5 | F14: Smurfit Westrock Sustainability Report 2024 | G14: P | H14: Calculated from 2024 Sustainability Report p.127 WestRock mill waste streams | I14: Calculated from self-reported WestRock mill waste data
... A30: Board Independence (% Independent) | B30: Ratio of non-executive/independent directors | C30: (Independent directors ÷ Total directors) × 100 | D30: % | E30: GRI 2-9 | F30: https://www.globalreporting.org/how-to-use-the-gri-standards/gri-standards-english-language/ | G30: P | H30: 2024 Sustainability Report | I30: Resonable
A31: Women on Board (%) | D31: % | G31: P | H31: 2024 Sustainability Report | I31: Resonable
A32: Average Board Tenure (years) | B32: Average length of service for board members. | C32: Sum of years served ÷ Total directors. | D32: # | E32: IFRS S1 | F32: https://navigator.sasb.ifrs.org/login | G32: X | H32: 2024 Sustainability Report | I32: Resonable
A33: CEO Pay Ratio (CEO to Median Employee) | B33: Pay equity between leadership and staff. | C33: Total CEO compensation ÷ Median employee pay. | D33: % | E33: SEC / ESRS S1 | F33: https://cdn.cdp.net/cdp-production/comfy/cms/files/files/000/006/299/original/CDP's_comment_on_the_European_Sustainability_Reporting_Standards.pdf | G33: X | H33: 2024 Sustainability Report | I33: Resonable
A34: ESG Metrics in Executive Incentive Pay (Y/N) | B34: Whether ESG KPIs affect executive bonuses. | C34: Binary disclosure (Yes/No). | E34: ESRS G1-1 | F34: https://cdn.cdp.net/cdp-production/comfy/cms/files/files/000/006/299/original/CDP's_comment_on_the_European_Sustainability_Reporting_Standards.pdf | G34: X | H34: 2024 Sustainability Report | I34: Resonable
A35: Number of Ethics / Compliance Violations | B35: Total number of confirmed breaches/whistleblows. | C35: Count of substantiated legal or policy breaches. | D35: # | E35: GRI 2-27 | F35: https://www.globalreporting.org/how-to-use-the-gri-standards/gri-standards-english-language/ | G35: X | H35: 2024 Sustainability Report | I35: Resonable
A36: Anti-corruption Policy in Place (Y/N) | B36: Publicly available commitment against bribery. | C36: Binary disclosure (Yes/No). | E36: GRI 205-2 | F36: https://www.globalreporting.org/how-to-use-the-gri-standards/gri-standards-english-language/ | G36: ✓ | H36: 2024 Sustainability Report | I36: Resonable
A37: ESG Assurance Provider | B37: 3rd party validation of information and data | G37: ✓ | H37: 2024 Sustainability Report | I37: Resonable
A39: Annual Revenue ($M) | B39: Net sales for the year. | C39: Direct annual-report figure for 2024 net sales. | D39: USD millions | E39: Annual Report / Form 10-K | F39: Smurfit Westrock 2024 Annual Report | G39: ✓ | H39: 2024 Annual Report pdf p.57 and Segment Information note pdf p.102: net sales (unaffiliated customers) = $21,109 million | I39: Audited annual report
A40: EBITDA Margin (%) | B40: Adjusted EBITDA as a percentage of net sales. | C40: Adjusted EBITDA ÷ net sales × 100. | D40: % | E40: Annual Report non-GAAP reconciliation | F40: Smurfit Westrock 2024 Annual Report | G40: ✓ | H40: Calculated from 2024 Annual Report pdf p.68 Adjusted EBITDA = $3,386 million and pdf p.57 net sales = $21,109 million | I40: Calculated from annual report figures
A41: Capital Expenditure ($M) | B41: Capital expenditures for the year. | C41: Direct annual-report figure for total capital expenditure. | D41: USD millions | E41: Annual Report / Form 10-K | F41: Smurfit Westrock 2024 Annual Report | G41: ✓ | H41: 2024 Annual Report pdf p.105: total capital expenditure = $1,466 million | I41: Audited annual report
A42: Market Capitalization ($M) | B42: Year-end market value of equity. | C42: Year-end closing share price × shares outstanding at December 31, 2024. | D42: USD millions | E42: Calculated from Annual Report + market price | F42: Smurfit Westrock 2024 Annual Report | G42: P | H42: Calculated from 2024 Annual Report pdf p.78 shares outstanding = 520,444,261 and 2024-12-31 closing share price = $51.3218 | I42: Calculated from audited shares and external market price
A43: R&D Expenditure ($M) | B43: Research and development expenditure. | C43: Not separately disclosed in the 2024 Annual Report. | D43: USD millions | E43: Not disclosed in Annual Report | F43: Smurfit Westrock 2024 Annual Report | G43: ✗ | H43: No separate R&D expenditure line disclosed in the 2024 Annual Report | I43: Not disclosed
B45: Count your ✓, P, and ✗ marks and calculate coverage rate below
B46: [Count manually]
B47: [Count manually]
B48: [Count manually]
B49: [=Available / Total KPIs]
B50: [Name the most critical missing KPI and why it matters]

Sheet Sheet1
A1: Pillar (E/S/G/Financial) | B1: E
A3: Sum of (Unit/$ Market Cap) | B3: Column Labels
A4: Row Labels | B4: S | C4: W | D4: Grand Total
A5: Carbon | B5: 1769.052 | C5: 9238.6689 | D5: 11007.721
A6: Scope 1 GHG Emissions | B6: 1478.706 | C6: 3721.0704 | D6: 5199.7764
A7: Scope 2 GHG Emissions (Location-Based) | B7: 290.34599 | C7: 1137.3981 | D7: 1427.7441
A8: Scope 2 GHG Emissions (Market-Based) | C8: 1434.0785 | D8: 1434.0785
A9: Scope 3 GHG Emissions (Total) | C9: 2946.1219 | D9: 2946.1219
A10: Energy | B10: 12.882567 | C10: 106.22946 | D10: 119.11203
A11: Non-Renewable Energy Consumptio | B11: 12.877253 | C11: 19.329786 | D11: 32.207038
A12: Total Energy Consumption | C12: 53.647555 | D12: 53.647555
A13: Total Renewable Energy Consumption | B13: 0.0053138177 | C13: 33.252123 | D13: 33.257437
A14: Sourcing | B14: 3827.7497 | C14: 3135.8245 | D14: 6963.5742
A15: Used Recovered Fiber | B15: 3827.7497 | C15: 3135.8245 | D15: 6963.5742
A16: Waste | B16: 535.73939 | C16: 777.06706 | D16: 1312.8065
A17: Hazardous Waste Generated | B17: 6.6094666 | D17: 6.6094666
A18: Other Waste | B18: 8.84957 | D18: 8.84957
A19: Waste-to-Energy | C19: 167.42728 | D19: 167.42728
A20: Waste-to-Landfill | B20: 256.63346 | C20: 472.5425 | D20: 729.17596
A21: Waste-to-Recovery | B21: 263.6469 | C21: 137.09728 | D21: 400.74418
A22: Grand Total | B22: 6145.4237 | C22: 13257.79 | D22: 19403.214

Sheet ESG
A1: Pillar (E/S/G/Financial) | B1: KPI Category | C1: KPI Name | D1: Total Value | E1: Buisness | F1: Unit | G1: Reporting Year | H1: (Unit/$ Revenue) | I1: (Unit/$ Market Cap)
A2: E | B2: Energy | C2: Total Renewable Energy Consumption | D2: 5 | E2: S | F2: GWh | G2: 2019 | H2: =$D2/IF($E2="S",_xlfn.XLOOKUP($G2,Tables_for_Reference!$J$15:$J$21,Tables_for_Reference!$I$15:$I$21),IF(ESG!$E2="W",_xlfn.XLOOKUP(ESG!$G2,Tables_for_Reference!$J$15:$J$21,Tables_for_Reference!$H$15:$H$21),"Error")) -> 0.00055260831 | I2: =$D2/IF($E2="S",_xlfn.XLOOKUP($G2,Tables_for_Reference!$J$24:$J$29,Tables_for_Reference!$I$24:$I$29),IF(ESG!E2="W",_xlfn.XLOOKUP(ESG!G2,Tables_for_Reference!$J$24:$J$29,Tables_for_Reference!$H$24:$H$29),"Error")) -> 0.00060941423
A3: E | B3: Energy | C3: Total Renewable Energy Consumption | D3: 6 | E3: S | F3: GWh | G3: 2021 | H3: =D3/IF(E3="S",_xlfn.XLOOKUP($G3,Tables_for_Reference!$J$15:$J$21,Tables_for_Reference!$I$15:$I$21),IF(ESG!$E3="W",_xlfn.XLOOKUP(ESG!$G3,Tables_for_Reference!$J$15:$J$21,Tables_for_Reference!$H$15:$H$21),"Error")) -> 0.00059364797 | I3: =$D3/IF($E3="S",_xlfn.XLOOKUP($G3,Tables_for_Reference!$J$24:$J$29,Tables_for_Reference!$I$24:$I$29),IF(ESG!E3="W",_xlfn.XLOOKUP(ESG!G3,Tables_for_Reference!$J$24:$J$29,Tables_for_Reference!$H$24:$H$29),"Error")) -> 0.00048028817
A4: E | B4: Energy | C4: Total Renewable Energy Consumption | D4: 6 | E4: S | F4: GWh | G4: 2020 | H4: =D4/IF(E4="S",_xlfn.XLOOKUP($G4,Tables_for_Reference!$J$15:$J$21,Tables_for_Reference!$I$15:$I$21),IF(ESG!$E4="W",_xlfn.XLOOKUP(ESG!$G4,Tables_for_Reference!$J$15:$J$21,Tables_for_Reference!$H$15:$H$21),"Error")) -> 0.00070339977 | I4: =$D4/IF($E4="S",_xlfn.XLOOKUP($G4,Tables_for_Reference!$J$24:$J$29,Tables_for_Reference!$I$24:$I$29),IF(ESG!E4="W",_xlfn.XLOOKUP(ESG!G4,Tables_for_Reference!$J$24:$J$29,Tables_for_Reference!$H$24:$H$29),"Error")) -> 0.00060617082
A5: E | B5: Energy | C5: Total Renewable Energy Consumption | D5: 8 | E5: S | F5: GWh | G5: 2022 | H5: =D5/IF(E5="S",_xlfn.XLOOKUP($G5,Tables_for_Reference!$J$15:$J$21,Tables_for_Reference!$I$15:$I$21),IF(ESG!$E5="W",_xlfn.XLOOKUP(ESG!$G5,Tables_for_Reference!$J$15:$J$21,Tables_for_Reference!$H$15:$H$21),"Error")) -> 0.00062426844 | I5: =$D5/IF($E5="S",_xlfn.XLOOKUP($G5,Tables_for_Reference!$J$24:$J$29,Tables_for_Reference!$I$24:$I$29),IF(ESG!E5="W",_xlfn.XLOOKUP(ESG!G5,Tables_for_Reference!$J$24:$J$29,Tables_for_Reference!$H$24:$H$29),"Error")) -> 0.00089037284
A6: E | B6: Energy | C6: Total Renewable Energy Consumption | D6: 11 | E6: S | F6: GWh | G6: 2023 | H6: =D6/IF(E6="S",_xlfn.XLOOKUP($G6,Tables_for_Reference!$J$15:$J$21,Tables_for_Reference!$I$15:$I$21),IF(ESG!$E6="W",_xlfn.XLOOKUP(ESG!$G6,Tables_for_Reference!$J$15:$J$21,Tables_for_Reference!$H$15:$H$21),"Error")) -> 0.00097586941 | I6: =$D6/IF($E6="S",_xlfn.XLOOKUP($G6,Tables_for_Reference!$J$24:$J$29,Tables_for_Reference!$I$24:$I$29),IF(ESG!E6="W",_xlfn.XLOOKUP(ESG!G6,Tables_for_Reference!$J$24:$J$29,Tables_for_Reference!$H$24:$H$29),"Error")) -> 0.0011739093
A7: E | B7: Energy | C7: Total Renewable Energy Consumption | D7: 22 | E7: S | F7: GWh | G7: 2024 | H7: =D7/IF(E7="S",_xlfn.XLOOKUP($G7,Tables_for_Reference!$J$15:$J$21,Tables_for_Reference!$I$15:$I$21),IF(ESG!$E7="W",_xlfn.XLOOKUP(ESG!$G7,Tables_for_Reference!$J$15:$J$21,Tables_for_Reference!$H$15:$H$21),"Error")) -> 0.0029200727 | I7: =$D7/IF($E7="S",_xlfn.XLOOKUP($G7,Tables_for_Reference!$J$24:$J$29,Tables_for_Reference!$I$24:$I$29),IF(ESG!E7="W",_xlfn.XLOOKUP(ESG!G7,Tables_for_Reference!$J$24:$J$29,Tables_for_Reference!$H$24:$H$29),"Error")) -> 0.0015536623
A8: E | B8: Carbon | C8: Scope 2 GHG Emissions (Location-Based) | D8: 467 | E8: S | F8: tCO₂e | G8: 2023 | H8: =D8/IF(E8="S",_xlfn.XLOOKUP($G8,Tables_for_Reference!$J$15:$J$21,Tables_for_Reference!$I$15:$I$21),IF(ESG!$E8="W",_xlfn.XLOOKUP(ESG!$G8,Tables_for_Reference!$J$15:$J$21,Tables_for_Reference!$H$15:$H$21),"Error")) -> 0.041430092 | I8: =$D8/IF($E8="S",_xlfn.XLOOKUP($G8,Tables_for_Reference!$J$24:$J$29,Tables_for_Reference!$I$24:$I$29),IF(ESG!E8="W",_xlfn.XLOOKUP(ESG!G8,Tables_for_Reference!$J$24:$J$29,Tables_for_Reference!$H$24:$H$29),"Error")) -> 0.049837787
A9: E | B9: Water | C9: Total BOD Discharged | D9: 8389.5455 | E9: W | F9: Metric Tonnes | G9: 2024 | H9: =D9/IF(E9="S",_xlfn.XLOOKUP($G9,Tables_for_Reference!$J$15:$J$21,Tables_for_Reference!$I$15:$I$21),IF(ESG!$E9="W",_xlfn.XLOOKUP(ESG!$G9,Tables_for_Reference!$J$15:$J$21,Tables_for_Reference!$H$15:$H$21),"Error")) -> 0.61801708 | I9: =$D9/IF($E9="S",_xlfn.XLOOKUP($G9,Tables_for_Reference!$J$24:$J$29,Tables_for_Reference!$I$24:$I$29),IF(ESG!E9="W",_xlfn.XLOOKUP(ESG!G9,Tables_for_Reference!$J$24:$J$29,Tables_for_Reference!$H$24:$H$29),"Error")) -> 0.60482592
A10: E | B10: Waste | C10: Hazardous Waste Generated | D10: 8774 | E10: S | F10: Metric Tonnes | G10: 2021 | H10: =D10/IF(E10="S",_xlfn.XLOOKUP($G10,Tables_for_Reference!$J$15:$J$21,Tables_for_Reference!$I$15:$I$21),IF(ESG!$E10="W",_xlfn.XLOOKUP(ESG!$G10,Tables_for_Reference!$J$15:$J$21,Tables_for_Reference!$H$15:$H$21),"Error")) -> 0.86811121 | I10: =$D10/IF($E10="S",_xlfn.XLOOKUP($G10,Tables_for_Reference!$J$24:$J$29,Tables_for_Reference!$I$24:$I$29),IF(ESG!E10="W",_xlfn.XLOOKUP(ESG!G10,Tables_for_Reference!$J$24:$J$29,Tables_for_Reference!$H$24:$H$29),"Error")) -> 0.7023414
A11: E | B11: Water | C11: Total BOD Discharged | D11: 8875.4545 | E11: W | F11: Metric Tonnes | G11: 2023 | H11: =D11/IF(E11="S",_xlfn.XLOOKUP($G11,Tables_for_Reference!$J$15:$J$21,Tables_for_Reference!$I$15:$I$21),IF(ESG!$E11="W",_xlfn.XLOOKUP(ESG!$G11,Tables_for_Reference!$J$15:$J$21,Tables_for_Reference!$H$15:$H$21),"Error")) -> 0.43699924 | I11: =$D11/IF($E11="S",_xlfn.XLOOKUP($G11,Tables_for_Reference!$J$24:$J$29,Tables_for_Reference!$I$24:$I$29),IF(ESG!E11="W",_xlfn.XLOOKUP(ESG!G11,Tables_for_Reference!$J$24:$J$29,Tables_for_Reference!$H$24:$H$29),"Error")) -> 0.96691991
A12: E | B12: Waste | C12: Other Waste | D12: 9002 | E12: S | F12: Metric Tonnes | G12: 2020 | H12: =D12/IF(E12="S",_xlfn.XLOOKUP($G12,Tables_for_Reference!$J$15:$J$21,Tables_for_Reference!$I$15:$I$21),IF(ESG!$E12="W",_xlfn.XLOOKUP(ESG!$G12,Tables_for_Reference!$J$15:$J$21,Tables_for_Reference!$H$15:$H$21),"Error")) -> 1.0553341 | I12: =$D12/IF($E12="S",_xlfn.XLOOKUP($G12,Tables_for_Reference!$J$24:$J$29,Tables_for_Reference!$I$24:$I$29),IF(ESG!E12="W",_xlfn.XLOOKUP(ESG!G12,Tables_for_Reference!$J$24:$J$29,Tables_for_Reference!$H$24:$H$29),"Error")) -> 0.90945829
A13: E | B13: Water | C13: Total BOD Discharged | D13: 9255 | E13: W | F13: Metric Tonnes | G13: 2020 | H13: =D13/IF(E13="S",_xlfn.XLOOKUP($G13,Tables_for_Reference!$J$15:$J$21,Tables_for_Reference!$I$15:$I$21),IF(ESG!$E13="W",_xlfn.XLOOKUP(ESG!$G13,Tables_for_Reference!$J$15:$J$21,Tables_for_Reference!$H$15:$H$21),"Error")) -> 0.52648645 | I13: =$D13/IF($E13="S",_xlfn.XLOOKUP($G13,Tables_for_Reference!$J$24:$J$29,Tables_for_Reference!$I$24:$I$29),IF(ESG!E13="W",_xlfn.XLOOKUP(ESG!G13,Tables_for_Reference!$J$24:$J$29,Tables_for_Reference!$H$24:$H$29),"Error")) -> 1.0230702
A14: E | B14: Waste | C14: Hazardous Waste Generated | D14: 9655 | E14: S | F14: Metric Tonnes | G14: 2019 | H14: =D14/IF(E14="S",_xlfn.XLOOKUP($G14,Tables_for_Reference!$J$15:$J$21,Tables_for_Reference!$I$15:$I$21),IF(ESG!$E14="W",_xlfn.XLOOKUP(ESG!$G14,Tables_for_Reference!$J$15:$J$21,Tables_for_Reference!$H$15:$H$21),"Error")) -> 1.0670866 | I14: =$D14/IF($E14="S",_xlfn.XLOOKUP($G14,Tables_for_Reference!$J$24:$J$29,Tables_for_Reference!$I$24:$I$29),IF(ESG!E14="W",_xlfn.XLOOKUP(ESG!G14,Tables_for_Reference!$J$24:$J$29,Tables_for_Reference!$H$24:$H$29),"Error")) -> 1.1767789
... A246: S | B246: Diversity | C246: Women in Total Workforce | D246: 9894.888 | E246: S | F246: employees | G246: 2024 | H246: =D246/IF(E246="S",_xlfn.XLOOKUP($G246,Tables_for_Reference!$J$15:$J$21,Tables_for_Reference!$I$15:$I$21),IF(ESG!$E246="W",_xlfn.XLOOKUP(ESG!$G246,Tables_for_Reference!$J$15:$J$21,Tables_for_Reference!$H$15:$H$21),"Error")) -> 1.3133542 | I246: =$D246/IF($E246="S",_xlfn.XLOOKUP($G246,Tables_for_Reference!$J$24:$J$29,Tables_for_Reference!$I$24:$I$29),IF(ESG!E246="W",_xlfn.XLOOKUP(ESG!G246,Tables_for_Reference!$J$24:$J$29,Tables_for_Reference!$H$24:$H$29),"Error")) -> 0.698787
A247: G | B247: Ethics | C247: Anti-corruption Policy in Place (Y/N) | D247: Yes | E247: SW | G247: 2024 | H247: =D247/IF(E247="S",_xlfn.XLOOKUP($G247,Tables_for_Reference!$J$15:$J$21,Tables_for_Reference!$I$15:$I$21),IF(ESG!$E247="W",_xlfn.XLOOKUP(ESG!$G247,Tables_for_Reference!$J$15:$J$21,Tables_for_Reference!$H$15:$H$21),"Error")) -> #VALUE! | I247: =$D247/IF($E247="S",_xlfn.XLOOKUP($G247,Tables_for_Reference!$J$24:$J$29,Tables_for_Reference!$I$24:$I$29),IF(ESG!E247="W",_xlfn.XLOOKUP(ESG!G247,Tables_for_Reference!$J$24:$J$29,Tables_for_Reference!$H$24:$H$29),"Error")) -> #VALUE!
A248: G | B248: Ethics | C248: Anti-corruption Policy in Place (Y/N) | D248: Yes | E248: W | G248: 2023 | H248: =D248/IF(E248="S",_xlfn.XLOOKUP($G248,Tables_for_Reference!$J$15:$J$21,Tables_for_Reference!$I$15:$I$21),IF(ESG!$E248="W",_xlfn.XLOOKUP(ESG!$G248,Tables_for_Reference!$J$15:$J$21,Tables_for_Reference!$H$15:$H$21),"Error")) -> #VALUE! | I248: =$D248/IF($E248="S",_xlfn.XLOOKUP($G248,Tables_for_Reference!$J$24:$J$29,Tables_for_Reference!$I$24:$I$29),IF(ESG!E248="W",_xlfn.XLOOKUP(ESG!G248,Tables_for_Reference!$J$24:$J$29,Tables_for_Reference!$H$24:$H$29),"Error")) -> #VALUE!
A249: G | B249: Ethics | C249: Anti-corruption Policy in Place (Y/N) | D249: Yes | E249: S | G249: 2023 | H249: =D249/IF(E249="S",_xlfn.XLOOKUP($G249,Tables_for_Reference!$J$15:$J$21,Tables_for_Reference!$I$15:$I$21),IF(ESG!$E249="W",_xlfn.XLOOKUP(ESG!$G249,Tables_for_Reference!$J$15:$J$21,Tables_for_Reference!$H$15:$H$21),"Error")) -> #VALUE! | I249: =$D249/IF($E249="S",_xlfn.XLOOKUP($G249,Tables_for_Reference!$J$24:$J$29,Tables_for_Reference!$I$24:$I$29),IF(ESG!E249="W",_xlfn.XLOOKUP(ESG!G249,Tables_for_Reference!$J$24:$J$29,Tables_for_Reference!$H$24:$H$29),"Error")) -> #VALUE!
A250: G | B250: Ethics | C250: Anti-corruption Policy in Place (Y/N) | D250: Yes | E250: W | G250: 2022 | H250: =D250/IF(E250="S",_xlfn.XLOOKUP($G250,Tables_for_Reference!$J$15:$J$21,Tables_for_Reference!$I$15:$I$21),IF(ESG!$E250="W",_xlfn.XLOOKUP(ESG!$G250,Tables_for_Reference!$J$15:$J$21,Tables_for_Reference!$H$15:$H$21),"Error")) -> #VALUE! | I250: =$D250/IF($E250="S",_xlfn.XLOOKUP($G250,Tables_for_Reference!$J$24:$J$29,Tables_for_Reference!$I$24:$I$29),IF(ESG!E250="W",_xlfn.XLOOKUP(ESG!G250,Tables_for_Reference!$J$24:$J$29,Tables_for_Reference!$H$24:$H$29),"Error")) -> #VALUE!
A251: G | B251: Ethics | C251: Anti-corruption Policy in Place (Y/N) | D251: Yes | E251: S | G251: 2022 | H251: =D251/IF(E251="S",_xlfn.XLOOKUP($G251,Tables_for_Reference!$J$15:$J$21,Tables_for_Reference!$I$15:$I$21),IF(ESG!$E251="W",_xlfn.XLOOKUP(ESG!$G251,Tables_for_Reference!$J$15:$J$21,Tables_for_Reference!$H$15:$H$21),"Error")) -> #VALUE! | I251: =$D251/IF($E251="S",_xlfn.XLOOKUP($G251,Tables_for_Reference!$J$24:$J$29,Tables_for_Reference!$I$24:$I$29),IF(ESG!E251="W",_xlfn.XLOOKUP(ESG!G251,Tables_for_Reference!$J$24:$J$29,Tables_for_Reference!$H$24:$H$29),"Error")) -> #VALUE!
A252: G | B252: Ethics | C252: Anti-corruption Policy in Place (Y/N) | D252: Yes | E252: W | G252: 2021 | H252: =D252/IF(E252="S",_xlfn.XLOOKUP($G252,Tables_for_Reference!$J$15:$J$21,Tables_for_Reference!$I$15:$I$21),IF(ESG!$E252="W",_xlfn.XLOOKUP(ESG!$G252,Tables_for_Reference!$J$15:$J$21,Tables_for_Reference!$H$15:$H$21),"Error")) -> #VALUE! | I252: =$D252/IF($E252="S",_xlfn.XLOOKUP($G252,Tables_for_Reference!$J$24:$J$29,Tables_for_Reference!$I$24:$I$29),IF(ESG!E252="W",_xlfn.XLOOKUP(ESG!G252,Tables_for_Reference!$J$24:$J$29,Tables_for_Reference!$H$24:$H$29),"Error")) -> #VALUE!
A253: G | B253: Ethics | C253: Anti-corruption Policy in Place (Y/N) | D253: Yes | E253: S | G253: 2021 | H253: =D253/IF(E253="S",_xlfn.XLOOKUP($G253,Tables_for_Reference!$J$15:$J$21,Tables_for_Reference!$I$15:$I$21),IF(ESG!$E253="W",_xlfn.XLOOKUP(ESG!$G253,Tables_for_Reference!$J$15:$J$21,Tables_for_Reference!$H$15:$H$21),"Error")) -> #VALUE! | I253: =$D253/IF($E253="S",_xlfn.XLOOKUP($G253,Tables_for_Reference!$J$24:$J$29,Tables_for_Reference!$I$24:$I$29),IF(ESG!E253="W",_xlfn.XLOOKUP(ESG!G253,Tables_for_Reference!$J$24:$J$29,Tables_for_Reference!$H$24:$H$29),"Error")) -> #VALUE!
A254: G | B254: Ethics | C254: Anti-corruption Policy in Place (Y/N) | D254: Yes | E254: W | G254: 2020 | H254: =D254/IF(E254="S",_xlfn.XLOOKUP($G254,Tables_for_Reference!$J$15:$J$21,Tables_for_Reference!$I$15:$I$21),IF(ESG!$E254="W",_xlfn.XLOOKUP(ESG!$G254,Tables_for_Reference!$J$15:$J$21,Tables_for_Reference!$H$15:$H$21),"Error")) -> #VALUE! | I254: =$D254/IF($E254="S",_xlfn.XLOOKUP($G254,Tables_for_Reference!$J$24:$J$29,Tables_for_Reference!$I$24:$I$29),IF(ESG!E254="W",_xlfn.XLOOKUP(ESG!G254,Tables_for_Reference!$J$24:$J$29,Tables_for_Reference!$H$24:$H$29),"Error")) -> #VALUE!
A255: G | B255: Ethics | C255: Anti-corruption Policy in Place (Y/N) | D255: Yes | E255: S | G255: 2020 | H255: =D255/IF(E255="S",_xlfn.XLOOKUP($G255,Tables_for_Reference!$J$15:$J$21,Tables_for_Reference!$I$15:$I$21),IF(ESG!$E255="W",_xlfn.XLOOKUP(ESG!$G255,Tables_for_Reference!$J$15:$J$21,Tables_for_Reference!$H$15:$H$21),"Error")) -> #VALUE! | I255: =$D255/IF($E255="S",_xlfn.XLOOKUP($G255,Tables_for_Reference!$J$24:$J$29,Tables_for_Reference!$I$24:$I$29),IF(ESG!E255="W",_xlfn.XLOOKUP(ESG!G255,Tables_for_Reference!$J$24:$J$29,Tables_for_Reference!$H$24:$H$29),"Error")) -> #VALUE!
A256: G | B256: Ethics | C256: Anti-corruption Policy in Place (Y/N) | D256: Yes | E256: W | G256: 2019 | H256: =D256/IF(E256="S",_xlfn.XLOOKUP($G256,Tables_for_Reference!$J$15:$J$21,Tables_for_Reference!$I$15:$I$21),IF(ESG!$E256="W",_xlfn.XLOOKUP(ESG!$G256,Tables_for_Reference!$J$15:$J$21,Tables_for_Reference!$H$15:$H$21),"Error")) -> #VALUE! | I256: =$D256/IF($E256="S",_xlfn.XLOOKUP($G256,Tables_for_Reference!$J$24:$J$29,Tables_for_Reference!$I$24:$I$29),IF(ESG!E256="W",_xlfn.XLOOKUP(ESG!G256,Tables_for_Reference!$J$24:$J$29,Tables_for_Reference!$H$24:$H$29),"Error")) -> #VALUE!
A257: G | B257: Ethics | C257: Anti-corruption Policy in Place (Y/N) | D257: Yes | E257: S | G257: 2019 | H257: =D257/IF(E257="S",_xlfn.XLOOKUP($G257,Tables_for_Reference!$J$15:$J$21,Tables_for_Reference!$I$15:$I$21),IF(ESG!$E257="W",_xlfn.XLOOKUP(ESG!$G257,Tables_for_Reference!$J$15:$J$21,Tables_for_Reference!$H$15:$H$21),"Error")) -> #VALUE! | I257: =$D257/IF($E257="S",_xlfn.XLOOKUP($G257,Tables_for_Reference!$J$24:$J$29,Tables_for_Reference!$I$24:$I$29),IF(ESG!E257="W",_xlfn.XLOOKUP(ESG!G257,Tables_for_Reference!$J$24:$J$29,Tables_for_Reference!$H$24:$H$29),"Error")) -> #VALUE!
A258: G | B258: Board | C258: Total Board Size | D258: 14 | E258: SW | F258: Directors | G258: 2024 | H258: =D258/IF(E258="S",_xlfn.XLOOKUP($G258,Tables_for_Reference!$J$15:$J$21,Tables_for_Reference!$I$15:$I$21),IF(ESG!$E258="W",_xlfn.XLOOKUP(ESG!$G258,Tables_for_Reference!$J$15:$J$21,Tables_for_Reference!$H$15:$H$21),"Error")) -> #VALUE! | I258: =$D258/IF($E258="S",_xlfn.XLOOKUP($G258,Tables_for_Reference!$J$24:$J$29,Tables_for_Reference!$I$24:$I$29),IF(ESG!E258="W",_xlfn.XLOOKUP(ESG!G258,Tables_for_Reference!$J$24:$J$29,Tables_for_Reference!$H$24:$H$29),"Error")) -> #VALUE!
A259: G | B259: Board | C259: Independent Directors | D259: 12 | E259: SW | F259: Directors | G259: 2024 | H259: =D259/IF(E259="S",_xlfn.XLOOKUP($G259,Tables_for_Reference!$J$15:$J$21,Tables_for_Reference!$I$15:$I$21),IF(ESG!$E259="W",_xlfn.XLOOKUP(ESG!$G259,Tables_for_Reference!$J$15:$J$21,Tables_for_Reference!$H$15:$H$21),"Error")) -> #VALUE! | I259: =$D259/IF($E259="S",_xlfn.XLOOKUP($G259,Tables_for_Reference!$J$24:$J$29,Tables_for_Reference!$I$24:$I$29),IF(ESG!E259="W",_xlfn.XLOOKUP(ESG!G259,Tables_for_Reference!$J$24:$J$29,Tables_for_Reference!$H$24:$H$29),"Error")) -> #VALUE!
A260: G | B260: Board | C260: Board Independence (% Independent Directors) | D260: 0.85714286 | E260: SW | F260: % | G260: 2024 | H260: =D260/IF(E260="S",_xlfn.XLOOKUP($G260,Tables_for_Reference!$J$15:$J$21,Tables_for_Reference!$I$15:$I$21),IF(ESG!$E260="W",_xlfn.XLOOKUP(ESG!$G260,Tables_for_Reference!$J$15:$J$21,Tables_for_Reference!$H$15:$H$21),"Error")) -> #VALUE! | I260: =$D260/IF($E260="S",_xlfn.XLOOKUP($G260,Tables_for_Reference!$J$24:$J$29,Tables_for_Reference!$I$24:$I$29),IF(ESG!E260="W",_xlfn.XLOOKUP(ESG!G260,Tables_for_Reference!$J$24:$J$29,Tables_for_Reference!$H$24:$H$29),"Error")) -> #VALUE!
A261: G | B261: Compliance | C261: ESG Assurance Provider | D261: Yes | E261: SW | G261: 2024 | H261: =D261/IF(E261="S",_xlfn.XLOOKUP($G261,Tables_for_Reference!$J$15:$J$21,Tables_for_Reference!$I$15:$I$21),IF(ESG!$E261="W",_xlfn.XLOOKUP(ESG!$G261,Tables_for_Reference!$J$15:$J$21,Tables_for_Reference!$H$15:$H$21),"Error")) -> #VALUE! | I261: =$D261/IF($E261="S",_xlfn.XLOOKUP($G261,Tables_for_Reference!$J$24:$J$29,Tables_for_Reference!$I$24:$I$29),IF(ESG!E261="W",_xlfn.XLOOKUP(ESG!G261,Tables_for_Reference!$J$24:$J$29,Tables_for_Reference!$H$24:$H$29),"Error")) -> #VALUE!
A262: G | B262: Compliance | C262: ESG Assurance Provider | D262: Yes | E262: W | G262: 2023 | H262: =D262/IF(E262="S",_xlfn.XLOOKUP($G262,Tables_for_Reference!$J$15:$J$21,Tables_for_Reference!$I$15:$I$21),IF(ESG!$E262="W",_xlfn.XLOOKUP(ESG!$G262,Tables_for_Reference!$J$15:$J$21,Tables_for_Reference!$H$15:$H$21),"Error")) -> #VALUE! | I262: =$D262/IF($E262="S",_xlfn.XLOOKUP($G262,Tables_for_Reference!$J$24:$J$29,Tables_for_Reference!$I$24:$I$29),IF(ESG!E262="W",_xlfn.XLOOKUP(ESG!G262,Tables_for_Reference!$J$24:$J$29,Tables_for_Reference!$H$24:$H$29),"Error")) -> #VALUE!
A263: G | B263: Compliance | C263: ESG Assurance Provider | D263: Yes | E263: S | G263: 2023 | H263: =D263/IF(E263="S",_xlfn.XLOOKUP($G263,Tables_for_Reference!$J$15:$J$21,Tables_for_Reference!$I$15:$I$21),IF(ESG!$E263="W",_xlfn.XLOOKUP(ESG!$G263,Tables_for_Reference!$J$15:$J$21,Tables_for_Reference!$H$15:$H$21),"Error")) -> #VALUE! | I263: =$D263/IF($E263="S",_xlfn.XLOOKUP($G263,Tables_for_Reference!$J$24:$J$29,Tables_for_Reference!$I$24:$I$29),IF(ESG!E263="W",_xlfn.XLOOKUP(ESG!G263,Tables_for_Reference!$J$24:$J$29,Tables_for_Reference!$H$24:$H$29),"Error")) -> #VALUE!
A264: G | B264: Compliance | C264: ESG Assurance Provider | D264: Yes | E264: W | G264: 2022 | H264: =D264/IF(E264="S",_xlfn.XLOOKUP($G264,Tables_for_Reference!$J$15:$J$21,Tables_for_Reference!$I$15:$I$21),IF(ESG!$E264="W",_xlfn.XLOOKUP(ESG!$G264,Tables_for_Reference!$J$15:$J$21,Tables_for_Reference!$H$15:$H$21),"Error")) -> #VALUE! | I264: =$D264/IF($E264="S",_xlfn.XLOOKUP($G264,Tables_for_Reference!$J$24:$J$29,Tables_for_Reference!$I$24:$I$29),IF(ESG!E264="W",_xlfn.XLOOKUP(ESG!G264,Tables_for_Reference!$J$24:$J$29,Tables_for_Reference!$H$24:$H$29),"Error")) -> #VALUE!
A265: G | B265: Compliance | C265: ESG Assurance Provider | D265: Yes | E265: S | G265: 2022 | H265: =D265/IF(E265="S",_xlfn.XLOOKUP($G265,Tables_for_Reference!$J$15:$J$21,Tables_for_Reference!$I$15:$I$21),IF(ESG!$E265="W",_xlfn.XLOOKUP(ESG!$G265,Tables_for_Reference!$J$15:$J$21,Tables_for_Reference!$H$15:$H$21),"Error")) -> #VALUE! | I265: =$D265/IF($E265="S",_xlfn.XLOOKUP($G265,Tables_for_Reference!$J$24:$J$29,Tables_for_Reference!$I$24:$I$29),IF(ESG!E265="W",_xlfn.XLOOKUP(ESG!G265,Tables_for_Reference!$J$24:$J$29,Tables_for_Reference!$H$24:$H$29),"Error")) -> #VALUE!
A266: G | B266: Compliance | C266: ESG Assurance Provider | D266: Yes | E266: W | G266: 2021 | H266: =D266/IF(E266="S",_xlfn.XLOOKUP($G266,Tables_for_Reference!$J$15:$J$21,Tables_for_Reference!$I$15:$I$21),IF(ESG!$E266="W",_xlfn.XLOOKUP(ESG!$G266,Tables_for_Reference!$J$15:$J$21,Tables_for_Reference!$H$15:$H$21),"Error")) -> #VALUE! | I266: =$D266/IF($E266="S",_xlfn.XLOOKUP($G266,Tables_for_Reference!$J$24:$J$29,Tables_for_Reference!$I$24:$I$29),IF(ESG!E266="W",_xlfn.XLOOKUP(ESG!G266,Tables_for_Reference!$J$24:$J$29,Tables_for_Reference!$H$24:$H$29),"Error")) -> #VALUE!
A267: G | B267: Compliance | C267: ESG Assurance Provider | D267: Yes | E267: S | G267: 2021 | H267: =D267/IF(E267="S",_xlfn.XLOOKUP($G267,Tables_for_Reference!$J$15:$J$21,Tables_for_Reference!$I$15:$I$21),IF(ESG!$E267="W",_xlfn.XLOOKUP(ESG!$G267,Tables_for_Reference!$J$15:$J$21,Tables_for_Reference!$H$15:$H$21),"Error")) -> #VALUE! | I267: =$D267/IF($E267="S",_xlfn.XLOOKUP($G267,Tables_for_Reference!$J$24:$J$29,Tables_for_Reference!$I$24:$I$29),IF(ESG!E267="W",_xlfn.XLOOKUP(ESG!G267,Tables_for_Reference!$J$24:$J$29,Tables_for_Reference!$H$24:$H$29),"Error")) -> #VALUE!
A268: G | B268: Compliance | C268: ESG Assurance Provider | D268: Yes | E268: W | G268: 2020 | H268: =D268/IF(E268="S",_xlfn.XLOOKUP($G268,Tables_for_Reference!$J$15:$J$21,Tables_for_Reference!$I$15:$I$21),IF(ESG!$E268="W",_xlfn.XLOOKUP(ESG!$G268,Tables_for_Reference!$J$15:$J$21,Tables_for_Reference!$H$15:$H$21),"Error")) -> #VALUE! | I268: =$D268/IF($E268="S",_xlfn.XLOOKUP($G268,Tables_for_Reference!$J$24:$J$29,Tables_for_Reference!$I$24:$I$29),IF(ESG!E268="W",_xlfn.XLOOKUP(ESG!G268,Tables_for_Reference!$J$24:$J$29,Tables_for_Reference!$H$24:$H$29),"Error")) -> #VALUE!
A269: G | B269: Compliance | C269: ESG Assurance Provider | D269: Yes | E269: S | G269: 2020 | H269: =D269/IF(E269="S",_xlfn.XLOOKUP($G269,Tables_for_Reference!$J$15:$J$21,Tables_for_Reference!$I$15:$I$21),IF(ESG!$E269="W",_xlfn.XLOOKUP(ESG!$G269,Tables_for_Reference!$J$15:$J$21,Tables_for_Reference!$H$15:$H$21),"Error")) -> #VALUE! | I269: =$D269/IF($E269="S",_xlfn.XLOOKUP($G269,Tables_for_Reference!$J$24:$J$29,Tables_for_Reference!$I$24:$I$29),IF(ESG!E269="W",_xlfn.XLOOKUP(ESG!G269,Tables_for_Reference!$J$24:$J$29,Tables_for_Reference!$H$24:$H$29),"Error")) -> #VALUE!
A270: G | B270: Compliance | C270: ESG Assurance Provider | D270: Yes | E270: W | G270: 2019 | H270: =D270/IF(E270="S",_xlfn.XLOOKUP($G270,Tables_for_Reference!$J$15:$J$21,Tables_for_Reference!$I$15:$I$21),IF(ESG!$E270="W",_xlfn.XLOOKUP(ESG!$G270,Tables_for_Reference!$J$15:$J$21,Tables_for_Reference!$H$15:$H$21),"Error")) -> #VALUE! | I270: =$D270/IF($E270="S",_xlfn.XLOOKUP($G270,Tables_for_Reference!$J$24:$J$29,Tables_for_Reference!$I$24:$I$29),IF(ESG!E270="W",_xlfn.XLOOKUP(ESG!G270,Tables_for_Reference!$J$24:$J$29,Tables_for_Reference!$H$24:$H$29),"Error")) -> #VALUE!
A271: G | B271: Compliance | C271: ESG Assurance Provider | D271: Yes | E271: S | G271: 2019 | H271: =D271/IF(E271="S",_xlfn.XLOOKUP($G271,Tables_for_Reference!$J$15:$J$21,Tables_for_Reference!$I$15:$I$21),IF(ESG!$E271="W",_xlfn.XLOOKUP(ESG!$G271,Tables_for_Reference!$J$15:$J$21,Tables_for_Reference!$H$15:$H$21),"Error")) -> #VALUE! | I271: =$D271/IF($E271="S",_xlfn.XLOOKUP($G271,Tables_for_Reference!$J$24:$J$29,Tables_for_Reference!$I$24:$I$29),IF(ESG!E271="W",_xlfn.XLOOKUP(ESG!G271,Tables_for_Reference!$J$24:$J$29,Tables_for_Reference!$H$24:$H$29),"Error")) -> #VALUE!
A272: G | B272: Board | C272: Women on Board | D272: 0.43 | E272: SW | F272: % | G272: 2024 | H272: =D272/IF(E272="S",_xlfn.XLOOKUP($G272,Tables_for_Reference!$J$15:$J$21,Tables_for_Reference!$I$15:$I$21),IF(ESG!$E272="W",_xlfn.XLOOKUP(ESG!$G272,Tables_for_Reference!$J$15:$J$21,Tables_for_Reference!$H$15:$H$21),"Error")) -> #VALUE! | I272: =$D272/IF($E272="S",_xlfn.XLOOKUP($G272,Tables_for_Reference!$J$24:$J$29,Tables_for_Reference!$I$24:$I$29),IF(ESG!E272="W",_xlfn.XLOOKUP(ESG!G272,Tables_for_Reference!$J$24:$J$29,Tables_for_Reference!$H$24:$H$29),"Error")) -> #VALUE!
A273: G | B273: Board | C273: Board Average Age | D273: 63.5 | E273: SW | F273: Years | G273: 2024 | H273: =D273/IF(E273="S",_xlfn.XLOOKUP($G273,Tables_for_Reference!$J$15:$J$21,Tables_for_Reference!$I$15:$I$21),IF(ESG!$E273="W",_xlfn.XLOOKUP(ESG!$G273,Tables_for_Reference!$J$15:$J$21,Tables_for_Reference!$H$15:$H$21),"Error")) -> #VALUE! | I273: =$D273/IF($E273="S",_xlfn.XLOOKUP($G273,Tables_for_Reference!$J$24:$J$29,Tables_for_Reference!$I$24:$I$29),IF(ESG!E273="W",_xlfn.XLOOKUP(ESG!G273,Tables_for_Reference!$J$24:$J$29,Tables_for_Reference!$H$24:$H$29),"Error")) -> #VALUE!
A274: P | B274: Production | C274: Paper Production | D274: 6954000 | E274: S | F274: Tons | G274: 2019 | H274: =D274/IF(E274="S",_xlfn.XLOOKUP($G274,Tables_for_Reference!$J$15:$J$21,Tables_for_Reference!$I$15:$I$21),IF(ESG!$E274="W",_xlfn.XLOOKUP(ESG!$G274,Tables_for_Reference!$J$15:$J$21,Tables_for_Reference!$H$15:$H$21),"Error")) -> 768.56764 | I274: =$D274/IF($E274="S",_xlfn.XLOOKUP($G274,Tables_for_Reference!$J$24:$J$29,Tables_for_Reference!$I$24:$I$29),IF(ESG!E274="W",_xlfn.XLOOKUP(ESG!G274,Tables_for_Reference!$J$24:$J$29,Tables_for_Reference!$H$24:$H$29),"Error")) -> 847.57331
A275: P | B275: Production | C275: Paper Production | D275: 15218523 | E275: W | F275: Tons | G275: 2019 | H275: =D275/IF(E275="S",_xlfn.XLOOKUP($G275,Tables_for_Reference!$J$15:$J$21,Tables_for_Reference!$I$15:$I$21),IF(ESG!$E275="W",_xlfn.XLOOKUP(ESG!$G275,Tables_for_Reference!$J$15:$J$21,Tables_for_Reference!$H$15:$H$21),"Error")) -> 832.11346 | I275: =$D275/IF($E275="S",_xlfn.XLOOKUP($G275,Tables_for_Reference!$J$24:$J$29,Tables_for_Reference!$I$24:$I$29),IF(ESG!E275="W",_xlfn.XLOOKUP(ESG!G275,Tables_for_Reference!$J$24:$J$29,Tables_for_Reference!$H$24:$H$29),"Error")) -> 1619.5431
A276: P | B276: Production | C276: Packaging Production | D276: 7396200 | E276: S | F276: Tons | G276: 2019 | H276: =D276/IF(E276="S",_xlfn.XLOOKUP($G276,Tables_for_Reference!$J$15:$J$21,Tables_for_Reference!$I$15:$I$21),IF(ESG!$E276="W",_xlfn.XLOOKUP(ESG!$G276,Tables_for_Reference!$J$15:$J$21,Tables_for_Reference!$H$15:$H$21),"Error")) -> 817.44032 | I276: =$D276/IF($E276="S",_xlfn.XLOOKUP($G276,Tables_for_Reference!$J$24:$J$29,Tables_for_Reference!$I$24:$I$29),IF(ESG!E276="W",_xlfn.XLOOKUP(ESG!G276,Tables_for_Reference!$J$24:$J$29,Tables_for_Reference!$H$24:$H$29),"Error")) -> 901.46991
A277: P | B277: Production | C277: Total Production | D277: 14350200 | E277: S | F277: Tons | G277: 2019 | H277: =D277/IF(E277="S",_xlfn.XLOOKUP($G277,Tables_for_Reference!$J$15:$J$21,Tables_for_Reference!$I$15:$I$21),IF(ESG!$E277="W",_xlfn.XLOOKUP(ESG!$G277,Tables_for_Reference!$J$15:$J$21,Tables_for_Reference!$H$15:$H$21),"Error")) -> 1586.008 | I277: =$D277/IF($E277="S",_xlfn.XLOOKUP($G277,Tables_for_Reference!$J$24:$J$29,Tables_for_Reference!$I$24:$I$29),IF(ESG!E277="W",_xlfn.XLOOKUP(ESG!G277,Tables_for_Reference!$J$24:$J$29,Tables_for_Reference!$H$24:$H$29),"Error")) -> 1749.0432
A278: P | B278: Production | C278: Paper Production | D278: 14463318 | E278: W | F278: Tons | G278: 2020 | H278: =D278/IF(E278="S",_xlfn.XLOOKUP($G278,Tables_for_Reference!$J$15:$J$21,Tables_for_Reference!$I$15:$I$21),IF(ESG!$E278="W",_xlfn.XLOOKUP(ESG!$G278,Tables_for_Reference!$J$15:$J$21,Tables_for_Reference!$H$15:$H$21),"Error")) -> 822.7705 | I278: =$D278/IF($E278="S",_xlfn.XLOOKUP($G278,Tables_for_Reference!$J$24:$J$29,Tables_for_Reference!$I$24:$I$29),IF(ESG!E278="W",_xlfn.XLOOKUP(ESG!G278,Tables_for_Reference!$J$24:$J$29,Tables_for_Reference!$H$24:$H$29),"Error")) -> 1598.8103
A279: P | B279: Production | C279: Paper Production | D279: 7049000 | E279: S | F279: Tons | G279: 2020 | H279: =D279/IF(E279="S",_xlfn.XLOOKUP($G279,Tables_for_Reference!$J$15:$J$21,Tables_for_Reference!$I$15:$I$21),IF(ESG!$E279="W",_xlfn.XLOOKUP(ESG!$G279,Tables_for_Reference!$J$15:$J$21,Tables_for_Reference!$H$15:$H$21),"Error")) -> 826.37749 | I279: =$D279/IF($E279="S",_xlfn.XLOOKUP($G279,Tables_for_Reference!$J$24:$J$29,Tables_for_Reference!$I$24:$I$29),IF(ESG!E279="W",_xlfn.XLOOKUP(ESG!G279,Tables_for_Reference!$J$24:$J$29,Tables_for_Reference!$H$24:$H$29),"Error")) -> 712.14968
A280: P | B280: Production | C280: Packaging Production | D280: 7461140 | E280: S | F280: Tons | G280: 2020 | H280: =D280/IF(E280="S",_xlfn.XLOOKUP($G280,Tables_for_Reference!$J$15:$J$21,Tables_for_Reference!$I$15:$I$21),IF(ESG!$E280="W",_xlfn.XLOOKUP(ESG!$G280,Tables_for_Reference!$J$15:$J$21,Tables_for_Reference!$H$15:$H$21),"Error")) -> 874.69402 | I280: =$D280/IF($E280="S",_xlfn.XLOOKUP($G280,Tables_for_Reference!$J$24:$J$29,Tables_for_Reference!$I$24:$I$29),IF(ESG!E280="W",_xlfn.XLOOKUP(ESG!G280,Tables_for_Reference!$J$24:$J$29,Tables_for_Reference!$H$24:$H$29),"Error")) -> 753.78756
A281: P | B281: Production | C281: Total Production | D281: 14510140 | E281: S | F281: Tons | G281: 2020 | H281: =D281/IF(E281="S",_xlfn.XLOOKUP($G281,Tables_for_Reference!$J$15:$J$21,Tables_for_Reference!$I$15:$I$21),IF(ESG!$E281="W",_xlfn.XLOOKUP(ESG!$G281,Tables_for_Reference!$J$15:$J$21,Tables_for_Reference!$H$15:$H$21),"Error")) -> 1701.0715 | I281: =$D281/IF($E281="S",_xlfn.XLOOKUP($G281,Tables_for_Reference!$J$24:$J$29,Tables_for_Reference!$I$24:$I$29),IF(ESG!E281="W",_xlfn.XLOOKUP(ESG!G281,Tables_for_Reference!$J$24:$J$29,Tables_for_Reference!$H$24:$H$29),"Error")) -> 1465.9372
A282: P | B282: Production | C282: Paper Production | D282: 14776992 | E282: W | F282: Tons | G282: 2021 | H282: =D282/IF(E282="S",_xlfn.XLOOKUP($G282,Tables_for_Reference!$J$15:$J$21,Tables_for_Reference!$I$15:$I$21),IF(ESG!$E282="W",_xlfn.XLOOKUP(ESG!$G282,Tables_for_Reference!$J$15:$J$21,Tables_for_Reference!$H$15:$H$21),"Error")) -> 788.2702 | I282: =$D282/IF($E282="S",_xlfn.XLOOKUP($G282,Tables_for_Reference!$J$24:$J$29,Tables_for_Reference!$I$24:$I$29),IF(ESG!E282="W",_xlfn.XLOOKUP(ESG!G282,Tables_for_Reference!$J$24:$J$29,Tables_for_Reference!$H$24:$H$29),"Error")) -> 1119.0452
A283: P | B283: Production | C283: Paper Production | D283: 7282000 | E283: S | F283: Tons | G283: 2021 | H283: =D283/IF(E283="S",_xlfn.XLOOKUP($G283,Tables_for_Reference!$J$15:$J$21,Tables_for_Reference!$I$15:$I$21),IF(ESG!$E283="W",_xlfn.XLOOKUP(ESG!$G283,Tables_for_Reference!$J$15:$J$21,Tables_for_Reference!$H$15:$H$21),"Error")) -> 720.49075 | I283: =$D283/IF($E283="S",_xlfn.XLOOKUP($G283,Tables_for_Reference!$J$24:$J$29,Tables_for_Reference!$I$24:$I$29),IF(ESG!E283="W",_xlfn.XLOOKUP(ESG!G283,Tables_for_Reference!$J$24:$J$29,Tables_for_Reference!$H$24:$H$29),"Error")) -> 582.90975
... A294: P | B294: Production | C294: Paper Production | D294: 13021711 | E294: W | F294: Tons | G294: 2024 | H294: =D294/IF(E294="S",_xlfn.XLOOKUP($G294,Tables_for_Reference!$J$15:$J$21,Tables_for_Reference!$I$15:$I$21),IF(ESG!$E294="W",_xlfn.XLOOKUP(ESG!$G294,Tables_for_Reference!$J$15:$J$21,Tables_for_Reference!$H$15:$H$21),"Error")) -> 959.24622 | I294: =$D294/IF($E294="S",_xlfn.XLOOKUP($G294,Tables_for_Reference!$J$24:$J$29,Tables_for_Reference!$I$24:$I$29),IF(ESG!E294="W",_xlfn.XLOOKUP(ESG!G294,Tables_for_Reference!$J$24:$J$29,Tables_for_Reference!$H$24:$H$29),"Error")) -> 938.77176
A295: P | B295: Production | C295: Paper Production | D295: =5994000+1600000 -> 7594000 | E295: S | F295: Tons | G295: 2024 | H295: =D295/IF(E295="S",_xlfn.XLOOKUP($G295,Tables_for_Reference!$J$15:$J$21,Tables_for_Reference!$I$15:$I$21),IF(ESG!$E295="W",_xlfn.XLOOKUP(ESG!$G295,Tables_for_Reference!$J$15:$J$21,Tables_for_Reference!$H$15:$H$21),"Error")) -> 1007.956 | I295: =$D295/IF($E295="S",_xlfn.XLOOKUP($G295,Tables_for_Reference!$J$24:$J$29,Tables_for_Reference!$I$24:$I$29),IF(ESG!E295="W",_xlfn.XLOOKUP(ESG!G295,Tables_for_Reference!$J$24:$J$29,Tables_for_Reference!$H$24:$H$29),"Error")) -> 536.29597
A296: P | B296: Production | C296: Packaging Production | D296: 7324000 | E296: S | F296: Tons | G296: 2024 | H296: =D296/IF(E296="S",_xlfn.XLOOKUP($G296,Tables_for_Reference!$J$15:$J$21,Tables_for_Reference!$I$15:$I$21),IF(ESG!$E296="W",_xlfn.XLOOKUP(ESG!$G296,Tables_for_Reference!$J$15:$J$21,Tables_for_Reference!$H$15:$H$21),"Error")) -> 972.11876 | I296: =$D296/IF($E296="S",_xlfn.XLOOKUP($G296,Tables_for_Reference!$J$24:$J$29,Tables_for_Reference!$I$24:$I$29),IF(ESG!E296="W",_xlfn.XLOOKUP(ESG!G296,Tables_for_Reference!$J$24:$J$29,Tables_for_Reference!$H$24:$H$29),"Error")) -> 517.22829
A297: P | B297: Production | C297: Total Production | D297: 14918000 | E297: S | F297: Tons | G297: 2024 | H297: =D297/IF(E297="S",_xlfn.XLOOKUP($G297,Tables_for_Reference!$J$15:$J$21,Tables_for_Reference!$I$15:$I$21),IF(ESG!$E297="W",_xlfn.XLOOKUP(ESG!$G297,Tables_for_Reference!$J$15:$J$21,Tables_for_Reference!$H$15:$H$21),"Error")) -> 1980.0748 | I297: =$D297/IF($E297="S",_xlfn.XLOOKUP($G297,Tables_for_Reference!$J$24:$J$29,Tables_for_Reference!$I$24:$I$29),IF(ESG!E297="W",_xlfn.XLOOKUP(ESG!G297,Tables_for_Reference!$J$24:$J$29,Tables_for_Reference!$H$24:$H$29),"Error")) -> 1053.5243
A298: P | B298: Performance | C298: Annual Revenue | D298: 31179 | E298: SW | F298: USD Millions | G298: 2025 | H298: =D298/IF(E298="S",_xlfn.XLOOKUP($G298,Tables_for_Reference!$J$15:$J$21,Tables_for_Reference!$I$15:$I$21),IF(ESG!$E298="W",_xlfn.XLOOKUP(ESG!$G298,Tables_for_Reference!$J$15:$J$21,Tables_for_Reference!$H$15:$H$21),"Error")) -> #VALUE! | I298: =$D298/IF($E298="S",_xlfn.XLOOKUP($G298,Tables_for_Reference!$J$24:$J$29,Tables_for_Reference!$I$24:$I$29),IF(ESG!E298="W",_xlfn.XLOOKUP(ESG!G298,Tables_for_Reference!$J$24:$J$29,Tables_for_Reference!$H$24:$H$29),"Error")) -> #VALUE!
A299: P | B299: Performance | C299: Annual Revenue | D299: 21109 | E299: SW | F299: USD Millions | G299: 2024 | H299: =D299/IF(E299="S",_xlfn.XLOOKUP($G299,Tables_for_Reference!$J$15:$J$21,Tables_for_Reference!$I$15:$I$21),IF(ESG!$E299="W",_xlfn.XLOOKUP(ESG!$G299,Tables_for_Reference!$J$15:$J$21,Tables_for_Reference!$H$15:$H$21),"Error")) -> #VALUE! | I299: =$D299/IF($E299="S",_xlfn.XLOOKUP($G299,Tables_for_Reference!$J$24:$J$29,Tables_for_Reference!$I$24:$I$29),IF(ESG!E299="W",_xlfn.XLOOKUP(ESG!G299,Tables_for_Reference!$J$24:$J$29,Tables_for_Reference!$H$24:$H$29),"Error")) -> #VALUE!
A300: P | B300: Performance | C300: Annual Revenue | D300: 20310 | E300: W | F300: USD Millions | G300: 2023 | H300: =D300/IF(E300="S",_xlfn.XLOOKUP($G300,Tables_for_Reference!$J$15:$J$21,Tables_for_Reference!$I$15:$I$21),IF(ESG!$E300="W",_xlfn.XLOOKUP(ESG!$G300,Tables_for_Reference!$J$15:$J$21,Tables_for_Reference!$H$15:$H$21),"Error")) -> 1 | I300: =$D300/IF($E300="S",_xlfn.XLOOKUP($G300,Tables_for_Reference!$J$24:$J$29,Tables_for_Reference!$I$24:$I$29),IF(ESG!E300="W",_xlfn.XLOOKUP(ESG!G300,Tables_for_Reference!$J$24:$J$29,Tables_for_Reference!$H$24:$H$29),"Error")) -> 2.2126352
A301: P | B301: Performance | C301: Annual Revenue | D301: 11272 | E301: S | F301: USD Millions | G301: 2023 | H301: =D301/IF(E301="S",_xlfn.XLOOKUP($G301,Tables_for_Reference!$J$15:$J$21,Tables_for_Reference!$I$15:$I$21),IF(ESG!$E301="W",_xlfn.XLOOKUP(ESG!$G301,Tables_for_Reference!$J$15:$J$21,Tables_for_Reference!$H$15:$H$21),"Error")) -> 1 | I301: =$D301/IF($E301="S",_xlfn.XLOOKUP($G301,Tables_for_Reference!$J$24:$J$29,Tables_for_Reference!$I$24:$I$29),IF(ESG!E301="W",_xlfn.XLOOKUP(ESG!G301,Tables_for_Reference!$J$24:$J$29,Tables_for_Reference!$H$24:$H$29),"Error")) -> 1.2029369
A302: P | B302: Performance | C302: Annual Revenue | D302: 21256.5 | E302: W | F302: USD Millions | G302: 2022 | H302: =D302/IF(E302="S",_xlfn.XLOOKUP($G302,Tables_for_Reference!$J$15:$J$21,Tables_for_Reference!$I$15:$I$21),IF(ESG!$E302="W",_xlfn.XLOOKUP(ESG!$G302,Tables_for_Reference!$J$15:$J$21,Tables_for_Reference!$H$15:$H$21),"Error")) -> 1 | I302: =$D302/IF($E302="S",_xlfn.XLOOKUP($G302,Tables_for_Reference!$J$24:$J$29,Tables_for_Reference!$I$24:$I$29),IF(ESG!E302="W",_xlfn.XLOOKUP(ESG!G302,Tables_for_Reference!$J$24:$J$29,Tables_for_Reference!$H$24:$H$29),"Error")) -> 2.7049399
A303: P | B303: Performance | C303: Annual Revenue | D303: 12815 | E303: S | F303: USD Millions | G303: 2022 | H303: =D303/IF(E303="S",_xlfn.XLOOKUP($G303,Tables_for_Reference!$J$15:$J$21,Tables_for_Reference!$I$15:$I$21),IF(ESG!$E303="W",_xlfn.XLOOKUP(ESG!$G303,Tables_for_Reference!$J$15:$J$21,Tables_for_Reference!$H$15:$H$21),"Error")) -> 1 | I303: =$D303/IF($E303="S",_xlfn.XLOOKUP($G303,Tables_for_Reference!$J$24:$J$29,Tables_for_Reference!$I$24:$I$29),IF(ESG!E303="W",_xlfn.XLOOKUP(ESG!G303,Tables_for_Reference!$J$24:$J$29,Tables_for_Reference!$H$24:$H$29),"Error")) -> 1.426266
A304: P | B304: Performance | C304: Annual Revenue | D304: 18746.1 | E304: W | F304: USD Millions | G304: 2021 | H304: =D304/IF(E304="S",_xlfn.XLOOKUP($G304,Tables_for_Reference!$J$15:$J$21,Tables_for_Reference!$I$15:$I$21),IF(ESG!$E304="W",_xlfn.XLOOKUP(ESG!$G304,Tables_for_Reference!$J$15:$J$21,Tables_for_Reference!$H$15:$H$21),"Error")) -> 1 | I304: =$D304/IF($E304="S",_xlfn.XLOOKUP($G304,Tables_for_Reference!$J$24:$J$29,Tables_for_Reference!$I$24:$I$29),IF(ESG!E304="W",_xlfn.XLOOKUP(ESG!G304,Tables_for_Reference!$J$24:$J$29,Tables_for_Reference!$H$24:$H$29),"Error")) -> 1.4196214
A305: P | B305: Performance | C305: Annual Revenue | D305: 10107 | E305: S | F305: USD Millions | G305: 2021 | H305: =D305/IF(E305="S",_xlfn.XLOOKUP($G305,Tables_for_Reference!$J$15:$J$21,Tables_for_Reference!$I$15:$I$21),IF(ESG!$E305="W",_xlfn.XLOOKUP(ESG!$G305,Tables_for_Reference!$J$15:$J$21,Tables_for_Reference!$H$15:$H$21),"Error")) -> 1 | I305: =$D305/IF($E305="S",_xlfn.XLOOKUP($G305,Tables_for_Reference!$J$24:$J$29,Tables_for_Reference!$I$24:$I$29),IF(ESG!E305="W",_xlfn.XLOOKUP(ESG!G305,Tables_for_Reference!$J$24:$J$29,Tables_for_Reference!$H$24:$H$29),"Error")) -> 0.80904543
A306: P | B306: Performance | C306: Annual Revenue | D306: 17578.8 | E306: W | F306: USD Millions | G306: 2020 | H306: =D306/IF(E306="S",_xlfn.XLOOKUP($G306,Tables_for_Reference!$J$15:$J$21,Tables_for_Reference!$I$15:$I$21),IF(ESG!$E306="W",_xlfn.XLOOKUP(ESG!$G306,Tables_for_Reference!$J$15:$J$21,Tables_for_Reference!$H$15:$H$21),"Error")) -> 1 | I306: =$D306/IF($E306="S",_xlfn.XLOOKUP($G306,Tables_for_Reference!$J$24:$J$29,Tables_for_Reference!$I$24:$I$29),IF(ESG!E306="W",_xlfn.XLOOKUP(ESG!G306,Tables_for_Reference!$J$24:$J$29,Tables_for_Reference!$H$24:$H$29),"Error")) -> 1.9432033
A307: P | B307: Performance | C307: Annual Revenue | D307: 8530 | E307: S | F307: USD Millions | G307: 2020 | H307: =D307/IF(E307="S",_xlfn.XLOOKUP($G307,Tables_for_Reference!$J$15:$J$21,Tables_for_Reference!$I$15:$I$21),IF(ESG!$E307="W",_xlfn.XLOOKUP(ESG!$G307,Tables_for_Reference!$J$15:$J$21,Tables_for_Reference!$H$15:$H$21),"Error")) -> 1 | I307: =$D307/IF($E307="S",_xlfn.XLOOKUP($G307,Tables_for_Reference!$J$24:$J$29,Tables_for_Reference!$I$24:$I$29),IF(ESG!E307="W",_xlfn.XLOOKUP(ESG!G307,Tables_for_Reference!$J$24:$J$29,Tables_for_Reference!$H$24:$H$29),"Error")) -> 0.86177285
... A342: F | B342: Performance | C342: EBITDA Margin | D342: 0.177 | E342: S | F342: % | G342: 2019 | H342: =D342/IF(E342="S",_xlfn.XLOOKUP($G342,Tables_for_Reference!$J$15:$J$21,Tables_for_Reference!$I$15:$I$21),IF(ESG!$E342="W",_xlfn.XLOOKUP(ESG!$G342,Tables_for_Reference!$J$15:$J$21,Tables_for_Reference!$H$15:$H$21),"Error")) -> 1.9562334e-05 | I342: =$D342/IF($E342="S",_xlfn.XLOOKUP($G342,Tables_for_Reference!$J$24:$J$29,Tables_for_Reference!$I$24:$I$29),IF(ESG!E342="W",_xlfn.XLOOKUP(ESG!G342,Tables_for_Reference!$J$24:$J$29,Tables_for_Reference!$H$24:$H$29),"Error")) -> 2.1573264e-05

Sheet E Data_Inventory
A1: ESG DATA INVENTORY & QUALITY SCORING
A2: Company: Smurfit Westrock | D2: Industry: Paper & Packaging | E2: Reporting Year: 2024 | L2: 25=Assured / 15=Self-rep / 5=Est. | M2: 25=Full method / 15=Value only / 0=None | N2: 25=Current yr / 20=1yr old / 5=3+yr | O2: 25=Match / 15=<5% var / 0=No 2nd source | P2: SUM of K+L+M+N | Q2: Auto-calculated
A3: # | B3: Pillar (E/S/G/Financial) | C3: KPI Category | D3: KPI Name | E3: Value (Enter number) | F3: Buisness | G3: Unit | H3: Reporting Year | I3: Source Type | J3: Source URL / Citation | K3: Assurance Level | L3: Accuracy Score (0–25) | M3: Completeness Score (0–25) | N3: Timeliness Score (0–25) | O3: Consistency Score (0–25) | P3: TOTAL Quality Score (0–100) | Q3: Quality Grade | R3: Notes / Caveats
B4: E | C4: Energy | D4: Total Renewable Energy Consumption | E4: 5 | F4: S | G4: GWh | H4: 2019 | I4: Company ESG Report | J4: Smurfit Kappa 2019 Sustainability Report | L4: 25 | M4: 15 | N4: 5 | O4: 15 | P4: =L4+M4+N4+O4 -> 60 | Q4: =IF(P4>=80,"✅ High Quality",IF(P4>=60,"🟡 Acceptable",IF(P4>=40,"⚠️ Use with Caution","🔴 Insufficient"))) -> 🟡 Acceptable
B5: E | C5: Energy | D5: Total Renewable Energy Consumption | E5: 6 | F5: S | G5: GWh | H5: 2021 | I5: Company ESG Report | J5: Smurfit Kappa 2021 Sustainability Report | L5: 25 | M5: 15 | N5: 5 | O5: 15 | P5: =L5+M5+N5+O5 -> 60 | Q5: =IF(P5>=80,"✅ High Quality",IF(P5>=60,"🟡 Acceptable",IF(P5>=40,"⚠️ Use with Caution","🔴 Insufficient"))) -> 🟡 Acceptable
B6: E | C6: Energy | D6: Total Renewable Energy Consumption | E6: 6 | F6: S | G6: GWh | H6: 2020 | I6: Company ESG Report | J6: Smurfit Kappa 2021 Sustainability Report | L6: 25 | M6: 15 | N6: 5 | O6: 15 | P6: =L6+M6+N6+O6 -> 60 | Q6: =IF(P6>=80,"✅ High Quality",IF(P6>=60,"🟡 Acceptable",IF(P6>=40,"⚠️ Use with Caution","🔴 Insufficient"))) -> 🟡 Acceptable
B7: E | C7: Energy | D7: Total Renewable Energy Consumption | E7: 8 | F7: S | G7: GWh | H7: 2022 | I7: Company ESG Report | J7: Smurfit Kappa 2022 Sustainability Report | L7: 25 | M7: 15 | N7: 20 | O7: 15 | P7: =L7+M7+N7+O7 -> 75 | Q7: =IF(P7>=80,"✅ High Quality",IF(P7>=60,"🟡 Acceptable",IF(P7>=40,"⚠️ Use with Caution","🔴 Insufficient"))) -> 🟡 Acceptable
B8: E | C8: Energy | D8: Total Renewable Energy Consumption | E8: 11 | F8: S | G8: GWh | H8: 2023 | I8: Company ESG Report | J8: Smurfit Kappa 2023 Sustainability Report | L8: 25 | M8: 15 | N8: 25 | O8: 15 | P8: =L8+M8+N8+O8 -> 80 | Q8: =IF(P8>=80,"✅ High Quality",IF(P8>=60,"🟡 Acceptable",IF(P8>=40,"⚠️ Use with Caution","🔴 Insufficient"))) -> ✅ High Quality
B9: E | C9: Energy | D9: Total Renewable Energy Consumption | E9: 22 | F9: S | G9: GWh | H9: 2024 | I9: Company ESG Report | J9: Smurfit Westrock 2024 Sustainability Report | L9: 25 | M9: 15 | N9: 25 | O9: 15 | P9: =L9+M9+N9+O9 -> 80 | Q9: =IF(P9>=80,"✅ High Quality",IF(P9>=60,"🟡 Acceptable",IF(P9>=40,"⚠️ Use with Caution","🔴 Insufficient"))) -> ✅ High Quality
B10: E | C10: Carbon | D10: Scope 2 GHG Emissions (Location-Based) | E10: 467 | F10: S | G10: tCO₂e | H10: 2023 | I10: Company ESG Report | J10: Smurfit Kappa 2023 Sustainability Report | L10: 25 | M10: 15 | N10: 25 | O10: 15 | P10: =L10+M10+N10+O10 -> 80 | Q10: =IF(P10>=80,"✅ High Quality",IF(P10>=60,"🟡 Acceptable",IF(P10>=40,"⚠️ Use with Caution","🔴 Insufficient"))) -> ✅ High Quality
B11: E | C11: Water | D11: Total BOD Discharged | E11: 8389.5455 | F11: W | G11: Metric Tonnes | H11: 2024 | I11: Company ESG Report | J11: Smurfit Westrock 2024 Sustainability Report | L11: 25 | M11: 15 | N11: 25 | O11: 15 | P11: =L11+M11+N11+O11 -> 80 | Q11: =IF(P11>=80,"✅ High Quality",IF(P11>=60,"🟡 Acceptable",IF(P11>=40,"⚠️ Use with Caution","🔴 Insufficient"))) -> ✅ High Quality
B12: E | C12: Waste | D12: Hazardous Waste Generated | E12: 8774 | F12: S | G12: Metric Tonnes | H12: 2021 | I12: Company ESG Report | J12: Smurfit Kappa 2021 Sustainability Report | L12: 25 | M12: 15 | N12: 5 | O12: 15 | P12: =L12+M12+N12+O12 -> 60 | Q12: =IF(P12>=80,"✅ High Quality",IF(P12>=60,"🟡 Acceptable",IF(P12>=40,"⚠️ Use with Caution","🔴 Insufficient"))) -> 🟡 Acceptable
B13: E | C13: Water | D13: Total BOD Discharged | E13: 8875.4545 | F13: W | G13: Metric Tonnes | H13: 2023 | I13: Company ESG Report | J13: Westrock 2023 Sustainability Report | L13: 25 | M13: 15 | N13: 25 | O13: 15 | P13: =L13+M13+N13+O13 -> 80 | Q13: =IF(P13>=80,"✅ High Quality",IF(P13>=60,"🟡 Acceptable",IF(P13>=40,"⚠️ Use with Caution","🔴 Insufficient"))) -> ✅ High Quality
B14: E | C14: Waste | D14: Other Waste | E14: 9002 | F14: S | G14: Metric Tonnes | H14: 2020 | I14: Company ESG Report | J14: Smurfit Kappa 2021 Sustainability Report | L14: 25 | M14: 15 | N14: 5 | O14: 15 | P14: =L14+M14+N14+O14 -> 60 | Q14: =IF(P14>=80,"✅ High Quality",IF(P14>=60,"🟡 Acceptable",IF(P14>=40,"⚠️ Use with Caution","🔴 Insufficient"))) -> 🟡 Acceptable
B15: E | C15: Water | D15: Total BOD Discharged | E15: 9255 | F15: W | G15: Metric Tonnes | H15: 2020 | I15: Company ESG Report | J15: Westrock 2020 GRI Report | L15: 25 | M15: 15 | N15: 5 | O15: 15 | P15: =L15+M15+N15+O15 -> 60 | Q15: =IF(P15>=80,"✅ High Quality",IF(P15>=60,"🟡 Acceptable",IF(P15>=40,"⚠️ Use with Caution","🔴 Insufficient"))) -> 🟡 Acceptable
... B178: E | C178: Water | D178: Total Water Withdrawal | E178: 588952000 | F178: W | G178: m3 | H178: 2020 | I178: Company ESG Report | J178: Westrock 2020 GRI Report | L178: 25 | M178: 15 | N178: 5 | O178: 15 | P178: =L178+M178+N178+O178 -> 60 | Q178: =IF(P178>=80,"✅ High Quality",IF(P178>=60,"🟡 Acceptable",IF(P178>=40,"⚠️ Use with Caution","🔴 Insufficient"))) -> 🟡 Acceptable
B179: E | C179: Water | D179: Water Recycled / Reused (%) | F179: W | G179: % | H179: 2024 | I179: Calculated | L179: 0 | M179: 0 | N179: 0 | O179: 15 | P179: =L179+M179+N179+O179 -> 15 | Q179: =IF(P179>=80,"✅ High Quality",IF(P179>=60,"🟡 Acceptable",IF(P179>=40,"⚠️ Use with Caution","🔴 Insufficient"))) -> 🔴 Insufficient
B180: E | C180: Water | D180: Water Recycled / Reused (%) | F180: S | G180: % | H180: 2024 | I180: Calculated | L180: 0 | M180: 0 | N180: 0 | O180: 15 | P180: =L180+M180+N180+O180 -> 15 | Q180: =IF(P180>=80,"✅ High Quality",IF(P180>=60,"🟡 Acceptable",IF(P180>=40,"⚠️ Use with Caution","🔴 Insufficient"))) -> 🔴 Insufficient
B181: E | C181: Water | D181: Water Recycled / Reused (%) | F181: W | G181: % | H181: 2023 | I181: Calculated | L181: 0 | M181: 0 | N181: 0 | O181: 15 | P181: =L181+M181+N181+O181 -> 15 | Q181: =IF(P181>=80,"✅ High Quality",IF(P181>=60,"🟡 Acceptable",IF(P181>=40,"⚠️ Use with Caution","🔴 Insufficient"))) -> 🔴 Insufficient
B182: E | C182: Water | D182: Water Recycled / Reused (%) | F182: S | G182: % | H182: 2023 | I182: Calculated | L182: 0 | M182: 0 | N182: 0 | O182: 15 | P182: =L182+M182+N182+O182 -> 15 | Q182: =IF(P182>=80,"✅ High Quality",IF(P182>=60,"🟡 Acceptable",IF(P182>=40,"⚠️ Use with Caution","🔴 Insufficient"))) -> 🔴 Insufficient
B183: E | C183: Water | D183: Water Recycled / Reused (%) | F183: W | G183: % | H183: 2022 | I183: Calculated | L183: 0 | M183: 0 | N183: 0 | O183: 15 | P183: =L183+M183+N183+O183 -> 15 | Q183: =IF(P183>=80,"✅ High Quality",IF(P183>=60,"🟡 Acceptable",IF(P183>=40,"⚠️ Use with Caution","🔴 Insufficient"))) -> 🔴 Insufficient
B184: E | C184: Water | D184: Water Recycled / Reused (%) | F184: S | G184: % | H184: 2022 | I184: Calculated | L184: 0 | M184: 0 | N184: 0 | O184: 15 | P184: =L184+M184+N184+O184 -> 15 | Q184: =IF(P184>=80,"✅ High Quality",IF(P184>=60,"🟡 Acceptable",IF(P184>=40,"⚠️ Use with Caution","🔴 Insufficient"))) -> 🔴 Insufficient
B185: E | C185: Water | D185: Water Recycled / Reused (%) | F185: W | G185: % | H185: 2021 | I185: Calculated | L185: 0 | M185: 0 | N185: 0 | O185: 15 | P185: =L185+M185+N185+O185 -> 15 | Q185: =IF(P185>=80,"✅ High Quality",IF(P185>=60,"🟡 Acceptable",IF(P185>=40,"⚠️ Use with Caution","🔴 Insufficient"))) -> 🔴 Insufficient
B186: E | C186: Water | D186: Water Recycled / Reused (%) | F186: S | G186: % | H186: 2021 | I186: Calculated | L186: 0 | M186: 0 | N186: 0 | O186: 15 | P186: =L186+M186+N186+O186 -> 15 | Q186: =IF(P186>=80,"✅ High Quality",IF(P186>=60,"🟡 Acceptable",IF(P186>=40,"⚠️ Use with Caution","🔴 Insufficient"))) -> 🔴 Insufficient
B187: E | C187: Water | D187: Water Recycled / Reused (%) | F187: W | G187: % | H187: 2020 | I187: Calculated | L187: 0 | M187: 0 | N187: 0 | O187: 15 | P187: =L187+M187+N187+O187 -> 15 | Q187: =IF(P187>=80,"✅ High Quality",IF(P187>=60,"🟡 Acceptable",IF(P187>=40,"⚠️ Use with Caution","🔴 Insufficient"))) -> 🔴 Insufficient
B188: E | C188: Water | D188: Water Recycled / Reused (%) | F188: S | G188: % | H188: 2020 | I188: Calculated | L188: 0 | M188: 0 | N188: 0 | O188: 15 | P188: =L188+M188+N188+O188 -> 15 | Q188: =IF(P188>=80,"✅ High Quality",IF(P188>=60,"🟡 Acceptable",IF(P188>=40,"⚠️ Use with Caution","🔴 Insufficient"))) -> 🔴 Insufficient
B189: E | C189: Water | D189: Water Recycled / Reused (%) | F189: W | G189: % | H189: 2019 | I189: Calculated | L189: 0 | M189: 0 | N189: 0 | O189: 15 | P189: =L189+M189+N189+O189 -> 15 | Q189: =IF(P189>=80,"✅ High Quality",IF(P189>=60,"🟡 Acceptable",IF(P189>=40,"⚠️ Use with Caution","🔴 Insufficient"))) -> 🔴 Insufficient
B190: E | C190: Water | D190: Water Recycled / Reused (%) | F190: S | G190: % | H190: 2019 | I190: Calculated | L190: 0 | M190: 0 | N190: 0 | O190: 15 | P190: =L190+M190+N190+O190 -> 15 | Q190: =IF(P190>=80,"✅ High Quality",IF(P190>=60,"🟡 Acceptable",IF(P190>=40,"⚠️ Use with Caution","🔴 Insufficient"))) -> 🔴 Insufficient
... B224: E | C224: Energy | D224: Total Energy Consumption | F224: S | G224: GWh | H224: 2019 | I224: Calculated | L224: 25 | M224: 15 | N224: 0 | O224: 15 | P224: =L224+M224+N224+O224 -> 55 | Q224: =IF(P224>=80,"✅ High Quality",IF(P224>=60,"🟡 Acceptable",IF(P224>=40,"⚠️ Use with Caution","🔴 Insufficient"))) -> ⚠️ Use with Caution
B225: E | C225: Carbon | D225: Scope 2 GHG Emissions (Market-Based) | F225: S | G225: tCO₂e | H225: 2024 | L225: 25 | M225: 10 | N225: 0 | O225: 15 | P225: =L225+M225+N225+O225 -> 50 | Q225: =IF(P225>=80,"✅ High Quality",IF(P225>=60,"🟡 Acceptable",IF(P225>=40,"⚠️ Use with Caution","🔴 Insufficient"))) -> ⚠️ Use with Caution
B226: E | C226: Carbon | D226: Scope 2 GHG Emissions (Market-Based) | F226: S | G226: tCO₂e | H226: 2023 | L226: 25 | M226: 10 | N226: 0 | O226: 15 | P226: =L226+M226+N226+O226 -> 50 | Q226: =IF(P226>=80,"✅ High Quality",IF(P226>=60,"🟡 Acceptable",IF(P226>=40,"⚠️ Use with Caution","🔴 Insufficient"))) -> ⚠️ Use with Caution
B227: E | C227: Carbon | D227: Scope 2 GHG Emissions (Market-Based) | F227: S | G227: tCO₂e | H227: 2022 | L227: 25 | M227: 10 | N227: 0 | O227: 15 | P227: =L227+M227+N227+O227 -> 50 | Q227: =IF(P227>=80,"✅ High Quality",IF(P227>=60,"🟡 Acceptable",IF(P227>=40,"⚠️ Use with Caution","🔴 Insufficient"))) -> ⚠️ Use with Caution
B228: E | C228: Carbon | D228: Scope 2 GHG Emissions (Market-Based) | F228: S | G228: tCO₂e | H228: 2021 | L228: 25 | M228: 10 | N228: 0 | O228: 15 | P228: =L228+M228+N228+O228 -> 50 | Q228: =IF(P228>=80,"✅ High Quality",IF(P228>=60,"🟡 Acceptable",IF(P228>=40,"⚠️ Use with Caution","🔴 Insufficient"))) -> ⚠️ Use with Caution
B229: E | C229: Carbon | D229: Scope 2 GHG Emissions (Market-Based) | F229: S | G229: tCO₂e | H229: 2020 | L229: 25 | M229: 10 | N229: 0 | O229: 15 | P229: =L229+M229+N229+O229 -> 50 | Q229: =IF(P229>=80,"✅ High Quality",IF(P229>=60,"🟡 Acceptable",IF(P229>=40,"⚠️ Use with Caution","🔴 Insufficient"))) -> ⚠️ Use with Caution
B230: E | C230: Carbon | D230: Scope 2 GHG Emissions (Market-Based) | F230: S | G230: tCO₂e | H230: 2019 | L230: 25 | M230: 10 | N230: 0 | O230: 15 | P230: =L230+M230+N230+O230 -> 50 | Q230: =IF(P230>=80,"✅ High Quality",IF(P230>=60,"🟡 Acceptable",IF(P230>=40,"⚠️ Use with Caution","🔴 Insufficient"))) -> ⚠️ Use with Caution
B231: E | C231: Carbon | D231: Scope 3 GHG Emissions (Total) | F231: W | G231: tCO₂e | H231: 2024 | L231: 25 | M231: 10 | N231: 0 | O231: 15 | P231: =L231+M231+N231+O231 -> 50 | Q231: =IF(P231>=80,"✅ High Quality",IF(P231>=60,"🟡 Acceptable",IF(P231>=40,"⚠️ Use with Caution","🔴 Insufficient"))) -> ⚠️ Use with Caution
B232: E | C232: Carbon | D232: Scope 3 GHG Emissions (Total) | F232: S | G232: tCO₂e | H232: 2024 | L232: 25 | M232: 10 | N232: 0 | O232: 15 | P232: =L232+M232+N232+O232 -> 50 | Q232: =IF(P232>=80,"✅ High Quality",IF(P232>=60,"🟡 Acceptable",IF(P232>=40,"⚠️ Use with Caution","🔴 Insufficient"))) -> ⚠️ Use with Caution
B233: E | C233: Carbon | D233: Scope 3 GHG Emissions (Total) | F233: S | G233: tCO₂e | H233: 2023 | L233: 25 | M233: 10 | N233: 0 | O233: 15 | P233: =L233+M233+N233+O233 -> 50 | Q233: =IF(P233>=80,"✅ High Quality",IF(P233>=60,"🟡 Acceptable",IF(P233>=40,"⚠️ Use with Caution","🔴 Insufficient"))) -> ⚠️ Use with Caution
B234: E | C234: Carbon | D234: Scope 3 GHG Emissions (Total) | F234: W | G234: tCO₂e | H234: 2022 | L234: 25 | M234: 10 | N234: 0 | O234: 15 | P234: =L234+M234+N234+O234 -> 50 | Q234: =IF(P234>=80,"✅ High Quality",IF(P234>=60,"🟡 Acceptable",IF(P234>=40,"⚠️ Use with Caution","🔴 Insufficient"))) -> ⚠️ Use with Caution
B235: E | C235: Carbon | D235: Scope 3 GHG Emissions (Total) | F235: S | G235: tCO₂e | H235: 2022 | L235: 25 | M235: 10 | N235: 0 | O235: 15 | P235: =L235+M235+N235+O235 -> 50 | Q235: =IF(P235>=80,"✅ High Quality",IF(P235>=60,"🟡 Acceptable",IF(P235>=40,"⚠️ Use with Caution","🔴 Insufficient"))) -> ⚠️ Use with Caution
B236: E | C236: Carbon | D236: Scope 3 GHG Emissions (Total) | F236: W | G236: tCO₂e | H236: 2021 | L236: 25 | M236: 10 | N236: 0 | O236: 15 | P236: =L236+M236+N236+O236 -> 50 | Q236: =IF(P236>=80,"✅ High Quality",IF(P236>=60,"🟡 Acceptable",IF(P236>=40,"⚠️ Use with Caution","🔴 Insufficient"))) -> ⚠️ Use with Caution
... B240: E | C240: Carbon | D240: Scope 3 GHG Emissions (Total) | F240: S | G240: tCO₂e | H240: 2019 | L240: 25 | M240: 10 | N240: 0 | O240: 15 | P240: =L240+M240+N240+O240 -> 50 | Q240: =IF(P240>=80,"✅ High Quality",IF(P240>=60,"🟡 Acceptable",IF(P240>=40,"⚠️ Use with Caution","🔴 Insufficient"))) -> ⚠️ Use with Caution

Sheet S Data_Inventory 
A1: ESG DATA INVENTORY & QUALITY SCORING
A2: Company: Smurfit Westrock | D2: Industry: Paper & Packaging | E2: Reporting Year: 2024 | L2: 25=Assured / 15=Self-rep / 5=Est. | M2: 25=Full method / 15=Value only / 0=None | N2: 25=Current yr / 20=1yr old / 5=3+yr | O2: 25=Match / 15=<5% var / 0=No 2nd source | P2: SUM of K+L+M+N | Q2: Auto-calculated
A3: # | B3: Pillar (E/S/G/Financial) | C3: KPI Category | D3: KPI Name | E3: Value (Enter number) | F3: Buisness | G3: Unit | H3: Reporting Year | I3: Source Type | J3: Source URL / Citation | K3: Assurance Level | L3: Accuracy Score (0–25) | M3: Completeness Score (0–25) | N3: Timeliness Score (0–25) | O3: Consistency Score (0–25) | P3: TOTAL Quality Score (0–100) | Q3: Quality Grade | R3: Notes / Caveats
B4: S | C4: Training | D4: Average Training Hours per Employee | E4: 14 | F4: W | G4: Hours/employee | H4: 2024 | I4: Company ESG Report | J4: Smurfit Westrock 2024 Sustainability Report | L4: 25 | M4: 15 | N4: =_xlfn.XLOOKUP(H4,'E Data_Inventory'!$H$3:$H$240,'E Data_Inventory'!N$3:N$240) -> 25 | O4: 20 | P4: =L4+M4+N4+O4 -> 85 | Q4: =IF(P4>=80,"✅ High Quality",IF(P4>=60,"🟡 Acceptable",IF(P4>=40,"⚠️ Use with Caution","🔴 Insufficient"))) -> ✅ High Quality
B5: S | C5: Training | D5: Average Training Hours per Employee | E5: 22 | F5: S | G5: Hours/employee | H5: 2019 | I5: Company ESG Report | J5: Smurfit Kappa 2021 Sustainability Report | L5: 25 | M5: 15 | N5: =_xlfn.XLOOKUP(H5,'E Data_Inventory'!$H$3:$H$240,'E Data_Inventory'!N$3:N$240) -> 5 | O5: 20 | P5: =L5+M5+N5+O5 -> 65 | Q5: =IF(P5>=80,"✅ High Quality",IF(P5>=60,"🟡 Acceptable",IF(P5>=40,"⚠️ Use with Caution","🔴 Insufficient"))) -> 🟡 Acceptable
B6: S | C6: Training | D6: Average Training Hours per Employee | E6: 11 | F6: W | G6: Hours/employee | H6: 2023 | I6: Company ESG Report | J6: Smurfit Kappa 2023 Sustainability Report | L6: 25 | M6: 15 | N6: =_xlfn.XLOOKUP(H6,'E Data_Inventory'!$H$3:$H$240,'E Data_Inventory'!N$3:N$240) -> 25 | O6: 20 | P6: =L6+M6+N6+O6 -> 85 | Q6: =IF(P6>=80,"✅ High Quality",IF(P6>=60,"🟡 Acceptable",IF(P6>=40,"⚠️ Use with Caution","🔴 Insufficient"))) -> ✅ High Quality
B7: S | C7: Workforce | D7: Total Number of Employees | E7: 46237 | F7: S | G7: Headcount | H7: 2019 | I7: Company ESG Report | J7: Smurfit Kappa 2022 Sustainability Report | L7: 25 | M7: 15 | N7: =_xlfn.XLOOKUP(H7,'E Data_Inventory'!$H$3:$H$240,'E Data_Inventory'!N$3:N$240) -> 5 | O7: 20 | P7: =L7+M7+N7+O7 -> 65 | Q7: =IF(P7>=80,"✅ High Quality",IF(P7>=60,"🟡 Acceptable",IF(P7>=40,"⚠️ Use with Caution","🔴 Insufficient"))) -> 🟡 Acceptable
B8: S | C8: Training | D8: Average Training Hours per Employee | E8: 8 | F8: W | G8: Hours/employee | H8: 2022 | I8: Company ESG Report | J8: Smurfit Westrock 2024 Sustainability Report | L8: 25 | M8: 15 | N8: =_xlfn.XLOOKUP(H8,'E Data_Inventory'!$H$3:$H$240,'E Data_Inventory'!N$3:N$240) -> 20 | O8: 20 | P8: =L8+M8+N8+O8 -> 80 | Q8: =IF(P8>=80,"✅ High Quality",IF(P8>=60,"🟡 Acceptable",IF(P8>=40,"⚠️ Use with Caution","🔴 Insufficient"))) -> ✅ High Quality
B9: S | C9: Safety | D9: Total Recordable Incident Rate (TRIR) | E9: 0.84 | F9: S | G9: Rate per 200k hrs | H9: 2019 | I9: Company ESG Report | J9: Smurfit Westrock 2024 Sustainability Report | L9: 25 | M9: 15 | N9: =_xlfn.XLOOKUP(H9,'E Data_Inventory'!$H$3:$H$240,'E Data_Inventory'!N$3:N$240) -> 5 | O9: 20 | P9: =L9+M9+N9+O9 -> 65 | Q9: =IF(P9>=80,"✅ High Quality",IF(P9>=60,"🟡 Acceptable",IF(P9>=40,"⚠️ Use with Caution","🔴 Insufficient"))) -> 🟡 Acceptable
B10: S | C10: Training | D10: Average Training Hours per Employee | E10: 11 | F10: W | G10: Hours/employee | H10: 2021 | I10: Company ESG Report | J10: Smurfit Westrock 2024 Sustainability Report | L10: 25 | M10: 15 | N10: =_xlfn.XLOOKUP(H10,'E Data_Inventory'!$H$3:$H$240,'E Data_Inventory'!N$3:N$240) -> 5 | O10: 20 | P10: =L10+M10+N10+O10 -> 65 | Q10: =IF(P10>=80,"✅ High Quality",IF(P10>=60,"🟡 Acceptable",IF(P10>=40,"⚠️ Use with Caution","🔴 Insufficient"))) -> 🟡 Acceptable
B11: S | C11: Training | D11: Total Training Hours | E11: =$E$13*$E$31 -> 843.57 | F11: S | G11: Hours | H11: 2019 | I11: Company ESG Report | J11: Smurfit Westrock 2024 Sustainability Report | L11: 25 | M11: 15 | N11: =_xlfn.XLOOKUP(H11,'E Data_Inventory'!$H$3:$H$240,'E Data_Inventory'!N$3:N$240) -> 5 | O11: 20 | P11: =L11+M11+N11+O11 -> 65 | Q11: =IF(P11>=80,"✅ High Quality",IF(P11>=60,"🟡 Acceptable",IF(P11>=40,"⚠️ Use with Caution","🔴 Insufficient"))) -> 🟡 Acceptable
B12: S | C12: Workforce | D12: Turnover | E12: 4842 | F12: S | G12: employees | H12: 2019 | I12: Company ESG Report | J12: Smurfit Kappa 2021 Sustainability Report | L12: 25 | M12: 15 | N12: =_xlfn.XLOOKUP(H12,'E Data_Inventory'!$H$3:$H$240,'E Data_Inventory'!N$3:N$240) -> 5 | O12: 20 | P12: =L12+M12+N12+O12 -> 65 | Q12: =IF(P12>=80,"✅ High Quality",IF(P12>=60,"🟡 Acceptable",IF(P12>=40,"⚠️ Use with Caution","🔴 Insufficient"))) -> 🟡 Acceptable
B13: S | C13: Diversity | D13: Women in Senior Management | E13: 0.21 | F13: S | G13: % | H13: 2019 | I13: Company ESG Report | J13: Westrock 2023 Sustainability Report | L13: 25 | M13: 15 | N13: =_xlfn.XLOOKUP(H13,'E Data_Inventory'!$H$3:$H$240,'E Data_Inventory'!N$3:N$240) -> 5 | O13: 20 | P13: =L13+M13+N13+O13 -> 65 | Q13: =IF(P13>=80,"✅ High Quality",IF(P13>=60,"🟡 Acceptable",IF(P13>=40,"⚠️ Use with Caution","🔴 Insufficient"))) -> 🟡 Acceptable
B14: S | C14: Safety | D14: Total Recordable Incident Rate (TRIR) | E14: 1.34 | F14: W | G14: Rate per 200k hrs | H14: 2024 | I14: Company ESG Report | J14: Smurfit Kappa 2021 Sustainability Report | L14: 25 | M14: 15 | N14: =_xlfn.XLOOKUP(H14,'E Data_Inventory'!$H$3:$H$240,'E Data_Inventory'!N$3:N$240) -> 25 | O14: 20 | P14: =L14+M14+N14+O14 -> 85 | Q14: =IF(P14>=80,"✅ High Quality",IF(P14>=60,"🟡 Acceptable",IF(P14>=40,"⚠️ Use with Caution","🔴 Insufficient"))) -> ✅ High Quality
B15: S | C15: Safety | D15: Total Recordable Incident Rate (TRIR) | E15: 1.52 | F15: W | G15: Rate per 200k hrs | H15: 2023 | I15: Company ESG Report | J15: Smurfit Kappa 2021 Sustainability Report | L15: 25 | M15: 15 | N15: =_xlfn.XLOOKUP(H15,'E Data_Inventory'!$H$3:$H$240,'E Data_Inventory'!N$3:N$240) -> 25 | O15: 20 | P15: =L15+M15+N15+O15 -> 85 | Q15: =IF(P15>=80,"✅ High Quality",IF(P15>=60,"🟡 Acceptable",IF(P15>=40,"⚠️ Use with Caution","🔴 Insufficient"))) -> ✅ High Quality
B16: S | C16: Safety | D16: Total Recordable Incident Rate (TRIR) | E16: 1.69 | F16: W | G16: Rate per 200k hrs | H16: 2022 | I16: Company ESG Report | J16: Smurfit Kappa 2021 Sustainability Report | L16: 25 | M16: 15 | N16: =_xlfn.XLOOKUP(H16,'E Data_Inventory'!$H$3:$H$240,'E Data_Inventory'!N$3:N$240) -> 20 | O16: 20 | P16: =L16+M16+N16+O16 -> 80 | Q16: =IF(P16>=80,"✅ High Quality",IF(P16>=60,"🟡 Acceptable",IF(P16>=40,"⚠️ Use with Caution","🔴 Insufficient"))) -> ✅ High Quality
B17: S | C17: Safety | D17: Total Recordable Incident Rate (TRIR) | E17: 1.61 | F17: W | G17: Rate per 200k hrs | H17: 2021 | I17: Company ESG Report | J17: Smurfit Westrock 2024 Sustainability Report | L17: 25 | M17: 15 | N17: =_xlfn.XLOOKUP(H17,'E Data_Inventory'!$H$3:$H$240,'E Data_Inventory'!N$3:N$240) -> 5 | O17: 20 | P17: =L17+M17+N17+O17 -> 65 | Q17: =IF(P17>=80,"✅ High Quality",IF(P17>=60,"🟡 Acceptable",IF(P17>=40,"⚠️ Use with Caution","🔴 Insufficient"))) -> 🟡 Acceptable
B18: S | C18: Safety | D18: Total Recordable Incident Rate (TRIR) | E18: 1.56 | F18: W | G18: Rate per 200k hrs | H18: 2020 | I18: Company ESG Report | J18: Westrock 2022 Sustainability Report | L18: 25 | M18: 15 | N18: =_xlfn.XLOOKUP(H18,'E Data_Inventory'!$H$3:$H$240,'E Data_Inventory'!N$3:N$240) -> 5 | O18: 20 | P18: =L18+M18+N18+O18 -> 65 | Q18: =IF(P18>=80,"✅ High Quality",IF(P18>=60,"🟡 Acceptable",IF(P18>=40,"⚠️ Use with Caution","🔴 Insufficient"))) -> 🟡 Acceptable
B19: S | C19: Safety | D19: Total Recordable Incident Rate (TRIR) | E19: 1.68 | F19: W | G19: Rate per 200k hrs | H19: 2019 | I19: Company ESG Report | J19: Smurfit Kappa 2021 Sustainability Report | L19: 25 | M19: 15 | N19: =_xlfn.XLOOKUP(H19,'E Data_Inventory'!$H$3:$H$240,'E Data_Inventory'!N$3:N$240) -> 5 | O19: 20 | P19: =L19+M19+N19+O19 -> 65 | Q19: =IF(P19>=80,"✅ High Quality",IF(P19>=60,"🟡 Acceptable",IF(P19>=40,"⚠️ Use with Caution","🔴 Insufficient"))) -> 🟡 Acceptable
B20: S | C20: Workforce | D20: Total Number of Employees | E20: 50017 | F20: W | G20: Headcount | H20: 2024 | I20: Company ESG Report | J20: Smurfit Kappa 2022 Sustainability Report | L20: 25 | M20: 15 | N20: =_xlfn.XLOOKUP(H20,'E Data_Inventory'!$H$3:$H$240,'E Data_Inventory'!N$3:N$240) -> 25 | O20: 20 | P20: =L20+M20+N20+O20 -> 85 | Q20: =IF(P20>=80,"✅ High Quality",IF(P20>=60,"🟡 Acceptable",IF(P20>=40,"⚠️ Use with Caution","🔴 Insufficient"))) -> ✅ High Quality
B21: S | C21: Diversity | D21: Women in Total Workforce | E21: 8785.03 | F21: S | G21: employees | H21: 2019 | I21: Company ESG Report | J21: Smurfit Westrock 2024 Sustainability Report | L21: 25 | M21: 15 | N21: =_xlfn.XLOOKUP(H21,'E Data_Inventory'!$H$3:$H$240,'E Data_Inventory'!N$3:N$240) -> 5 | O21: 20 | P21: =L21+M21+N21+O21 -> 65 | Q21: =IF(P21>=80,"✅ High Quality",IF(P21>=60,"🟡 Acceptable",IF(P21>=40,"⚠️ Use with Caution","🔴 Insufficient"))) -> 🟡 Acceptable
B22: S | C22: Workforce | D22: Total Number of Employees | E22: 54075 | F22: W | G22: Headcount | H22: 2023 | I22: Company ESG Report | J22: Smurfit Westrock 2024 Sustainability Report | L22: 25 | M22: 15 | N22: =_xlfn.XLOOKUP(H22,'E Data_Inventory'!$H$3:$H$240,'E Data_Inventory'!N$3:N$240) -> 25 | O22: 20 | P22: =L22+M22+N22+O22 -> 85 | Q22: =IF(P22>=80,"✅ High Quality",IF(P22>=60,"🟡 Acceptable",IF(P22>=40,"⚠️ Use with Caution","🔴 Insufficient"))) -> ✅ High Quality
B23: S | C23: Training | D23: Average Training Hours per Employee | E23: 15 | F23: S | G23: Hours/employee | H23: 2020 | I23: Company ESG Report | J23: Smurfit Kappa 2022 Sustainability Report | L23: 25 | M23: 15 | N23: =_xlfn.XLOOKUP(H23,'E Data_Inventory'!$H$3:$H$240,'E Data_Inventory'!N$3:N$240) -> 5 | O23: 20 | P23: =L23+M23+N23+O23 -> 65 | Q23: =IF(P23>=80,"✅ High Quality",IF(P23>=60,"🟡 Acceptable",IF(P23>=40,"⚠️ Use with Caution","🔴 Insufficient"))) -> 🟡 Acceptable
... B28: S | C28: Workforce | D28: Total Number of Employees | E28: 49300 | F28: W | G28: Headcount | H28: 2020 | I28: Company ESG Report | J28: Smurfit Kappa 2019 Sustainability Report | L28: 25 | M28: 15 | N28: =_xlfn.XLOOKUP(H28,'E Data_Inventory'!$H$3:$H$240,'E Data_Inventory'!N$3:N$240) -> 5 | O28: 20 | P28: =L28+M28+N28+O28 -> 65 | Q28: =IF(P28>=80,"✅ High Quality",IF(P28>=60,"🟡 Acceptable",IF(P28>=40,"⚠️ Use with Caution","🔴 Insufficient"))) -> 🟡 Acceptable
B29: S | C29: Training | D29: Total Training Hours | E29: =$E$12*$E$29 -> 5162891184 | F29: S | G29: Hours | H29: 2020 | I29: Company ESG Report | J29: Smurfit Kappa 2021 Sustainability Report | L29: 25 | M29: 15 | N29: =_xlfn.XLOOKUP(H29,'E Data_Inventory'!$H$3:$H$240,'E Data_Inventory'!N$3:N$240) -> 5 | O29: 20 | P29: =L29+M29+N29+O29 -> 65 | Q29: =IF(P29>=80,"✅ High Quality",IF(P29>=60,"🟡 Acceptable",IF(P29>=40,"⚠️ Use with Caution","🔴 Insufficient"))) -> 🟡 Acceptable
B30: S | C30: Workforce | D30: Total Number of Employees | E30: N/A | F30: W | G30: Headcount | H30: 2019 | I30: Company ESG Report | J30: Smurfit Kappa 2019 Sustainability Report | L30: 25 | M30: 25 | N30: 25 | O30: 15 | P30: =L30+M30+N30+O30 -> 90 | Q30: =IF(P30>=80,"✅ High Quality",IF(P30>=60,"🟡 Acceptable",IF(P30>=40,"⚠️ Use with Caution","🔴 Insufficient"))) -> ✅ High Quality
B31: S | C31: Workforce | D31: Turnover | E31: 4017 | F31: S | G31: employees | H31: 2020 | I31: Company ESG Report | J31: Smurfit Kappa 2022 Sustainability Report | L31: 25 | M31: 15 | N31: =_xlfn.XLOOKUP(H31,'E Data_Inventory'!$H$3:$H$240,'E Data_Inventory'!N$3:N$240) -> 5 | O31: 20 | P31: =L31+M31+N31+O31 -> 65 | Q31: =IF(P31>=80,"✅ High Quality",IF(P31>=60,"🟡 Acceptable",IF(P31>=40,"⚠️ Use with Caution","🔴 Insufficient"))) -> 🟡 Acceptable
B32: S | C32: Diversity | D32: Women in Senior Management | E32: 0.22 | F32: S | G32: % | H32: 2020 | I32: Company ESG Report | J32: Smurfit Kappa 2023 Sustainability Report | L32: 25 | M32: 15 | N32: =_xlfn.XLOOKUP(H32,'E Data_Inventory'!$H$3:$H$240,'E Data_Inventory'!N$3:N$240) -> 5 | O32: 20 | P32: =L32+M32+N32+O32 -> 65 | Q32: =IF(P32>=80,"✅ High Quality",IF(P32>=60,"🟡 Acceptable",IF(P32>=40,"⚠️ Use with Caution","🔴 Insufficient"))) -> 🟡 Acceptable
B33: S | C33: Diversity | D33: Women in Total Workforce | E33: 8870.72 | F33: S | G33: employees | H33: 2020 | I33: Company ESG Report | J33: Westrock 2022 Sustainability Report | L33: 25 | M33: 15 | N33: =_xlfn.XLOOKUP(H33,'E Data_Inventory'!$H$3:$H$240,'E Data_Inventory'!N$3:N$240) -> 5 | O33: 20 | P33: =L33+M33+N33+O33 -> 65 | Q33: =IF(P33>=80,"✅ High Quality",IF(P33>=60,"🟡 Acceptable",IF(P33>=40,"⚠️ Use with Caution","🔴 Insufficient"))) -> 🟡 Acceptable
B34: S | C34: Training | D34: Average Training Hours per Employee | E34: 18.7 | F34: S | G34: Hours/employee | H34: 2021 | I34: Company ESG Report | J34: Westrock 2022 Sustainability Report | L34: 25 | M34: 15 | N34: =_xlfn.XLOOKUP(H34,'E Data_Inventory'!$H$3:$H$240,'E Data_Inventory'!N$3:N$240) -> 5 | O34: 20 | P34: =L34+M34+N34+O34 -> 65 | Q34: =IF(P34>=80,"✅ High Quality",IF(P34>=60,"🟡 Acceptable",IF(P34>=40,"⚠️ Use with Caution","🔴 Insufficient"))) -> 🟡 Acceptable
B35: S | C35: Workforce | D35: Total Number of Employees | E35: 48045 | F35: S | G35: Headcount | H35: 2021 | I35: Company ESG Report | J35: Smurfit Kappa 2021 Sustainability Report | L35: 25 | M35: 15 | N35: =_xlfn.XLOOKUP(H35,'E Data_Inventory'!$H$3:$H$240,'E Data_Inventory'!N$3:N$240) -> 5 | O35: 20 | P35: =L35+M35+N35+O35 -> 65 | Q35: =IF(P35>=80,"✅ High Quality",IF(P35>=60,"🟡 Acceptable",IF(P35>=40,"⚠️ Use with Caution","🔴 Insufficient"))) -> 🟡 Acceptable
B36: S | C36: Safety | D36: Total Recordable Incident Rate (TRIR) | E36: 0.59 | F36: S | G36: Rate per 200k hrs | H36: 2021 | I36: Company ESG Report | J36: Smurfit Kappa 2021 Sustainability Report | L36: 25 | M36: 15 | N36: =_xlfn.XLOOKUP(H36,'E Data_Inventory'!$H$3:$H$240,'E Data_Inventory'!N$3:N$240) -> 5 | O36: 20 | P36: =L36+M36+N36+O36 -> 65 | Q36: =IF(P36>=80,"✅ High Quality",IF(P36>=60,"🟡 Acceptable",IF(P36>=40,"⚠️ Use with Caution","🔴 Insufficient"))) -> 🟡 Acceptable
B37: S | C37: Training | D37: Total Training Hours | E37: =$E$27*$E$11 -> 506.142 | F37: S | G37: Hours | H37: 2021 | I37: Company ESG Report | J37: Smurfit Kappa 2023 Sustainability Report | L37: 25 | M37: 15 | N37: =_xlfn.XLOOKUP(H37,'E Data_Inventory'!$H$3:$H$240,'E Data_Inventory'!N$3:N$240) -> 5 | O37: 20 | P37: =L37+M37+N37+O37 -> 65 | Q37: =IF(P37>=80,"✅ High Quality",IF(P37>=60,"🟡 Acceptable",IF(P37>=40,"⚠️ Use with Caution","🔴 Insufficient"))) -> 🟡 Acceptable
B38: S | C38: Training | D38: Total Training Hours | E38: 602035 | F38: W | G38: Hours | H38: 2024 | I38: Company ESG Report | J38: Smurfit Kappa 2021 Sustainability Report | L38: 25 | M38: 15 | N38: =_xlfn.XLOOKUP(H38,'E Data_Inventory'!$H$3:$H$240,'E Data_Inventory'!N$3:N$240) -> 25 | O38: 20 | P38: =L38+M38+N38+O38 -> 85 | Q38: =IF(P38>=80,"✅ High Quality",IF(P38>=60,"🟡 Acceptable",IF(P38>=40,"⚠️ Use with Caution","🔴 Insufficient"))) -> ✅ High Quality
B39: S | C39: Training | D39: Total Training Hours | E39: 557244 | F39: W | G39: Hours | H39: 2023 | I39: Company ESG Report | J39: Smurfit Kappa 2021 Sustainability Report | L39: 25 | M39: 15 | N39: =_xlfn.XLOOKUP(H39,'E Data_Inventory'!$H$3:$H$240,'E Data_Inventory'!N$3:N$240) -> 25 | O39: 20 | P39: =L39+M39+N39+O39 -> 85 | Q39: =IF(P39>=80,"✅ High Quality",IF(P39>=60,"🟡 Acceptable",IF(P39>=40,"⚠️ Use with Caution","🔴 Insufficient"))) -> ✅ High Quality
B40: S | C40: Training | D40: Total Training Hours | E40: 335505 | F40: W | G40: Hours | H40: 2022 | I40: Company ESG Report | J40: Smurfit Kappa 2021 Sustainability Report | L40: 25 | M40: 15 | N40: =_xlfn.XLOOKUP(H40,'E Data_Inventory'!$H$3:$H$240,'E Data_Inventory'!N$3:N$240) -> 20 | O40: 20 | P40: =L40+M40+N40+O40 -> 80 | Q40: =IF(P40>=80,"✅ High Quality",IF(P40>=60,"🟡 Acceptable",IF(P40>=40,"⚠️ Use with Caution","🔴 Insufficient"))) -> ✅ High Quality
B41: S | C41: Training | D41: Total Training Hours | E41: 347459 | F41: W | G41: Hours | H41: 2021 | I41: Company ESG Report | J41: Smurfit Kappa 2019 Sustainability Report | L41: 25 | M41: 15 | N41: =_xlfn.XLOOKUP(H41,'E Data_Inventory'!$H$3:$H$240,'E Data_Inventory'!N$3:N$240) -> 5 | O41: 20 | P41: =L41+M41+N41+O41 -> 65 | Q41: =IF(P41>=80,"✅ High Quality",IF(P41>=60,"🟡 Acceptable",IF(P41>=40,"⚠️ Use with Caution","🔴 Insufficient"))) -> 🟡 Acceptable
B42: S | C42: Training | D42: Total Training Hours | E42: 255410 | F42: W | G42: Hours | H42: 2020 | I42: Company ESG Report | J42: Smurfit Kappa 2021 Sustainability Report | L42: 25 | M42: 15 | N42: =_xlfn.XLOOKUP(H42,'E Data_Inventory'!$H$3:$H$240,'E Data_Inventory'!N$3:N$240) -> 5 | O42: 20 | P42: =L42+M42+N42+O42 -> 65 | Q42: =IF(P42>=80,"✅ High Quality",IF(P42>=60,"🟡 Acceptable",IF(P42>=40,"⚠️ Use with Caution","🔴 Insufficient"))) -> 🟡 Acceptable
B43: S | C43: Training | D43: Total Training Hours | E43: N/A | F43: W | G43: Hours | H43: 2019 | I43: Company ESG Report | J43: Smurfit Kappa 2021 Sustainability Report | L43: 25 | M43: 25 | N43: 25 | O43: 15 | P43: =L43+M43+N43+O43 -> 90 | Q43: =IF(P43>=80,"✅ High Quality",IF(P43>=60,"🟡 Acceptable",IF(P43>=40,"⚠️ Use with Caution","🔴 Insufficient"))) -> ✅ High Quality
B44: S | C44: Workforce | D44: Turnover | E44: 4919 | F44: S | G44: employees | H44: 2021 | I44: Company ESG Report | J44: Smurfit Westrock 2024 Sustainability Report | L44: 25 | M44: 15 | N44: =_xlfn.XLOOKUP(H44,'E Data_Inventory'!$H$3:$H$240,'E Data_Inventory'!N$3:N$240) -> 5 | O44: 20 | P44: =L44+M44+N44+O44 -> 65 | Q44: =IF(P44>=80,"✅ High Quality",IF(P44>=60,"🟡 Acceptable",IF(P44>=40,"⚠️ Use with Caution","🔴 Insufficient"))) -> 🟡 Acceptable
B45: S | C45: Diversity | D45: Women in Senior Management | E45: 0.22 | F45: S | G45: % | H45: 2021 | I45: Company ESG Report | J45: Smurfit Kappa 2022 Sustainability Report | L45: 25 | M45: 15 | N45: =_xlfn.XLOOKUP(H45,'E Data_Inventory'!$H$3:$H$240,'E Data_Inventory'!N$3:N$240) -> 5 | O45: 20 | P45: =L45+M45+N45+O45 -> 65 | Q45: =IF(P45>=80,"✅ High Quality",IF(P45>=60,"🟡 Acceptable",IF(P45>=40,"⚠️ Use with Caution","🔴 Insufficient"))) -> 🟡 Acceptable
B46: S | C46: Diversity | D46: Women in Total Workforce | E46: 9609 | F46: S | G46: employees | H46: 2021 | I46: Company ESG Report | J46: Smurfit Westrock 2024 Sustainability Report | L46: 25 | M46: 15 | N46: =_xlfn.XLOOKUP(H46,'E Data_Inventory'!$H$3:$H$240,'E Data_Inventory'!N$3:N$240) -> 5 | O46: 20 | P46: =L46+M46+N46+O46 -> 65 | Q46: =IF(P46>=80,"✅ High Quality",IF(P46>=60,"🟡 Acceptable",IF(P46>=40,"⚠️ Use with Caution","🔴 Insufficient"))) -> 🟡 Acceptable
B47: S | C47: Training | D47: Average Training Hours per Employee | E47: 21 | F47: S | G47: Hours/employee | H47: 2022 | I47: Company ESG Report | J47: Westrock 2023 Sustainability Report | L47: 25 | M47: 15 | N47: =_xlfn.XLOOKUP(H47,'E Data_Inventory'!$H$3:$H$240,'E Data_Inventory'!N$3:N$240) -> 20 | O47: 20 | P47: =L47+M47+N47+O47 -> 80 | Q47: =IF(P47>=80,"✅ High Quality",IF(P47>=60,"🟡 Acceptable",IF(P47>=40,"⚠️ Use with Caution","🔴 Insufficient"))) -> ✅ High Quality
B48: S | C48: Workforce | D48: Total Number of Employees | E48: 48058 | F48: S | G48: Headcount | H48: 2022 | I48: Company ESG Report | J48: Smurfit Westrock 2024 Sustainability Report | L48: 25 | M48: 15 | N48: =_xlfn.XLOOKUP(H48,'E Data_Inventory'!$H$3:$H$240,'E Data_Inventory'!N$3:N$240) -> 20 | O48: 20 | P48: =L48+M48+N48+O48 -> 80 | Q48: =IF(P48>=80,"✅ High Quality",IF(P48>=60,"🟡 Acceptable",IF(P48>=40,"⚠️ Use with Caution","🔴 Insufficient"))) -> ✅ High Quality
B49: S | C49: Safety | D49: Total Recordable Incident Rate (TRIR) | E49: 0.51 | F49: S | G49: Rate per 200k hrs | H49: 2022 | I49: Company ESG Report | J49: Westrock 2022 Sustainability Report | L49: 25 | M49: 15 | N49: =_xlfn.XLOOKUP(H49,'E Data_Inventory'!$H$3:$H$240,'E Data_Inventory'!N$3:N$240) -> 20 | O49: 20 | P49: =L49+M49+N49+O49 -> 80 | Q49: =IF(P49>=80,"✅ High Quality",IF(P49>=60,"🟡 Acceptable",IF(P49>=40,"⚠️ Use with Caution","🔴 Insufficient"))) -> ✅ High Quality
B50: S | C50: Workforce | D50: Turnover | E50: 15934 | F50: W | G50: employees | H50: 2024 | I50: Company ESG Report | J50: Smurfit Kappa 2023 Sustainability Report | L50: 25 | M50: 15 | N50: =_xlfn.XLOOKUP(H50,'E Data_Inventory'!$H$3:$H$240,'E Data_Inventory'!N$3:N$240) -> 25 | O50: 20 | P50: =L50+M50+N50+O50 -> 85 | Q50: =IF(P50>=80,"✅ High Quality",IF(P50>=60,"🟡 Acceptable",IF(P50>=40,"⚠️ Use with Caution","🔴 Insufficient"))) -> ✅ High Quality
B51: S | C51: Workforce | D51: Turnover | E51: 17863 | F51: W | G51: employees | H51: 2023 | I51: Company ESG Report | J51: Smurfit Kappa 2023 Sustainability Report | L51: 25 | M51: 15 | N51: =_xlfn.XLOOKUP(H51,'E Data_Inventory'!$H$3:$H$240,'E Data_Inventory'!N$3:N$240) -> 25 | O51: 20 | P51: =L51+M51+N51+O51 -> 85 | Q51: =IF(P51>=80,"✅ High Quality",IF(P51>=60,"🟡 Acceptable",IF(P51>=40,"⚠️ Use with Caution","🔴 Insufficient"))) -> ✅ High Quality
B52: S | C52: Workforce | D52: Turnover | E52: 14935 | F52: W | G52: employees | H52: 2022 | I52: Company ESG Report | J52: Smurfit Kappa 2023 Sustainability Report | L52: 25 | M52: 15 | N52: =_xlfn.XLOOKUP(H52,'E Data_Inventory'!$H$3:$H$240,'E Data_Inventory'!N$3:N$240) -> 20 | O52: 20 | P52: =L52+M52+N52+O52 -> 80 | Q52: =IF(P52>=80,"✅ High Quality",IF(P52>=60,"🟡 Acceptable",IF(P52>=40,"⚠️ Use with Caution","🔴 Insufficient"))) -> ✅ High Quality
B53: S | C53: Workforce | D53: Turnover | E53: 11753 | F53: W | G53: employees | H53: 2021 | I53: Company ESG Report | J53: Smurfit Westrock 2024 Sustainability Report | L53: 25 | M53: 15 | N53: =_xlfn.XLOOKUP(H53,'E Data_Inventory'!$H$3:$H$240,'E Data_Inventory'!N$3:N$240) -> 5 | O53: 20 | P53: =L53+M53+N53+O53 -> 65 | Q53: =IF(P53>=80,"✅ High Quality",IF(P53>=60,"🟡 Acceptable",IF(P53>=40,"⚠️ Use with Caution","🔴 Insufficient"))) -> 🟡 Acceptable
B54: S | C54: Workforce | D54: Turnover | E54: N/A | F54: W | G54: employees | H54: 2020 | I54: Company ESG Report | J54: Smurfit Kappa 2021 Sustainability Report | L54: 25 | M54: 25 | N54: 25 | O54: 15 | P54: =L54+M54+N54+O54 -> 90 | Q54: =IF(P54>=80,"✅ High Quality",IF(P54>=60,"🟡 Acceptable",IF(P54>=40,"⚠️ Use with Caution","🔴 Insufficient"))) -> ✅ High Quality
B55: S | C55: Workforce | D55: Turnover | E55: N/A | F55: W | G55: employees | H55: 2019 | I55: Company ESG Report | J55: Smurfit Kappa 2023 Sustainability Report | L55: 25 | M55: 25 | N55: 25 | O55: 15 | P55: =L55+M55+N55+O55 -> 90 | Q55: =IF(P55>=80,"✅ High Quality",IF(P55>=60,"🟡 Acceptable",IF(P55>=40,"⚠️ Use with Caution","🔴 Insufficient"))) -> ✅ High Quality
B56: S | C56: Training | D56: Total Training Hours | E56: =$E$25*$E$9 -> 39217.92 | F56: S | G56: Hours | H56: 2022 | I56: Company ESG Report | J56: Smurfit Kappa 2019 Sustainability Report | L56: 25 | M56: 15 | N56: =_xlfn.XLOOKUP(H56,'E Data_Inventory'!$H$3:$H$240,'E Data_Inventory'!N$3:N$240) -> 20 | O56: 20 | P56: =L56+M56+N56+O56 -> 80 | Q56: =IF(P56>=80,"✅ High Quality",IF(P56>=60,"🟡 Acceptable",IF(P56>=40,"⚠️ Use with Caution","🔴 Insufficient"))) -> ✅ High Quality
B57: S | C57: Workforce | D57: Turnover | E57: 5421 | F57: S | G57: employees | H57: 2022 | I57: Company ESG Report | J57: Smurfit Westrock 2024 Sustainability Report | L57: 25 | M57: 15 | N57: =_xlfn.XLOOKUP(H57,'E Data_Inventory'!$H$3:$H$240,'E Data_Inventory'!N$3:N$240) -> 20 | O57: 20 | P57: =L57+M57+N57+O57 -> 80 | Q57: =IF(P57>=80,"✅ High Quality",IF(P57>=60,"🟡 Acceptable",IF(P57>=40,"⚠️ Use with Caution","🔴 Insufficient"))) -> ✅ High Quality
B58: S | C58: Diversity | D58: Women in Senior Management | E58: 0.235 | F58: S | G58: % | H58: 2022 | I58: Company ESG Report | J58: Westrock 2023 Sustainability Report | L58: 25 | M58: 15 | N58: =_xlfn.XLOOKUP(H58,'E Data_Inventory'!$H$3:$H$240,'E Data_Inventory'!N$3:N$240) -> 20 | O58: 20 | P58: =L58+M58+N58+O58 -> 80 | Q58: =IF(P58>=80,"✅ High Quality",IF(P58>=60,"🟡 Acceptable",IF(P58>=40,"⚠️ Use with Caution","🔴 Insufficient"))) -> ✅ High Quality
B59: S | C59: Diversity | D59: Women in Total Workforce | E59: 9611.6 | F59: S | G59: employees | H59: 2022 | I59: Company ESG Report | J59: Westrock 2022 Sustainability Report | L59: 25 | M59: 15 | N59: =_xlfn.XLOOKUP(H59,'E Data_Inventory'!$H$3:$H$240,'E Data_Inventory'!N$3:N$240) -> 20 | O59: 20 | P59: =L59+M59+N59+O59 -> 80 | Q59: =IF(P59>=80,"✅ High Quality",IF(P59>=60,"🟡 Acceptable",IF(P59>=40,"⚠️ Use with Caution","🔴 Insufficient"))) -> ✅ High Quality
B60: S | C60: Training | D60: Average Training Hours per Employee | E60: 22 | F60: S | G60: Hours/employee | H60: 2023 | I60: Company ESG Report | J60: Westrock 2020 GRI Report | L60: 25 | M60: 15 | N60: =_xlfn.XLOOKUP(H60,'E Data_Inventory'!$H$3:$H$240,'E Data_Inventory'!N$3:N$240) -> 25 | O60: 20 | P60: =L60+M60+N60+O60 -> 85 | Q60: =IF(P60>=80,"✅ High Quality",IF(P60>=60,"🟡 Acceptable",IF(P60>=40,"⚠️ Use with Caution","🔴 Insufficient"))) -> ✅ High Quality
B61: S | C61: Workforce | D61: Total Number of Employees | E61: 46982 | F61: S | G61: Headcount | H61: 2023 | I61: Company ESG Report | J61: Smurfit Westrock 2024 Sustainability Report | L61: 25 | M61: 15 | N61: =_xlfn.XLOOKUP(H61,'E Data_Inventory'!$H$3:$H$240,'E Data_Inventory'!N$3:N$240) -> 25 | O61: 20 | P61: =L61+M61+N61+O61 -> 85 | Q61: =IF(P61>=80,"✅ High Quality",IF(P61>=60,"🟡 Acceptable",IF(P61>=40,"⚠️ Use with Caution","🔴 Insufficient"))) -> ✅ High Quality
B62: S | C62: Safety | D62: Total Recordable Incident Rate (TRIR) | E62: 0.53 | F62: S | G62: Rate per 200k hrs | H62: 2023 | I62: Company ESG Report | J62: Smurfit Westrock 2024 Sustainability Report | L62: 25 | M62: 15 | N62: =_xlfn.XLOOKUP(H62,'E Data_Inventory'!$H$3:$H$240,'E Data_Inventory'!N$3:N$240) -> 25 | O62: 20 | P62: =L62+M62+N62+O62 -> 85 | Q62: =IF(P62>=80,"✅ High Quality",IF(P62>=60,"🟡 Acceptable",IF(P62>=40,"⚠️ Use with Caution","🔴 Insufficient"))) -> ✅ High Quality
B63: S | C63: Diversity | D63: Women in Senior Management | F63: W | G63: % | H63: 2023 | I63: Company ESG Report | J63: Westrock 2023 Sustainability Report | L63: 25 | M63: 25 | N63: 25 | O63: 15 | P63: =L63+M63+N63+O63 -> 90 | Q63: =IF(P63>=80,"✅ High Quality",IF(P63>=60,"🟡 Acceptable",IF(P63>=40,"⚠️ Use with Caution","🔴 Insufficient"))) -> ✅ High Quality
B64: S | C64: Training | D64: Total Training Hours | E64: =$E$23*$E$7 -> 693555 | F64: S | G64: Hours | H64: 2023 | I64: Company ESG Report | J64: Westrock 2022 Sustainability Report | L64: 25 | M64: 15 | N64: =_xlfn.XLOOKUP(H64,'E Data_Inventory'!$H$3:$H$240,'E Data_Inventory'!N$3:N$240) -> 25 | O64: 20 | P64: =L64+M64+N64+O64 -> 85 | Q64: =IF(P64>=80,"✅ High Quality",IF(P64>=60,"🟡 Acceptable",IF(P64>=40,"⚠️ Use with Caution","🔴 Insufficient"))) -> ✅ High Quality
B65: S | C65: Diversity | D65: Women in Senior Management | F65: W | G65: % | H65: 2022 | I65: Company ESG Report | J65: Westrock 2022 Sustainability Report | L65: 25 | M65: 25 | N65: 25 | O65: 15 | P65: =L65+M65+N65+O65 -> 90 | Q65: =IF(P65>=80,"✅ High Quality",IF(P65>=60,"🟡 Acceptable",IF(P65>=40,"⚠️ Use with Caution","🔴 Insufficient"))) -> ✅ High Quality
B66: S | C66: Workforce | D66: Turnover | E66: 5221 | F66: S | G66: employees | H66: 2023 | I66: Company ESG Report | J66: Westrock 2021 Sustainability Report | L66: 25 | M66: 15 | N66: =_xlfn.XLOOKUP(H66,'E Data_Inventory'!$H$3:$H$240,'E Data_Inventory'!N$3:N$240) -> 25 | O66: 20 | P66: =L66+M66+N66+O66 -> 85 | Q66: =IF(P66>=80,"✅ High Quality",IF(P66>=60,"🟡 Acceptable",IF(P66>=40,"⚠️ Use with Caution","🔴 Insufficient"))) -> ✅ High Quality
B67: S | C67: Diversity | D67: Women in Senior Management | F67: W | G67: % | H67: 2021 | I67: Company ESG Report | J67: Westrock 2022 Sustainability Report | L67: 25 | M67: 25 | N67: 25 | O67: 15 | P67: =L67+M67+N67+O67 -> 90 | Q67: =IF(P67>=80,"✅ High Quality",IF(P67>=60,"🟡 Acceptable",IF(P67>=40,"⚠️ Use with Caution","🔴 Insufficient"))) -> ✅ High Quality
B68: S | C68: Diversity | D68: Women in Senior Management | E68: 0.251 | F68: S | G68: % | H68: 2023 | I68: Company ESG Report | J68: Westrock 2021 Sustainability Report | L68: 25 | M68: 15 | N68: =_xlfn.XLOOKUP(H68,'E Data_Inventory'!$H$3:$H$240,'E Data_Inventory'!N$3:N$240) -> 25 | O68: 20 | P68: =L68+M68+N68+O68 -> 85 | Q68: =IF(P68>=80,"✅ High Quality",IF(P68>=60,"🟡 Acceptable",IF(P68>=40,"⚠️ Use with Caution","🔴 Insufficient"))) -> ✅ High Quality
B69: S | C69: Diversity | D69: Women in Senior Management | F69: W | G69: % | H69: 2020 | I69: Company ESG Report | J69: Smurfit Westrock 2024 Sustainability Report | L69: 25 | M69: 25 | N69: 25 | O69: 15 | P69: =L69+M69+N69+O69 -> 90 | Q69: =IF(P69>=80,"✅ High Quality",IF(P69>=60,"🟡 Acceptable",IF(P69>=40,"⚠️ Use with Caution","🔴 Insufficient"))) -> ✅ High Quality
B70: S | C70: Diversity | D70: Women in Total Workforce | E70: 9678.292 | F70: S | G70: employees | H70: 2023 | I70: Company ESG Report | J70: Westrock 2020 GRI Report | L70: 25 | M70: 15 | N70: =_xlfn.XLOOKUP(H70,'E Data_Inventory'!$H$3:$H$240,'E Data_Inventory'!N$3:N$240) -> 25 | O70: 20 | P70: =L70+M70+N70+O70 -> 85 | Q70: =IF(P70>=80,"✅ High Quality",IF(P70>=60,"🟡 Acceptable",IF(P70>=40,"⚠️ Use with Caution","🔴 Insufficient"))) -> ✅ High Quality
B71: S | C71: Training | D71: Average Training Hours per Employee | E71: 24 | F71: S | G71: Hours/employee | H71: 2024 | I71: Company ESG Report | J71: Westrock 2023 Sustainability Report | L71: 25 | M71: 15 | N71: =_xlfn.XLOOKUP(H71,'E Data_Inventory'!$H$3:$H$240,'E Data_Inventory'!N$3:N$240) -> 25 | O71: 20 | P71: =L71+M71+N71+O71 -> 85 | Q71: =IF(P71>=80,"✅ High Quality",IF(P71>=60,"🟡 Acceptable",IF(P71>=40,"⚠️ Use with Caution","🔴 Insufficient"))) -> ✅ High Quality
B72: S | C72: Diversity | D72: Women in Total Workforce | E72: 12352 | F72: W | G72: employees | H72: 2024 | I72: Company ESG Report | J72: Westrock 2022 Sustainability Report | L72: 25 | M72: 15 | N72: =_xlfn.XLOOKUP(H72,'E Data_Inventory'!$H$3:$H$240,'E Data_Inventory'!N$3:N$240) -> 25 | O72: 20 | P72: =L72+M72+N72+O72 -> 85 | Q72: =IF(P72>=80,"✅ High Quality",IF(P72>=60,"🟡 Acceptable",IF(P72>=40,"⚠️ Use with Caution","🔴 Insufficient"))) -> ✅ High Quality
B73: S | C73: Workforce | D73: Total Number of Employees | E73: 46674 | F73: S | G73: Headcount | H73: 2024 | I73: Company ESG Report | J73: Westrock 2023 Sustainability Report | L73: 25 | M73: 15 | N73: =_xlfn.XLOOKUP(H73,'E Data_Inventory'!$H$3:$H$240,'E Data_Inventory'!N$3:N$240) -> 25 | O73: 20 | P73: =L73+M73+N73+O73 -> 85 | Q73: =IF(P73>=80,"✅ High Quality",IF(P73>=60,"🟡 Acceptable",IF(P73>=40,"⚠️ Use with Caution","🔴 Insufficient"))) -> ✅ High Quality
B74: S | C74: Diversity | D74: Women in Total Workforce | E74: 12735 | F74: W | G74: employees | H74: 2023 | I74: Company ESG Report | J74: Westrock 2023 Sustainability Report | L74: 25 | M74: 15 | N74: =_xlfn.XLOOKUP(H74,'E Data_Inventory'!$H$3:$H$240,'E Data_Inventory'!N$3:N$240) -> 25 | O74: 20 | P74: =L74+M74+N74+O74 -> 85 | Q74: =IF(P74>=80,"✅ High Quality",IF(P74>=60,"🟡 Acceptable",IF(P74>=40,"⚠️ Use with Caution","🔴 Insufficient"))) -> ✅ High Quality
B75: S | C75: Safety | D75: Total Recordable Incident Rate (TRIR) | E75: 0.46 | F75: S | G75: Rate per 200k hrs | H75: 2024 | I75: Company ESG Report | J75: Smurfit Westrock 2024 Sustainability Report | L75: 25 | M75: 15 | N75: =_xlfn.XLOOKUP(H75,'E Data_Inventory'!$H$3:$H$240,'E Data_Inventory'!N$3:N$240) -> 25 | O75: 20 | P75: =L75+M75+N75+O75 -> 85 | Q75: =IF(P75>=80,"✅ High Quality",IF(P75>=60,"🟡 Acceptable",IF(P75>=40,"⚠️ Use with Caution","🔴 Insufficient"))) -> ✅ High Quality
B76: S | C76: Diversity | D76: Women in Total Workforce | E76: 11059 | F76: W | G76: employees | H76: 2022 | I76: Company ESG Report | J76: Smurfit Westrock 2024 Sustainability Report | L76: 25 | M76: 15 | N76: =_xlfn.XLOOKUP(H76,'E Data_Inventory'!$H$3:$H$240,'E Data_Inventory'!N$3:N$240) -> 20 | O76: 20 | P76: =L76+M76+N76+O76 -> 80 | Q76: =IF(P76>=80,"✅ High Quality",IF(P76>=60,"🟡 Acceptable",IF(P76>=40,"⚠️ Use with Caution","🔴 Insufficient"))) -> ✅ High Quality
B77: S | C77: Training | D77: Total Training Hours | E77: =$E$21*$E$5 -> 193270.66 | F77: S | G77: Hours | H77: 2024 | I77: Company ESG Report | J77: Westrock 2021 Sustainability Report | L77: 25 | M77: 15 | N77: =_xlfn.XLOOKUP(H77,'E Data_Inventory'!$H$3:$H$240,'E Data_Inventory'!N$3:N$240) -> 25 | O77: 20 | P77: =L77+M77+N77+O77 -> 85 | Q77: =IF(P77>=80,"✅ High Quality",IF(P77>=60,"🟡 Acceptable",IF(P77>=40,"⚠️ Use with Caution","🔴 Insufficient"))) -> ✅ High Quality
B78: S | C78: Diversity | D78: Women in Total Workforce | E78: 10525 | F78: W | G78: employees | H78: 2021 | I78: Company ESG Report | J78: Smurfit Westrock 2024 Sustainability Report | L78: 25 | M78: 15 | N78: =_xlfn.XLOOKUP(H78,'E Data_Inventory'!$H$3:$H$240,'E Data_Inventory'!N$3:N$240) -> 5 | O78: 20 | P78: =L78+M78+N78+O78 -> 65 | Q78: =IF(P78>=80,"✅ High Quality",IF(P78>=60,"🟡 Acceptable",IF(P78>=40,"⚠️ Use with Caution","🔴 Insufficient"))) -> 🟡 Acceptable
B79: S | C79: Workforce | D79: Turnover | E79: 5028 | F79: S | G79: employees | H79: 2024 | I79: Company ESG Report | J79: Westrock 2022 Sustainability Report | L79: 25 | M79: 15 | N79: =_xlfn.XLOOKUP(H79,'E Data_Inventory'!$H$3:$H$240,'E Data_Inventory'!N$3:N$240) -> 25 | O79: 20 | P79: =L79+M79+N79+O79 -> 85 | Q79: =IF(P79>=80,"✅ High Quality",IF(P79>=60,"🟡 Acceptable",IF(P79>=40,"⚠️ Use with Caution","🔴 Insufficient"))) -> ✅ High Quality
B80: S | C80: Diversity | D80: Women in Total Workforce | F80: W | G80: employees | H80: 2020 | I80: Company ESG Report | J80: Westrock 2021 Sustainability Report | L80: 25 | M80: 25 | N80: 25 | O80: 15 | P80: =L80+M80+N80+O80 -> 90 | Q80: =IF(P80>=80,"✅ High Quality",IF(P80>=60,"🟡 Acceptable",IF(P80>=40,"⚠️ Use with Caution","🔴 Insufficient"))) -> ✅ High Quality
B81: S | C81: Diversity | D81: Women in Senior Management | E81: 0.267 | F81: S | G81: % | H81: 2024 | I81: Company ESG Report | J81: Smurfit Kappa 2023 Sustainability Report | L81: 25 | M81: 15 | N81: =_xlfn.XLOOKUP(H81,'E Data_Inventory'!$H$3:$H$240,'E Data_Inventory'!N$3:N$240) -> 25 | O81: 20 | P81: =L81+M81+N81+O81 -> 85 | Q81: =IF(P81>=80,"✅ High Quality",IF(P81>=60,"🟡 Acceptable",IF(P81>=40,"⚠️ Use with Caution","🔴 Insufficient"))) -> ✅ High Quality
B82: S | C82: Diversity | D82: Women in Total Workforce | F82: W | G82: employees | H82: 2019 | I82: Company ESG Report | J82: Westrock 2021 Sustainability Report | L82: 25 | M82: 25 | N82: 25 | O82: 15 | P82: =L82+M82+N82+O82 -> 90 | Q82: =IF(P82>=80,"✅ High Quality",IF(P82>=60,"🟡 Acceptable",IF(P82>=40,"⚠️ Use with Caution","🔴 Insufficient"))) -> ✅ High Quality
B83: S | C83: Diversity | D83: Women in Total Workforce | E83: 9894.888 | F83: S | G83: employees | H83: 2024 | I83: Company ESG Report | J83: Smurfit Kappa 2021 Sustainability Report | L83: 25 | M83: 15 | N83: =_xlfn.XLOOKUP(H83,'E Data_Inventory'!$H$3:$H$240,'E Data_Inventory'!N$3:N$240) -> 25 | O83: 20 | P83: =L83+M83+N83+O83 -> 85 | Q83: =IF(P83>=80,"✅ High Quality",IF(P83>=60,"🟡 Acceptable",IF(P83>=40,"⚠️ Use with Caution","🔴 Insufficient"))) -> ✅ High Quality

Sheet G Data_Inventory 
A1: ESG DATA INVENTORY & QUALITY SCORING
A2: Company: Smurfit Westrock | D2: Industry: Paper & Packaging | E2: Reporting Year: 2024 | L2: 25=Assured / 15=Self-rep / 5=Est. | M2: 25=Full method / 15=Value only / 0=None | N2: 25=Current yr / 20=1yr old / 5=3+yr | O2: 25=Match / 15=<5% var / 0=No 2nd source | P2: SUM of K+L+M+N | Q2: Auto-calculated
A3: # | B3: Pillar (E/S/G/Financial) | C3: KPI Category | D3: KPI Name | E3: Value (Enter number) | F3: Buisness | G3: Unit | H3: Reporting Year | I3: Source Type | J3: Source URL / Citation | K3: Assurance Level | L3: Accuracy Score (0–25) | M3: Completeness Score (0–25) | N3: Timeliness Score (0–25) | O3: Consistency Score (0–25) | P3: TOTAL Quality Score (0–100) | Q3: Quality Grade | R3: Notes / Caveats
A4: 31 | B4: G | C4: Ethics | D4: Anti-corruption Policy in Place (Y/N) | E4: Yes | F4: SW | H4: 2024 | L4: 25 | M4: 25 | N4: 25 | O4: 15 | P4: =L4+M4+N4+O4 -> 90 | Q4: =IF(P4>=80,"✅ High Quality",IF(P4>=60,"🟡 Acceptable",IF(P4>=40,"⚠️ Use with Caution","🔴 Insufficient"))) -> ✅ High Quality
A5: 31 | B5: G | C5: Ethics | D5: Anti-corruption Policy in Place (Y/N) | E5: Yes | F5: W | H5: 2023 | L5: 25 | M5: 25 | N5: 25 | O5: 15 | P5: =L5+M5+N5+O5 -> 90 | Q5: =IF(P5>=80,"✅ High Quality",IF(P5>=60,"🟡 Acceptable",IF(P5>=40,"⚠️ Use with Caution","🔴 Insufficient"))) -> ✅ High Quality
A6: 31 | B6: G | C6: Ethics | D6: Anti-corruption Policy in Place (Y/N) | E6: Yes | F6: S | H6: 2023 | L6: 25 | M6: 25 | N6: 25 | O6: 15 | P6: =L6+M6+N6+O6 -> 90 | Q6: =IF(P6>=80,"✅ High Quality",IF(P6>=60,"🟡 Acceptable",IF(P6>=40,"⚠️ Use with Caution","🔴 Insufficient"))) -> ✅ High Quality
A7: 31 | B7: G | C7: Ethics | D7: Anti-corruption Policy in Place (Y/N) | E7: Yes | F7: W | H7: 2022 | L7: 25 | M7: 25 | N7: 25 | O7: 15 | P7: =L7+M7+N7+O7 -> 90 | Q7: =IF(P7>=80,"✅ High Quality",IF(P7>=60,"🟡 Acceptable",IF(P7>=40,"⚠️ Use with Caution","🔴 Insufficient"))) -> ✅ High Quality
A8: 31 | B8: G | C8: Ethics | D8: Anti-corruption Policy in Place (Y/N) | E8: Yes | F8: S | H8: 2022 | L8: 25 | M8: 25 | N8: 25 | O8: 15 | P8: =L8+M8+N8+O8 -> 90 | Q8: =IF(P8>=80,"✅ High Quality",IF(P8>=60,"🟡 Acceptable",IF(P8>=40,"⚠️ Use with Caution","🔴 Insufficient"))) -> ✅ High Quality
A9: 31 | B9: G | C9: Ethics | D9: Anti-corruption Policy in Place (Y/N) | E9: Yes | F9: W | H9: 2021 | L9: 25 | M9: 25 | N9: 25 | O9: 15 | P9: =L9+M9+N9+O9 -> 90 | Q9: =IF(P9>=80,"✅ High Quality",IF(P9>=60,"🟡 Acceptable",IF(P9>=40,"⚠️ Use with Caution","🔴 Insufficient"))) -> ✅ High Quality
A10: 31 | B10: G | C10: Ethics | D10: Anti-corruption Policy in Place (Y/N) | E10: Yes | F10: S | H10: 2021 | L10: 25 | M10: 25 | N10: 25 | O10: 15 | P10: =L10+M10+N10+O10 -> 90 | Q10: =IF(P10>=80,"✅ High Quality",IF(P10>=60,"🟡 Acceptable",IF(P10>=40,"⚠️ Use with Caution","🔴 Insufficient"))) -> ✅ High Quality
A11: 31 | B11: G | C11: Ethics | D11: Anti-corruption Policy in Place (Y/N) | E11: Yes | F11: W | H11: 2020 | L11: 25 | M11: 25 | N11: 25 | O11: 15 | P11: =L11+M11+N11+O11 -> 90 | Q11: =IF(P11>=80,"✅ High Quality",IF(P11>=60,"🟡 Acceptable",IF(P11>=40,"⚠️ Use with Caution","🔴 Insufficient"))) -> ✅ High Quality
A12: 31 | B12: G | C12: Ethics | D12: Anti-corruption Policy in Place (Y/N) | E12: Yes | F12: S | H12: 2020 | L12: 25 | M12: 25 | N12: 25 | O12: 15 | P12: =L12+M12+N12+O12 -> 90 | Q12: =IF(P12>=80,"✅ High Quality",IF(P12>=60,"🟡 Acceptable",IF(P12>=40,"⚠️ Use with Caution","🔴 Insufficient"))) -> ✅ High Quality
A13: 31 | B13: G | C13: Ethics | D13: Anti-corruption Policy in Place (Y/N) | E13: Yes | F13: W | H13: 2019 | L13: 25 | M13: 25 | N13: 25 | O13: 15 | P13: =L13+M13+N13+O13 -> 90 | Q13: =IF(P13>=80,"✅ High Quality",IF(P13>=60,"🟡 Acceptable",IF(P13>=40,"⚠️ Use with Caution","🔴 Insufficient"))) -> ✅ High Quality
A14: 31 | B14: G | C14: Ethics | D14: Anti-corruption Policy in Place (Y/N) | E14: Yes | F14: S | H14: 2019 | L14: 25 | M14: 25 | N14: 25 | O14: 15 | P14: =L14+M14+N14+O14 -> 90 | Q14: =IF(P14>=80,"✅ High Quality",IF(P14>=60,"🟡 Acceptable",IF(P14>=40,"⚠️ Use with Caution","🔴 Insufficient"))) -> ✅ High Quality
A15: 26 | B15: G | C15: Board | D15: Total Board Size | E15: 14 | F15: SW | G15: Directors | H15: 2024 | L15: 25 | M15: 25 | N15: 25 | O15: 15 | P15: =L15+M15+N15+O15 -> 90 | Q15: =IF(P15>=80,"✅ High Quality",IF(P15>=60,"🟡 Acceptable",IF(P15>=40,"⚠️ Use with Caution","🔴 Insufficient"))) -> ✅ High Quality
A16: 26 | B16: G | C16: Board | D16: Total Board Size | F16: W | G16: Directors | H16: 2023 | P16: =L16+M16+N16+O16 -> 0 | Q16: =IF(P16>=80,"✅ High Quality",IF(P16>=60,"🟡 Acceptable",IF(P16>=40,"⚠️ Use with Caution","🔴 Insufficient"))) -> 🔴 Insufficient
A17: 26 | B17: G | C17: Board | D17: Total Board Size | F17: S | G17: Directors | H17: 2023 | P17: =L17+M17+N17+O17 -> 0 | Q17: =IF(P17>=80,"✅ High Quality",IF(P17>=60,"🟡 Acceptable",IF(P17>=40,"⚠️ Use with Caution","🔴 Insufficient"))) -> 🔴 Insufficient
A18: 26 | B18: G | C18: Board | D18: Total Board Size | F18: W | G18: Directors | H18: 2022 | P18: =L18+M18+N18+O18 -> 0 | Q18: =IF(P18>=80,"✅ High Quality",IF(P18>=60,"🟡 Acceptable",IF(P18>=40,"⚠️ Use with Caution","🔴 Insufficient"))) -> 🔴 Insufficient
A19: 26 | B19: G | C19: Board | D19: Total Board Size | F19: S | G19: Directors | H19: 2022 | P19: =L19+M19+N19+O19 -> 0 | Q19: =IF(P19>=80,"✅ High Quality",IF(P19>=60,"🟡 Acceptable",IF(P19>=40,"⚠️ Use with Caution","🔴 Insufficient"))) -> 🔴 Insufficient
A20: 26 | B20: G | C20: Board | D20: Total Board Size | F20: W | G20: Directors | H20: 2021 | P20: =L20+M20+N20+O20 -> 0 | Q20: =IF(P20>=80,"✅ High Quality",IF(P20>=60,"🟡 Acceptable",IF(P20>=40,"⚠️ Use with Caution","🔴 Insufficient"))) -> 🔴 Insufficient
A21: 26 | B21: G | C21: Board | D21: Total Board Size | F21: S | G21: Directors | H21: 2021 | P21: =L21+M21+N21+O21 -> 0 | Q21: =IF(P21>=80,"✅ High Quality",IF(P21>=60,"🟡 Acceptable",IF(P21>=40,"⚠️ Use with Caution","🔴 Insufficient"))) -> 🔴 Insufficient
A22: 26 | B22: G | C22: Board | D22: Total Board Size | F22: W | G22: Directors | H22: 2020 | P22: =L22+M22+N22+O22 -> 0 | Q22: =IF(P22>=80,"✅ High Quality",IF(P22>=60,"🟡 Acceptable",IF(P22>=40,"⚠️ Use with Caution","🔴 Insufficient"))) -> 🔴 Insufficient
A23: 26 | B23: G | C23: Board | D23: Total Board Size | F23: S | G23: Directors | H23: 2020 | P23: =L23+M23+N23+O23 -> 0 | Q23: =IF(P23>=80,"✅ High Quality",IF(P23>=60,"🟡 Acceptable",IF(P23>=40,"⚠️ Use with Caution","🔴 Insufficient"))) -> 🔴 Insufficient
A24: 26 | B24: G | C24: Board | D24: Total Board Size | F24: W | G24: Directors | H24: 2019 | P24: =L24+M24+N24+O24 -> 0 | Q24: =IF(P24>=80,"✅ High Quality",IF(P24>=60,"🟡 Acceptable",IF(P24>=40,"⚠️ Use with Caution","🔴 Insufficient"))) -> 🔴 Insufficient
A25: 26 | B25: G | C25: Board | D25: Total Board Size | F25: S | G25: Directors | H25: 2019 | P25: =L25+M25+N25+O25 -> 0 | Q25: =IF(P25>=80,"✅ High Quality",IF(P25>=60,"🟡 Acceptable",IF(P25>=40,"⚠️ Use with Caution","🔴 Insufficient"))) -> 🔴 Insufficient
A26: 26 | B26: G | C26: Board | D26: Independent Directors | E26: 12 | F26: SW | G26: Directors | H26: 2024 | L26: 25 | M26: 25 | N26: 25 | O26: 15 | P26: =L26+M26+N26+O26 -> 90 | Q26: =IF(P26>=80,"✅ High Quality",IF(P26>=60,"🟡 Acceptable",IF(P26>=40,"⚠️ Use with Caution","🔴 Insufficient"))) -> ✅ High Quality
A27: 26 | B27: G | C27: Board | D27: Independent Directors | F27: W | G27: Directors | H27: 2023 | P27: =L27+M27+N27+O27 -> 0 | Q27: =IF(P27>=80,"✅ High Quality",IF(P27>=60,"🟡 Acceptable",IF(P27>=40,"⚠️ Use with Caution","🔴 Insufficient"))) -> 🔴 Insufficient
A28: 26 | B28: G | C28: Board | D28: Independent Directors | F28: S | G28: Directors | H28: 2023 | P28: =L28+M28+N28+O28 -> 0 | Q28: =IF(P28>=80,"✅ High Quality",IF(P28>=60,"🟡 Acceptable",IF(P28>=40,"⚠️ Use with Caution","🔴 Insufficient"))) -> 🔴 Insufficient
A29: 26 | B29: G | C29: Board | D29: Independent Directors | F29: W | G29: Directors | H29: 2022 | P29: =L29+M29+N29+O29 -> 0 | Q29: =IF(P29>=80,"✅ High Quality",IF(P29>=60,"🟡 Acceptable",IF(P29>=40,"⚠️ Use with Caution","🔴 Insufficient"))) -> 🔴 Insufficient
A30: 26 | B30: G | C30: Board | D30: Independent Directors | F30: S | G30: Directors | H30: 2022 | P30: =L30+M30+N30+O30 -> 0 | Q30: =IF(P30>=80,"✅ High Quality",IF(P30>=60,"🟡 Acceptable",IF(P30>=40,"⚠️ Use with Caution","🔴 Insufficient"))) -> 🔴 Insufficient
A31: 26 | B31: G | C31: Board | D31: Independent Directors | F31: W | G31: Directors | H31: 2021 | P31: =L31+M31+N31+O31 -> 0 | Q31: =IF(P31>=80,"✅ High Quality",IF(P31>=60,"🟡 Acceptable",IF(P31>=40,"⚠️ Use with Caution","🔴 Insufficient"))) -> 🔴 Insufficient
A32: 26 | B32: G | C32: Board | D32: Independent Directors | F32: S | G32: Directors | H32: 2021 | P32: =L32+M32+N32+O32 -> 0 | Q32: =IF(P32>=80,"✅ High Quality",IF(P32>=60,"🟡 Acceptable",IF(P32>=40,"⚠️ Use with Caution","🔴 Insufficient"))) -> 🔴 Insufficient
A33: 26 | B33: G | C33: Board | D33: Independent Directors | F33: W | G33: Directors | H33: 2020 | P33: =L33+M33+N33+O33 -> 0 | Q33: =IF(P33>=80,"✅ High Quality",IF(P33>=60,"🟡 Acceptable",IF(P33>=40,"⚠️ Use with Caution","🔴 Insufficient"))) -> 🔴 Insufficient
A34: 26 | B34: G | C34: Board | D34: Independent Directors | F34: S | G34: Directors | H34: 2020 | P34: =L34+M34+N34+O34 -> 0 | Q34: =IF(P34>=80,"✅ High Quality",IF(P34>=60,"🟡 Acceptable",IF(P34>=40,"⚠️ Use with Caution","🔴 Insufficient"))) -> 🔴 Insufficient
A35: 26 | B35: G | C35: Board | D35: Independent Directors | F35: W | G35: Directors | H35: 2019 | P35: =L35+M35+N35+O35 -> 0 | Q35: =IF(P35>=80,"✅ High Quality",IF(P35>=60,"🟡 Acceptable",IF(P35>=40,"⚠️ Use with Caution","🔴 Insufficient"))) -> 🔴 Insufficient
A36: 26 | B36: G | C36: Board | D36: Independent Directors | F36: S | G36: Directors | H36: 2019 | P36: =L36+M36+N36+O36 -> 0 | Q36: =IF(P36>=80,"✅ High Quality",IF(P36>=60,"🟡 Acceptable",IF(P36>=40,"⚠️ Use with Caution","🔴 Insufficient"))) -> 🔴 Insufficient
A37: 26 | B37: G | C37: Board | D37: Board Independence (% Independent Directors) | E37: =E26/E15 -> 0.85714286 | F37: SW | G37: % | H37: 2024 | L37: 25 | M37: 25 | N37: 25 | O37: 15 | P37: =L37+M37+N37+O37 -> 90 | Q37: =IF(P37>=80,"✅ High Quality",IF(P37>=60,"🟡 Acceptable",IF(P37>=40,"⚠️ Use with Caution","🔴 Insufficient"))) -> ✅ High Quality
A38: 26 | B38: G | C38: Board | D38: Board Independence (% Independent Directors) | F38: W | G38: % | H38: 2023 | P38: =L38+M38+N38+O38 -> 0 | Q38: =IF(P38>=80,"✅ High Quality",IF(P38>=60,"🟡 Acceptable",IF(P38>=40,"⚠️ Use with Caution","🔴 Insufficient"))) -> 🔴 Insufficient
A39: 26 | B39: G | C39: Board | D39: Board Independence (% Independent Directors) | F39: S | G39: % | H39: 2023 | P39: =L39+M39+N39+O39 -> 0 | Q39: =IF(P39>=80,"✅ High Quality",IF(P39>=60,"🟡 Acceptable",IF(P39>=40,"⚠️ Use with Caution","🔴 Insufficient"))) -> 🔴 Insufficient
A40: 26 | B40: G | C40: Board | D40: Board Independence (% Independent Directors) | F40: W | G40: % | H40: 2022 | P40: =L40+M40+N40+O40 -> 0 | Q40: =IF(P40>=80,"✅ High Quality",IF(P40>=60,"🟡 Acceptable",IF(P40>=40,"⚠️ Use with Caution","🔴 Insufficient"))) -> 🔴 Insufficient
A41: 26 | B41: G | C41: Board | D41: Board Independence (% Independent Directors) | F41: S | G41: % | H41: 2022 | P41: =L41+M41+N41+O41 -> 0 | Q41: =IF(P41>=80,"✅ High Quality",IF(P41>=60,"🟡 Acceptable",IF(P41>=40,"⚠️ Use with Caution","🔴 Insufficient"))) -> 🔴 Insufficient
A42: 26 | B42: G | C42: Board | D42: Board Independence (% Independent Directors) | F42: W | G42: % | H42: 2021 | P42: =L42+M42+N42+O42 -> 0 | Q42: =IF(P42>=80,"✅ High Quality",IF(P42>=60,"🟡 Acceptable",IF(P42>=40,"⚠️ Use with Caution","🔴 Insufficient"))) -> 🔴 Insufficient
A43: 26 | B43: G | C43: Board | D43: Board Independence (% Independent Directors) | F43: S | G43: % | H43: 2021 | P43: =L43+M43+N43+O43 -> 0 | Q43: =IF(P43>=80,"✅ High Quality",IF(P43>=60,"🟡 Acceptable",IF(P43>=40,"⚠️ Use with Caution","🔴 Insufficient"))) -> 🔴 Insufficient
A44: 26 | B44: G | C44: Board | D44: Board Independence (% Independent Directors) | F44: W | G44: % | H44: 2020 | P44: =L44+M44+N44+O44 -> 0 | Q44: =IF(P44>=80,"✅ High Quality",IF(P44>=60,"🟡 Acceptable",IF(P44>=40,"⚠️ Use with Caution","🔴 Insufficient"))) -> 🔴 Insufficient
A45: 26 | B45: G | C45: Board | D45: Board Independence (% Independent Directors) | F45: S | G45: % | H45: 2020 | P45: =L45+M45+N45+O45 -> 0 | Q45: =IF(P45>=80,"✅ High Quality",IF(P45>=60,"🟡 Acceptable",IF(P45>=40,"⚠️ Use with Caution","🔴 Insufficient"))) -> 🔴 Insufficient
A46: 26 | B46: G | C46: Board | D46: Board Independence (% Independent Directors) | F46: W | G46: % | H46: 2019 | P46: =L46+M46+N46+O46 -> 0 | Q46: =IF(P46>=80,"✅ High Quality",IF(P46>=60,"🟡 Acceptable",IF(P46>=40,"⚠️ Use with Caution","🔴 Insufficient"))) -> 🔴 Insufficient
A47: 26 | B47: G | C47: Board | D47: Board Independence (% Independent Directors) | F47: S | G47: % | H47: 2019 | P47: =L47+M47+N47+O47 -> 0 | Q47: =IF(P47>=80,"✅ High Quality",IF(P47>=60,"🟡 Acceptable",IF(P47>=40,"⚠️ Use with Caution","🔴 Insufficient"))) -> 🔴 Insufficient
A48: 32 | B48: G | C48: Compliance | D48: ESG Assurance Provider | E48: Yes | F48: SW | H48: 2024 | L48: 25 | M48: 25 | N48: 25 | O48: 15 | P48: =L48+M48+N48+O48 -> 90 | Q48: =IF(P48>=80,"✅ High Quality",IF(P48>=60,"🟡 Acceptable",IF(P48>=40,"⚠️ Use with Caution","🔴 Insufficient"))) -> ✅ High Quality
A49: 32 | B49: G | C49: Compliance | D49: ESG Assurance Provider | E49: Yes | F49: W | H49: 2023 | L49: 25 | M49: 25 | N49: 25 | O49: 15 | P49: =L49+M49+N49+O49 -> 90 | Q49: =IF(P49>=80,"✅ High Quality",IF(P49>=60,"🟡 Acceptable",IF(P49>=40,"⚠️ Use with Caution","🔴 Insufficient"))) -> ✅ High Quality
A50: 32 | B50: G | C50: Compliance | D50: ESG Assurance Provider | E50: Yes | F50: S | H50: 2023 | L50: 25 | M50: 25 | N50: 25 | O50: 15 | P50: =L50+M50+N50+O50 -> 90 | Q50: =IF(P50>=80,"✅ High Quality",IF(P50>=60,"🟡 Acceptable",IF(P50>=40,"⚠️ Use with Caution","🔴 Insufficient"))) -> ✅ High Quality
A51: 32 | B51: G | C51: Compliance | D51: ESG Assurance Provider | E51: Yes | F51: W | H51: 2022 | L51: 25 | M51: 25 | N51: 25 | O51: 15 | P51: =L51+M51+N51+O51 -> 90 | Q51: =IF(P51>=80,"✅ High Quality",IF(P51>=60,"🟡 Acceptable",IF(P51>=40,"⚠️ Use with Caution","🔴 Insufficient"))) -> ✅ High Quality
A52: 32 | B52: G | C52: Compliance | D52: ESG Assurance Provider | E52: Yes | F52: S | H52: 2022 | L52: 25 | M52: 25 | N52: 25 | O52: 15 | P52: =L52+M52+N52+O52 -> 90 | Q52: =IF(P52>=80,"✅ High Quality",IF(P52>=60,"🟡 Acceptable",IF(P52>=40,"⚠️ Use with Caution","🔴 Insufficient"))) -> ✅ High Quality
A53: 32 | B53: G | C53: Compliance | D53: ESG Assurance Provider | E53: Yes | F53: W | H53: 2021 | L53: 25 | M53: 25 | N53: 25 | O53: 15 | P53: =L53+M53+N53+O53 -> 90 | Q53: =IF(P53>=80,"✅ High Quality",IF(P53>=60,"🟡 Acceptable",IF(P53>=40,"⚠️ Use with Caution","🔴 Insufficient"))) -> ✅ High Quality
A54: 32 | B54: G | C54: Compliance | D54: ESG Assurance Provider | E54: Yes | F54: S | H54: 2021 | L54: 25 | M54: 25 | N54: 25 | O54: 15 | P54: =L54+M54+N54+O54 -> 90 | Q54: =IF(P54>=80,"✅ High Quality",IF(P54>=60,"🟡 Acceptable",IF(P54>=40,"⚠️ Use with Caution","🔴 Insufficient"))) -> ✅ High Quality
A55: 32 | B55: G | C55: Compliance | D55: ESG Assurance Provider | E55: Yes | F55: W | H55: 2020 | L55: 25 | M55: 25 | N55: 25 | O55: 15 | P55: =L55+M55+N55+O55 -> 90 | Q55: =IF(P55>=80,"✅ High Quality",IF(P55>=60,"🟡 Acceptable",IF(P55>=40,"⚠️ Use with Caution","🔴 Insufficient"))) -> ✅ High Quality
A56: 32 | B56: G | C56: Compliance | D56: ESG Assurance Provider | E56: Yes | F56: S | H56: 2020 | L56: 25 | M56: 25 | N56: 25 | O56: 15 | P56: =L56+M56+N56+O56 -> 90 | Q56: =IF(P56>=80,"✅ High Quality",IF(P56>=60,"🟡 Acceptable",IF(P56>=40,"⚠️ Use with Caution","🔴 Insufficient"))) -> ✅ High Quality
A57: 32 | B57: G | C57: Compliance | D57: ESG Assurance Provider | E57: Yes | F57: W | H57: 2019 | L57: 25 | M57: 25 | N57: 25 | O57: 15 | P57: =L57+M57+N57+O57 -> 90 | Q57: =IF(P57>=80,"✅ High Quality",IF(P57>=60,"🟡 Acceptable",IF(P57>=40,"⚠️ Use with Caution","🔴 Insufficient"))) -> ✅ High Quality
A58: 32 | B58: G | C58: Compliance | D58: ESG Assurance Provider | E58: Yes | F58: S | H58: 2019 | L58: 25 | M58: 25 | N58: 25 | O58: 15 | P58: =L58+M58+N58+O58 -> 90 | Q58: =IF(P58>=80,"✅ High Quality",IF(P58>=60,"🟡 Acceptable",IF(P58>=40,"⚠️ Use with Caution","🔴 Insufficient"))) -> ✅ High Quality
A59: 27 | B59: G | C59: Board | D59: Women on Board | E59: 0.43 | F59: SW | G59: % | H59: 2024 | L59: 25 | M59: 25 | N59: 25 | O59: 15 | P59: =L59+M59+N59+O59 -> 90 | Q59: =IF(P59>=80,"✅ High Quality",IF(P59>=60,"🟡 Acceptable",IF(P59>=40,"⚠️ Use with Caution","🔴 Insufficient"))) -> ✅ High Quality
A60: 27 | B60: G | C60: Board | D60: Women on Board | F60: W | G60: % | H60: 2023 | L60: 25 | M60: 25 | N60: 25 | O60: 15 | P60: =L60+M60+N60+O60 -> 90 | Q60: =IF(P60>=80,"✅ High Quality",IF(P60>=60,"🟡 Acceptable",IF(P60>=40,"⚠️ Use with Caution","🔴 Insufficient"))) -> ✅ High Quality
A61: 27 | B61: G | C61: Board | D61: Women on Board | F61: S | G61: % | H61: 2023 | L61: 25 | M61: 25 | N61: 25 | O61: 15 | P61: =L61+M61+N61+O61 -> 90 | Q61: =IF(P61>=80,"✅ High Quality",IF(P61>=60,"🟡 Acceptable",IF(P61>=40,"⚠️ Use with Caution","🔴 Insufficient"))) -> ✅ High Quality
A62: 27 | B62: G | C62: Board | D62: Women on Board | F62: W | G62: % | H62: 2022 | L62: 25 | M62: 25 | N62: 25 | O62: 15 | P62: =L62+M62+N62+O62 -> 90 | Q62: =IF(P62>=80,"✅ High Quality",IF(P62>=60,"🟡 Acceptable",IF(P62>=40,"⚠️ Use with Caution","🔴 Insufficient"))) -> ✅ High Quality
A63: 27 | B63: G | C63: Board | D63: Women on Board | F63: S | G63: % | H63: 2022 | L63: 25 | M63: 25 | N63: 25 | O63: 15 | P63: =L63+M63+N63+O63 -> 90 | Q63: =IF(P63>=80,"✅ High Quality",IF(P63>=60,"🟡 Acceptable",IF(P63>=40,"⚠️ Use with Caution","🔴 Insufficient"))) -> ✅ High Quality
A64: 27 | B64: G | C64: Board | D64: Women on Board | F64: W | G64: % | H64: 2021 | L64: 25 | M64: 25 | N64: 25 | O64: 15 | P64: =L64+M64+N64+O64 -> 90 | Q64: =IF(P64>=80,"✅ High Quality",IF(P64>=60,"🟡 Acceptable",IF(P64>=40,"⚠️ Use with Caution","🔴 Insufficient"))) -> ✅ High Quality
A65: 27 | B65: G | C65: Board | D65: Women on Board | F65: S | G65: % | H65: 2021 | L65: 25 | M65: 25 | N65: 25 | O65: 15 | P65: =L65+M65+N65+O65 -> 90 | Q65: =IF(P65>=80,"✅ High Quality",IF(P65>=60,"🟡 Acceptable",IF(P65>=40,"⚠️ Use with Caution","🔴 Insufficient"))) -> ✅ High Quality
A66: 27 | B66: G | C66: Board | D66: Women on Board | F66: W | G66: % | H66: 2020 | L66: 25 | M66: 25 | N66: 25 | O66: 15 | P66: =L66+M66+N66+O66 -> 90 | Q66: =IF(P66>=80,"✅ High Quality",IF(P66>=60,"🟡 Acceptable",IF(P66>=40,"⚠️ Use with Caution","🔴 Insufficient"))) -> ✅ High Quality
A67: 27 | B67: G | C67: Board | D67: Women on Board | F67: S | G67: % | H67: 2020 | L67: 25 | M67: 25 | N67: 25 | O67: 15 | P67: =L67+M67+N67+O67 -> 90 | Q67: =IF(P67>=80,"✅ High Quality",IF(P67>=60,"🟡 Acceptable",IF(P67>=40,"⚠️ Use with Caution","🔴 Insufficient"))) -> ✅ High Quality
A68: 27 | B68: G | C68: Board | D68: Women on Board | F68: W | G68: % | H68: 2019 | L68: 25 | M68: 25 | N68: 25 | O68: 15 | P68: =L68+M68+N68+O68 -> 90 | Q68: =IF(P68>=80,"✅ High Quality",IF(P68>=60,"🟡 Acceptable",IF(P68>=40,"⚠️ Use with Caution","🔴 Insufficient"))) -> ✅ High Quality
A69: 27 | B69: G | C69: Board | D69: Women on Board | F69: S | G69: % | H69: 2019 | L69: 25 | M69: 25 | N69: 25 | O69: 15 | P69: =L69+M69+N69+O69 -> 90 | Q69: =IF(P69>=80,"✅ High Quality",IF(P69>=60,"🟡 Acceptable",IF(P69>=40,"⚠️ Use with Caution","🔴 Insufficient"))) -> ✅ High Quality
A70: 27 | B70: G | C70: Board | D70: Board Average Age | E70: 63.5 | F70: SW | G70: Years | H70: 2024 | L70: 25 | M70: 25 | N70: 25 | O70: 15 | P70: =L70+M70+N70+O70 -> 90 | Q70: =IF(P70>=80,"✅ High Quality",IF(P70>=60,"🟡 Acceptable",IF(P70>=40,"⚠️ Use with Caution","🔴 Insufficient"))) -> ✅ High Quality

Sheet P Data_Inventory
A1: Pillar (E/S/G/Financial/Performance) | B1: KPI Category | C1: KPI Name | D1: Value (Enter number) | E1: Buisness | F1: Unit | G1: Reporting Year | H1: Source Type | I1: Source URL / Citation | J1: Assurance Level | K1: Accuracy Score (0–25) | L1: Completeness Score (0–25) | M1: Timeliness Score (0–25) | N1: Consistency Score (0–25) | O1: TOTAL Quality Score (0–100) | P1: Quality Grade | Q1: Notes / Caveats
A2: P | B2: Production | C2: Total Production | D2: 14918000 | E2: S | F2: Tons | G2: 2024 | K2: 25 | L2: 25 | M2: 25 | N2: 0 | O2: =K2+L2+M2+N2 -> 75 | P2: =IF(O2>=80,"✅ High Quality",IF(O2>=60,"🟡 Acceptable",IF(O2>=40,"⚠️ Use with Caution","🔴 Insufficient"))) -> 🟡 Acceptable
A3: P | B3: Production | C3: Total Production | D3: 14539000 | E3: S | F3: Tons | G3: 2023 | K3: 25 | L3: 25 | M3: 25 | N3: 0 | O3: =K3+L3+M3+N3 -> 75 | P3: =IF(O3>=80,"✅ High Quality",IF(O3>=60,"🟡 Acceptable",IF(O3>=40,"⚠️ Use with Caution","🔴 Insufficient"))) -> 🟡 Acceptable
A4: P | B4: Production | C4: Total Production | D4: 15373000 | E4: S | F4: Tons | G4: 2022 | K4: 25 | L4: 25 | M4: 25 | N4: 0 | O4: =K4+L4+M4+N4 -> 75 | P4: =IF(O4>=80,"✅ High Quality",IF(O4>=60,"🟡 Acceptable",IF(O4>=40,"⚠️ Use with Caution","🔴 Insufficient"))) -> 🟡 Acceptable
A5: P | B5: Production | C5: Total Production | D5: 15337900 | E5: S | F5: Tons | G5: 2021 | K5: 25 | L5: 25 | M5: 25 | N5: 0 | O5: =K5+L5+M5+N5 -> 75 | P5: =IF(O5>=80,"✅ High Quality",IF(O5>=60,"🟡 Acceptable",IF(O5>=40,"⚠️ Use with Caution","🔴 Insufficient"))) -> 🟡 Acceptable
A6: P | B6: Production | C6: Total Production | D6: 14510140 | E6: S | F6: Tons | G6: 2020 | K6: 25 | L6: 25 | M6: 25 | N6: 0 | O6: =K6+L6+M6+N6 -> 75 | P6: =IF(O6>=80,"✅ High Quality",IF(O6>=60,"🟡 Acceptable",IF(O6>=40,"⚠️ Use with Caution","🔴 Insufficient"))) -> 🟡 Acceptable
A7: P | B7: Production | C7: Total Production | D7: 14350200 | E7: S | F7: Tons | G7: 2019 | K7: 25 | L7: 25 | M7: 25 | N7: 0 | O7: =K7+L7+M7+N7 -> 75 | P7: =IF(O7>=80,"✅ High Quality",IF(O7>=60,"🟡 Acceptable",IF(O7>=40,"⚠️ Use with Caution","🔴 Insufficient"))) -> 🟡 Acceptable
A8: P | B8: Production | C8: Paper Production | D8: 13021711 | E8: W | F8: Tons | G8: 2024 | K8: 25 | L8: 25 | M8: 25 | N8: 0 | O8: =K8+L8+M8+N8 -> 75 | P8: =IF(O8>=80,"✅ High Quality",IF(O8>=60,"🟡 Acceptable",IF(O8>=40,"⚠️ Use with Caution","🔴 Insufficient"))) -> 🟡 Acceptable
A9: P | B9: Production | C9: Paper Production | D9: 12820853 | E9: W | F9: Tons | G9: 2023 | K9: 25 | L9: 25 | M9: 25 | N9: 0 | O9: =K9+L9+M9+N9 -> 75 | P9: =IF(O9>=80,"✅ High Quality",IF(O9>=60,"🟡 Acceptable",IF(O9>=40,"⚠️ Use with Caution","🔴 Insufficient"))) -> 🟡 Acceptable
A10: P | B10: Production | C10: Paper Production | D10: 14437610 | E10: W | F10: Tons | G10: 2022 | K10: 25 | L10: 25 | M10: 25 | N10: 0 | O10: =K10+L10+M10+N10 -> 75 | P10: =IF(O10>=80,"✅ High Quality",IF(O10>=60,"🟡 Acceptable",IF(O10>=40,"⚠️ Use with Caution","🔴 Insufficient"))) -> 🟡 Acceptable
A11: P | B11: Production | C11: Paper Production | D11: 14776992 | E11: W | F11: Tons | G11: 2021 | K11: 25 | L11: 25 | M11: 25 | N11: 0 | O11: =K11+L11+M11+N11 -> 75 | P11: =IF(O11>=80,"✅ High Quality",IF(O11>=60,"🟡 Acceptable",IF(O11>=40,"⚠️ Use with Caution","🔴 Insufficient"))) -> 🟡 Acceptable
A12: P | B12: Production | C12: Paper Production | D12: 14463318 | E12: W | F12: Tons | G12: 2020 | K12: 25 | L12: 25 | M12: 25 | N12: 0 | O12: =K12+L12+M12+N12 -> 75 | P12: =IF(O12>=80,"✅ High Quality",IF(O12>=60,"🟡 Acceptable",IF(O12>=40,"⚠️ Use with Caution","🔴 Insufficient"))) -> 🟡 Acceptable
A13: P | B13: Production | C13: Paper Production | D13: 15218523 | E13: W | F13: Tons | G13: 2019 | K13: 25 | L13: 25 | M13: 25 | N13: 0 | O13: =K13+L13+M13+N13 -> 75 | P13: =IF(O13>=80,"✅ High Quality",IF(O13>=60,"🟡 Acceptable",IF(O13>=40,"⚠️ Use with Caution","🔴 Insufficient"))) -> 🟡 Acceptable
A14: P | B14: Production | C14: Paper Production | D14: =5994000+1600000 -> 7594000 | E14: S | F14: Tons | G14: 2024 | K14: 25 | L14: 25 | M14: 25 | N14: 0 | O14: =K14+L14+M14+N14 -> 75 | P14: =IF(O14>=80,"✅ High Quality",IF(O14>=60,"🟡 Acceptable",IF(O14>=40,"⚠️ Use with Caution","🔴 Insufficient"))) -> 🟡 Acceptable
A15: P | B15: Production | C15: Paper Production | D15: 7220000 | E15: S | F15: Tons | G15: 2023 | K15: 25 | L15: 25 | M15: 25 | N15: 0 | O15: =K15+L15+M15+N15 -> 75 | P15: =IF(O15>=80,"✅ High Quality",IF(O15>=60,"🟡 Acceptable",IF(O15>=40,"⚠️ Use with Caution","🔴 Insufficient"))) -> 🟡 Acceptable
A16: P | B16: Production | C16: Paper Production | D16: 7523000 | E16: S | F16: Tons | G16: 2022 | K16: 25 | L16: 25 | M16: 25 | N16: 0 | O16: =K16+L16+M16+N16 -> 75 | P16: =IF(O16>=80,"✅ High Quality",IF(O16>=60,"🟡 Acceptable",IF(O16>=40,"⚠️ Use with Caution","🔴 Insufficient"))) -> 🟡 Acceptable
A17: P | B17: Production | C17: Paper Production | D17: 7282000 | E17: S | F17: Tons | G17: 2021 | K17: 25 | L17: 25 | M17: 25 | N17: 0 | O17: =K17+L17+M17+N17 -> 75 | P17: =IF(O17>=80,"✅ High Quality",IF(O17>=60,"🟡 Acceptable",IF(O17>=40,"⚠️ Use with Caution","🔴 Insufficient"))) -> 🟡 Acceptable
A18: P | B18: Production | C18: Paper Production | D18: 7049000 | E18: S | F18: Tons | G18: 2020 | K18: 25 | L18: 25 | M18: 25 | N18: 0 | O18: =K18+L18+M18+N18 -> 75 | P18: =IF(O18>=80,"✅ High Quality",IF(O18>=60,"🟡 Acceptable",IF(O18>=40,"⚠️ Use with Caution","🔴 Insufficient"))) -> 🟡 Acceptable
A19: P | B19: Production | C19: Paper Production | D19: 6954000 | E19: S | F19: Tons | G19: 2019 | K19: 25 | L19: 25 | M19: 25 | N19: 0 | O19: =K19+L19+M19+N19 -> 75 | P19: =IF(O19>=80,"✅ High Quality",IF(O19>=60,"🟡 Acceptable",IF(O19>=40,"⚠️ Use with Caution","🔴 Insufficient"))) -> 🟡 Acceptable
A20: P | B20: Production | C20: Packaging Production | D20: 7324000 | E20: S | F20: Tons | G20: 2024 | K20: 25 | L20: 25 | M20: 25 | N20: 0 | O20: =K20+L20+M20+N20 -> 75 | P20: =IF(O20>=80,"✅ High Quality",IF(O20>=60,"🟡 Acceptable",IF(O20>=40,"⚠️ Use with Caution","🔴 Insufficient"))) -> 🟡 Acceptable
A21: P | B21: Production | C21: Packaging Production | D21: 7319000 | E21: S | F21: Tons | G21: 2023 | K21: 25 | L21: 25 | M21: 25 | N21: 0 | O21: =K21+L21+M21+N21 -> 75 | P21: =IF(O21>=80,"✅ High Quality",IF(O21>=60,"🟡 Acceptable",IF(O21>=40,"⚠️ Use with Caution","🔴 Insufficient"))) -> 🟡 Acceptable
A22: P | B22: Production | C22: Packaging Production | D22: 7850000 | E22: S | F22: Tons | G22: 2022 | K22: 25 | L22: 25 | M22: 25 | N22: 0 | O22: =K22+L22+M22+N22 -> 75 | P22: =IF(O22>=80,"✅ High Quality",IF(O22>=60,"🟡 Acceptable",IF(O22>=40,"⚠️ Use with Caution","🔴 Insufficient"))) -> 🟡 Acceptable
A23: P | B23: Production | C23: Packaging Production | D23: 8055900 | E23: S | F23: Tons | G23: 2021 | K23: 25 | L23: 25 | M23: 25 | N23: 0 | O23: =K23+L23+M23+N23 -> 75 | P23: =IF(O23>=80,"✅ High Quality",IF(O23>=60,"🟡 Acceptable",IF(O23>=40,"⚠️ Use with Caution","🔴 Insufficient"))) -> 🟡 Acceptable
A24: P | B24: Production | C24: Packaging Production | D24: 7461140 | E24: S | F24: Tons | G24: 2020 | K24: 25 | L24: 25 | M24: 25 | N24: 0 | O24: =K24+L24+M24+N24 -> 75 | P24: =IF(O24>=80,"✅ High Quality",IF(O24>=60,"🟡 Acceptable",IF(O24>=40,"⚠️ Use with Caution","🔴 Insufficient"))) -> 🟡 Acceptable
A25: P | B25: Production | C25: Packaging Production | D25: 7396200 | E25: S | F25: Tons | G25: 2019 | K25: 25 | L25: 25 | M25: 25 | N25: 0 | O25: =K25+L25+M25+N25 -> 75 | P25: =IF(O25>=80,"✅ High Quality",IF(O25>=60,"🟡 Acceptable",IF(O25>=40,"⚠️ Use with Caution","🔴 Insufficient"))) -> 🟡 Acceptable
A26: P | B26: Performance | C26: Market Capitalization | D26: 9179.1 | E26: W | F26: USD Millions | G26: 2023 | K26: 25 | L26: 25 | M26: 25 | N26: 0 | O26: =K26+L26+M26+N26 -> 75 | P26: =IF(O26>=80,"✅ High Quality",IF(O26>=60,"🟡 Acceptable",IF(O26>=40,"⚠️ Use with Caution","🔴 Insufficient"))) -> 🟡 Acceptable
... A70: F | B70: Performance | C70: Annual Revenue | D70: 9048 | E70: S | F70: USD Millions | G70: 2019 | K70: 20 | L70: 15 | M70: 25 | N70: 0 | O70: =K70+L70+M70+N70 -> 60 | P70: =IF(O70>=80,"✅ High Quality",IF(O70>=60,"🟡 Acceptable",IF(O70>=40,"⚠️ Use with Caution","🔴 Insufficient"))) -> 🟡 Acceptable

Sheet 3_Cross-Source Compare
A1: CROSS-SOURCE COMPARISON — 3 KPIs (1 Environmental · 1 Social · 1 Governance)
A2: PURPOSE: Pull the same KPI from 3 different sources. Calculate the variance. Write your explanation. This becomes your Methodology section.
A4: ENVIRONMENTAL KPI
A5: KPI Being Compared:
A6: Field | B6: Source 1 (Company Report) | C6: Source 2 (Bloomberg / CDP) | D6: Source 3 (Other Database) | E6: Variance
A7: Value | B7: [Enter value] | C7: [Enter value] | D7: [Enter value] | E7: =IF(AND(ISNUMBER(B7),ISNUMBER(C7)),ABS(B7-C7)/ABS(B7),"N/A") -> N/A
A8: Unit / Definition | B8: [Enter unit] | C8: [Enter unit] | D8: [Enter unit]
A9: Reporting Year | B9: [Enter year] | C9: [Enter year] | D9: [Enter year]
A10: Assurance Level | B10: [None/Limited/Reasonable] | C10: [None/Limited/Reasonable] | D10: [None/Limited/Reasonable]
A11: Source URL / Citation | B11: [Enter URL or citation] | C11: [Enter URL or citation] | D11: [Enter URL or citation]
A12: ⬇ YOUR EXPLANATION OF DISCREPANCY (write below — this becomes part of your capstone project)
A13: [Enter your explanation here: What caused the discrepancy? Different boundary? Different fiscal year? Restatement? Methodology difference? Which source do you trust most and why?]
A16: SOCIAL KPI
A17: KPI Being Compared:
A18: Field | B18: Source 1 (Company Report) | C18: Source 2 (Bloomberg / CDP) | D18: Source 3 (Other Database) | E18: Variance
A19: Value | B19: [Enter value] | C19: [Enter value] | D19: [Enter value] | E19: =IF(AND(ISNUMBER(B19),ISNUMBER(C19)),ABS(B19-C19)/ABS(B19),"N/A") -> N/A
A20: Unit / Definition | B20: [Enter unit] | C20: [Enter unit] | D20: [Enter unit]
A21: Reporting Year | B21: [Enter year] | C21: [Enter year] | D21: [Enter year]
A22: Assurance Level | B22: [None/Limited/Reasonable] | C22: [None/Limited/Reasonable] | D22: [None/Limited/Reasonable]
A23: Source URL / Citation | B23: [Enter URL or citation] | C23: [Enter URL or citation] | D23: [Enter URL or citation]
A24: ⬇ YOUR EXPLANATION OF DISCREPANCY (write below — this becomes part of your capstone project)
A25: [Enter your explanation here: What caused the discrepancy? Different boundary? Different fiscal year? Restatement? Methodology difference? Which source do you trust most and why?]
A28: GOVERNANCE KPI
A29: KPI Being Compared:
A30: Field | B30: Source 1 (Company Report) | C30: Source 2 (Bloomberg / CDP) | D30: Source 3 (Other Database) | E30: Variance
A31: Value | B31: [Enter value] | C31: [Enter value] | D31: [Enter value] | E31: =IF(AND(ISNUMBER(B31),ISNUMBER(C31)),ABS(B31-C31)/ABS(B31),"N/A") -> N/A
A32: Unit / Definition | B32: [Enter unit] | C32: [Enter unit] | D32: [Enter unit]
A33: Reporting Year | B33: [Enter year] | C33: [Enter year] | D33: [Enter year]
A34: Assurance Level | B34: [None/Limited/Reasonable] | C34: [None/Limited/Reasonable] | D34: [None/Limited/Reasonable]
A35: Source URL / Citation | B35: [Enter URL or citation] | C35: [Enter URL or citation] | D35: [Enter URL or citation]
A36: ⬇ YOUR EXPLANATION OF DISCREPANCY (write below — this becomes part of your capstone project)
A37: [Enter your explanation here: What caused the discrepancy? Different boundary? Different fiscal year? Restatement? Methodology difference? Which source do you trust most and why?]

Sheet 4_Summary
A1: ESG DATA QUALITY — SUMMARY
A2: Company: [Auto-updates from Data Inventory] | This sheet summarizes quality scores and coverage from your data entry.
A4: SECTION 1 — KPI COUNT BY PILLAR
A5: Pillar | B5: Total KPIs Entered | C5: Avg Quality Score | D5: High Quality | E5: Acceptable | F5: Needs Improvement
A6: Environmental | B6: =COUNTA('E Data_Inventory'!D4:D250) -> 237 | C6: =IFERROR(AVERAGE('E Data_Inventory'!P4:P250),"No data") -> 61.962025 | D6: =COUNTIF('E Data_Inventory'!Q4:Q245,"✅ High Quality") -> 58 | E6: =COUNTIF('E Data_Inventory'!Q4:Q245,"🟡 Acceptable") -> 117 | F6: =COUNTIF('E Data_Inventory'!Q4:Q245,"⚠️ Use with Caution")+COUNTIF('E Data_Inventory'!Q4:Q245,"🔴 Insufficient") -> 62
A7: Social | B7: =COUNTA('S Data_Inventory '!D4:D90) -> 80 | C7: =IFERROR(AVERAGE('S Data_Inventory '!P4:P90),"No data") -> 77.0625 | D7: =COUNTIF('S Data_Inventory '!Q4:Q94,"✅ High Quality") -> 49 | E7: =COUNTIF('S Data_Inventory '!Q4:Q94,"🟡 Acceptable") -> 31 | F7: =COUNTIF('S Data_Inventory '!Q4:Q94,"⚠️ Use with Caution")+COUNTIF('S Data_Inventory '!Q4:Q94,"🔴 Insufficient") -> 0
A8: Governance | B8: =COUNTA('G Data_Inventory '!D4:D180) -> 67 | C8: =IFERROR(AVERAGE('G Data_Inventory '!P4:P75),"No data") -> 49.701493 | D8: =COUNTIF('G Data_Inventory '!Q5:Q195,"✅ High Quality") -> 36 | E8: =COUNTIF('G Data_Inventory '!Q5:Q195,"🟡 Acceptable") -> 0 | F8: =COUNTIF('G Data_Inventory '!Q5:Q195,"⚠️ Use with Caution")+COUNTIF('G Data_Inventory '!Q5:Q195,"🔴 Insufficient") -> 30
A9: Performance | B9: =COUNTA('P Data_Inventory'!C2:C70) -> 69 | C9: =IFERROR(AVERAGE('P Data_Inventory'!O2:O75),"No data") -> 67.826087 | D9: =COUNTIFS('E Data_Inventory'!B4:B302,"Financial",'E Data_Inventory'!Q4:Q302,"✅ High Quality") -> 0 | E9: =COUNTIFS('E Data_Inventory'!B4:B302,"Financial",'E Data_Inventory'!Q4:Q302,"🟡 Acceptable") -> 0 | F9: =COUNTIFS('E Data_Inventory'!B4:B302,"Financial",'E Data_Inventory'!Q4:Q302,"⚠️ Use with Caution")+COUNTIFS('E Data_Inventory'!B4:B302,"Financial",'E Data_Inventory'!Q4:Q302,"🔴 Insufficient") -> 0
A10: ALL PILLARS | B10: =SUM(B6:B9) -> 453 | C10: =IFERROR(AVERAGE('E Data_Inventory'!P4:P302,'S Data_Inventory '!P4:P87,'G Data_Inventory '!P4:P74,'P Data_Inventory'!O2:O71),"No data") -> 63.708609 | D10: =SUM(D6:D9) -> 143 | E10: =SUM(E6:E9) -> 148 | F10: =SUM(F6:F9) -> 92
A13: SECTION 2 — DATA GAPS (KPIs with Insufficient Quality)
A14: Pillar | B14: KPI Name | C14: Quality Score | D14: Grade | E14: Suggested Action
A22: SECTION 3 — DATA GAP ANALYSIS (150-word written reflection)
A23: The current information shows several gaps regarding the data across all pillars. For Governance the number of sustained ethics violations due to the lack of regulation on disclosure, this doesnt represent an impact on the carbon footprint analysis. The company has stablished methods to report ethics complains and a process to adress them. For Financial the Market Capitalization, as a recently formed company and indexed into the SP500 after the Merger the market volatility it shows its dependance on global supply chain transport demand, this changes pose an impact on the carbon footprint calculation as it grows as the demand for products increase across the supply chain. For the Social pillar the audited supply chain represents the bigest gap since its focus is on the fiber sourcing for both virgin and recycled fibers validated by third parties but other key suppliers are under internal regulations not much is disclosed about small suppliers, this represents an impact on the carbon footprint calculation as small suppliers represent portion of the footprint. The gaps presented show a company that is growing and is focused on covering this gaps in a short and medium term.

Sheet Tables_for_Reference
A1: Quality Scoring Rubric & Framework Guide
A3: TABLE 1 — QUALITY SCORING RUBRIC (Reference while filling Data Inventory)
A4: Dimension | B4: Max Points | C4: Score | D4: Criteria | E4: Example | G4: QUALITY SCORE INTERPRETATION
A5: ACCURACY | B5: 25 pts | C5: 25 | D5: Externally assured by independent firm (KPMG, Deloitte, PwC) | From externally audited Annual Report / 10-K\ | E5: Limited Assurance provided by Deloitte' stated in report | Revenue from SEC 10-K filing | G5: 80 – 100 | H5: HIGH QUALITY — Use with full confidence in analysis
C6: 15 | D6: Company self-reported in Sustainability / ESG Report | E6: Scope 1 data in standalone sustainability PDF | G6: 60 – 79 | H6: ACCEPTABLE — Use with appropriate caveats in report | I6: ACCEPTABLE
C7: 10 | D7: Estimated by reputable third party (Bloomberg, MSCI) | E7: Bloomberg ESG estimate for small-cap company | G7: 40 – 59 | H7: USE WITH CAUTION — Flag as estimated in methodology | I7: REASONABLE
C8: 5 | D8: Modeled / inferred from proxy data | E8: Estimated from industry average intensity × revenue | G8: 0 – 39 | H8: INSUFFICIENT — Seek alternative source or disclose gap | I8: NO ASURANCE
C9: 0 | D9: Unknown source or not disclosed | E9: 'Data not available for this metric'
A10: COMPLETENESS | B10: 25 pts | C10: 25 | D10: Full value + complete methodology + boundary definition disclosed | E10: 'Scope 1 includes all wholly-owned facilities. Calculated using EPA emission factors 2023. Methodology reviewed by [firm].'
C11: 15 | D11: Value disclosed, no methodology detail | E11: 'Scope 1 Emissions: 245,000 tCO₂e' with no further detail | H11: 31179
C12: 10 | D12: Partial data — some years or business units missing | E12: Only 2 of 5 operating regions included in figure | H12: 21109
C13: 5 | D13: Range given rather than specific value | E13: 'Approximately 200,000–250,000 tCO₂e'
C14: 0 | D14: Not disclosed at all | E14: KPI completely absent from all reports | H14: W Revenue | I14: S Revenue | J14: Year
A15: TIMELINESS | B15: 25 pts | C15: 25 | D15: Data is from current fiscal year (within 12 months) | E15: 2023 data in a 2024 report (published early 2024) | H15: 20050.836 | I15: 11128.164 | J15: 2025
C16: 15 | D16: Data is 1 fiscal year old | E16: 2022 data cited in 2024 report | H16: 13574.941 | I16: 7534.0589 | J16: 2024
C17: 10 | D17: Data is 2 fiscal years old | E17: 2021 data in 2024 report — common for Scope 3 | H17: 20310 | I17: 11272 | J17: 2023
C18: 5 | D18: Data is 3 or more years old | E18: 2020 data — baseline only, not current performance | H18: 21256.5 | I18: 12815 | J18: 2022
C19: 0 | D19: Date of data is unknown | E19: No year specified for the reported figure | H19: 18746.1 | I19: 10107 | J19: 2021
A20: CONSISTENCY | B20: 25 pts | C20: 25 | D20: Values match exactly (or within rounding) across all sources | E20: Company report: 245,000 tCO₂e | CDP: 245,200 tCO₂e ← rounding only | H20: 17578.8 | I20: 8530 | J20: 2020
C21: 15 | D21: Minor variation < 5% between sources | E21: Company: 245,000 | Bloomberg: 250,000 ← 2% variance | H21: 18289 | I21: 9048 | J21: 2019
C22: 10 | D22: Medium variation 5–10% between sources | E22: Company: 245,000 | Bloomberg: 250,000 ← 5% variance
C23: 5 | D23: Significant variation 10–15% | E23: Company: 245,000 | CDP: 280,000 ← 14% variance — investigate | H23: W Market Cap | I23: S Market Cap | J23: Year
C24: 0 | D24: Major discrepancy > 15% or only one source available | E24: Only one source found — cannot assess consistency | H24: 13871.008 | I24: 14160.092 | J24: 2024
H25: 9179.1 | I25: 9370.4 | J25: 2023
H26: 7858.4 | I26: 8985 | J26: 2022
A27: TABLE 2 — SOURCE TYPE CLASSIFICATION GUIDE | H27: 13205 | I27: 12492.5 | J27: 2021
A28: Source Type | B28: Description | C28: Typical Accuracy Score | D28: Where to Find | H28: 9046.3 | I28: 9898.2 | J28: 2020
A29: Company ESG / Sustainability Report | B29: Standalone annual sustainability disclosure published by company | C29: 15 | D29: Company IR website → Sustainability or ESG section | H29: 9396.8 | I29: 8204.6 | J29: 2019
A30: Annual Report / 10-K / 20-F | B30: Legally filed annual report with financial statements | C30: 25 | D30: SEC EDGAR (US), Companies House (UK), company IR site
A31: CDP Submission | B31: Response to CDP climate/water/forest questionnaire | C31: 15–20 | D31: cdp.net → data portal → search company name
A32: Proxy Statement / DEF 14A | B32: Annual shareholder meeting document with governance data | C32: 20 | D32: SEC EDGAR → search company → DEF 14A
A33: Verified / Assured Data | B33: Data with independent third-party assurance statement | C33: 25 | D33: Look for assurance letter in back of sustainability report
A34: Bloomberg / Refinitiv | B34: Commercial data providers that aggregate ESG data | C34: 10–15 | D34: Bloomberg terminal → ESG tab or Refinitiv Eikon
A35: GRI Database | B35: Global Reporting Initiative database of GRI-aligned disclosures | C35: 15 | D35: database.globalreporting.org
A36: Third-Party Estimate | B36: MSCI, Sustainalytics, or similar agency estimates | C36: 10 | D36: MSCI ESG Ratings, Sustainalytics.com
A37: Calculated / Derived | B37: Value calculated by you from primary sources | C37: 15 | D37: Document your calculation methodology clearly
A40: TABLE 3 — ESG FRAMEWORK QUICK REFERENCE
A41: Framework | B41: Focus | C41: Best For | D41: Key KPIs Covered | E41: Website
A42: GRI | B42: Stakeholder-focused sustainability disclosures | C42: Comprehensive ESG reporting | D42: 300+ disclosures across environmental, social, governance topics | E42: https://www.globalreporting.org/standards/
A43: SASB (now maintained by ISSB) | B43: Industry-specific financially material ESG metrics | C43: Investor-focused reporting | D43: 77 industry standards with 5–13 metrics | E43: https://www.ifrs.org/issued-standards/sasb-standards/
A44: TCFD | B44: Climate-related financial risk disclosure | C44: Climate governance and risk management | D44: Governance, Strategy, Risk Management, Metrics & Targets | E44: https://www.fsb-tcfd.org/#:~:text=The%20Task%20Force%20on%20Climate%2Drelated%20Financial%20Disclosures,the%20organization's%20businesses%2C%20strategy%2C%20and%20financial%20planning
A45: ISSB (IFRS S1 & S2) | B45: Global baseline sustainability reporting | C45: Financial market transparency | D45: Sustainability risks, climate metrics, governance, strategy | E45: https://www.ifrs.org/groups/international-sustainability-standards-board/
A46: EU Taxonomy | B46: Classification of sustainable activities | C46: EU companies under CSRD | D46: % revenue, CAPEX, OPEX aligned to taxonomy | E46: https://finance.ec.europa.eu/sustainable-finance/tools-and-standards/eu-taxonomy-sustainable-activities_en
A47: CDP (Carbon Disclosure Project) | B47: Global environmental disclosure platform for climate, water, and forest impacts | C47: Companies reporting environmental risks and sustainability performance to investors and stakeholders | D47: Greenhouse gas emissions (Scope 1, 2, 3), climate risk management, water use, deforestation impacts, environmental targets and governance | E47: https://www.cdp.net
A50: COLOR CODING IN THIS WORKBOOK
A51: Blue text | B51: Hardcoded inputs — cells YOU should fill in
A52: Black text | B52: Formulas — do not edit these
A53: Green text | B53: Cross-sheet references — do not edit these
A54: Yellow background | B54: Cells requiring your attention / inputs

Sheet zz_Helper_Calcs
A1: Metric | B1: Value / Formula | C1: Source / Notes
A2: Scope 1 direct emissions (WestRock, tCO2e) | B2: 5674000 | C2: 2024 Sustainability Report p.125 and EY schedule p.169. WestRock only. https://www.smurfitkappa.com/-/m/files/publications---global/sr-2024-downloads/smurfit_westrock_sustainability_report_2024.pdf?rev=8fa6453fc2294a2a894c5bedcc52de80
A3: Scope 2 market-based (WestRock, tCO2e) | B3: 2300000 | C3: 2024 Sustainability Report p.125 and EY schedule p.169. WestRock only. https://www.smurfitkappa.com/-/m/files/publications---global/sr-2024-downloads/smurfit_westrock_sustainability_report_2024.pdf?rev=8fa6453fc2294a2a894c5bedcc52de80
A4: Scope 2 location-based (WestRock, tCO2e) | B4: 1746000 | C4: 2024 Sustainability Report p.125. WestRock only. https://www.smurfitkappa.com/-/m/files/publications---global/sr-2024-downloads/smurfit_westrock_sustainability_report_2024.pdf?rev=8fa6453fc2294a2a894c5bedcc52de80
A5: Scope 3 relevant categories (WestRock, tCO2e) | B5: 9452000 | C5: 2024 Sustainability Report p.125 and EY schedule p.171. WestRock relevant categories only. https://www.smurfitkappa.com/-/m/files/publications---global/sr-2024-downloads/smurfit_westrock_sustainability_report_2024.pdf?rev=8fa6453fc2294a2a894c5bedcc52de80
A6: Total energy used (WestRock, MMBtu) | B6: 284911157 | C6: 2024 Sustainability Report p.125. https://www.smurfitkappa.com/-/m/files/publications---global/sr-2024-downloads/smurfit_westrock_sustainability_report_2024.pdf?rev=8fa6453fc2294a2a894c5bedcc52de80
A7: Total energy consumption (GWh) | B7: =B6*0.00029307107 -> 83499.218 | C7: Converted from MMBtu to GWh for the template using 1 MMBtu = 0.00029307107 GWh.
A8: Renewable energy percentage (WestRock %) | B8: 60 | C8: 2024 Sustainability Report p.125 energy mix = 60% renewable. https://www.smurfitkappa.com/-/m/files/publications---global/sr-2024-downloads/smurfit_westrock_sustainability_report_2024.pdf?rev=8fa6453fc2294a2a894c5bedcc52de80
A9: Total water withdrawal (WestRock mills, ML) | B9: 470201 | C9: 2024 Sustainability Report p.127. WestRock mills only. https://www.smurfitkappa.com/-/m/files/publications---global/sr-2024-downloads/smurfit_westrock_sustainability_report_2024.pdf?rev=8fa6453fc2294a2a894c5bedcc52de80
A10: Landfill waste (WestRock mills, short tons) | B10: 694211 | C10: 2024 Sustainability Report p.127. https://www.smurfitkappa.com/-/m/files/publications---global/sr-2024-downloads/smurfit_westrock_sustainability_report_2024.pdf?rev=8fa6453fc2294a2a894c5bedcc52de80
A11: Waste to energy (WestRock mills, short tons) | B11: 227237 | C11: 2024 Sustainability Report p.127. https://www.smurfitkappa.com/-/m/files/publications---global/sr-2024-downloads/smurfit_westrock_sustainability_report_2024.pdf?rev=8fa6453fc2294a2a894c5bedcc52de80
A12: Beneficial use waste (WestRock mills, short tons) | B12: 269335 | C12: 2024 Sustainability Report p.127. https://www.smurfitkappa.com/-/m/files/publications---global/sr-2024-downloads/smurfit_westrock_sustainability_report_2024.pdf?rev=8fa6453fc2294a2a894c5bedcc52de80
A13: Total waste generated (WestRock mills, short tons) | B13: =SUM(B10:B12) -> 1190783 | C13: Sum of landfill, waste-to-energy and beneficial-use streams.
A14: Total waste generated (WestRock mills, metric tonnes) | B14: =B13*0.90718474 -> 1080260.2 | C14: Converted from U.S. short tons to metric tonnes using 0.90718474.
A15: Purchased fuel energy efficiency (WestRock, MMBtu/ton) | B15: 12.62 | C15: 2024 Sustainability Report p.125 and EY schedule p.175. Proxy metric only. https://www.smurfitkappa.com/-/m/files/publications---global/sr-2024-downloads/smurfit_westrock_sustainability_report_2024.pdf?rev=8fa6453fc2294a2a894c5bedcc52de80
A16: Energy intensity proxy (GJ/ton) | B16: =B15*1.05505585262 -> 13.314805 | C16: Converted from MMBtu/ton to GJ/ton using 1 MMBtu = 1.05505585262 GJ.
A17: Waste diversion rate (%) | B17: =100*(B11+B12)/B13 -> 41.701301 | C17: Calculated as (waste-to-energy + beneficial use) / total waste * 100.
A18: Hazardous waste generated (Smurfit Kappa, metric tonnes) | B18: 13369 | C18: 2024 Sustainability Report p.59 / supporting data p.119. Smurfit Kappa only. https://www.smurfitkappa.com/-/m/files/publications---global/sr-2024-downloads/smurfit_westrock_sustainability_report_2024.pdf?rev=8fa6453fc2294a2a894c5bedcc52de80
A19: Annual revenue (USD millions) | B19: 21109 | C19: 2024 Annual Report pdf p.57 and pdf p.102: net sales (unaffiliated customers) = $21,109 million. https://www.smurfitwestrock.com/-/m/files/publications---global/financial-reports/sw-2024-annual-report.pdf?rev=4870ca9e316e43588dd14c35c5247fa3
A20: Adjusted EBITDA (USD millions) | B20: 3386 | C20: 2024 Annual Report pdf p.68: Adjusted EBITDA = $3,386 million. https://www.smurfitwestrock.com/-/m/files/publications---global/financial-reports/sw-2024-annual-report.pdf?rev=4870ca9e316e43588dd14c35c5247fa3
A21: EBITDA margin (%) | B21: =100*B20/B19 -> 16.040551 | C21: Calculated as Adjusted EBITDA / net sales * 100.
A22: Capital expenditure (USD millions) | B22: 1466 | C22: 2024 Annual Report pdf p.105: total capital expenditure = $1,466 million. https://www.smurfitwestrock.com/-/m/files/publications---global/financial-reports/sw-2024-annual-report.pdf?rev=4870ca9e316e43588dd14c35c5247fa3
A23: Shares outstanding at 12/31/2024 | B23: 520444261 | C23: 2024 Annual Report pdf p.78: shares outstanding at 12/31/2024 = 520,444,261. https://www.smurfitwestrock.com/-/m/files/publications---global/financial-reports/sw-2024-annual-report.pdf?rev=4870ca9e316e43588dd14c35c5247fa3
A24: SW closing share price on 12/31/2024 (USD) | B24: 51.3218 | C24: Historical closing price for SW on 2024-12-31. https://www.macrotrends.net/stocks/charts/SW/smurfit-westrock/stock-price-history
A25: Market capitalization (USD millions) | B25: =B23*B24/1000000 -> 26710.136 | C25: Calculated as shares outstanding * year-end closing share price / 1,000,000.
