Workbook

Sheet Instructions
A1: LAB 2 — Carbon Footprint Calculator | GHG Protocol Framework
A2: ESG Analytics & Management · Session 4 · Week 2 · This workbook feeds directly into Lab 3 (Environmental Dashboard)
A4: WORKBOOK CONTENTS
A5: Sheet | B5: Purpose & What to Complete
A6: 📋 Instructions | B6: You are here
A7: Assumptions | B7: Central inputs: company name, reporting years, financial data, GWP factors — FILL THIS FIRST
A8: Scope 1 | B8: Direct emissions: combustion, fleet, process, fugitive sources — enter activity data
A9: Scope 2 | B9: Purchased energy: market-based AND location-based dual calculation
A10: Scope 3 | B10: Value chain emissions: 5 categories using spend-based and activity-based methods
A11: Summary & Intensity | B11: Auto-calculated totals, intensity ratios, scope breakdown — review after entering data
A12: Trend Analysis | B12: 3-year historical trend table and chart builder — enter prior year data
A13: Emission Factors | B13: Reference tables: EPA, DEFRA, IEA grid factors — DO NOT EDIT formulas here
A14: Assumptions | B14: Document every emission factor used, boundary decisions, and methodology notes
A16: STEP-BY-STEP GUIDE
A17: Step 1 | B17: Fill Assumptions sheet: company info, financial metrics, years, GWP values
A18: Step 2 | B18: Enter activity data in Scope 1 (fuel consumption by source)
A19: Step 3 | B19: Enter electricity/energy data in Scope 2 (both market and location-based)
A20: Step 4 | B20: Estimate Scope 3 for at least 3 categories in Scope 3 sheet
A21: Step 5 | B21: Check Summary & Intensity — all totals pull automatically via formulas
A22: Step 6 | B22: Enter 2 prior years of data in Trend Analysis to build the trend chart
A23: Step 7 | B23: Document all sources and decisions in Assumptions Log
A25: COLOR CODING
A26: Blue text / Yellow background | B26: Your inputs — cells you must fill in
A27: Black text / White background | B27: Calculated formulas — do not edit
A28: Green text / Light green background | B28: Cross-sheet references pulling from other sheets
A30: GHG PROTOCOL BOUNDARY REMINDER
A31: Operational Control | B31: Include 100% of emissions from operations you control (most common approach)
A32: Equity Share | B32: Include % of emissions proportional to your ownership stake
A33: Financial Control | B33: Include entities where you have financial control
A34: Your boundary choice → | B34: Document in Methodology your Assumptions
A36: KEY FORMULAS USED IN THIS WORKBOOK
A37: Scope 1 (combustion) | B37: Activity (units) × Emission Factor (kgCO₂e/unit) ÷ 1,000 = tCO₂e | C37: This is the standard way to convert fuel use into tonnes of CO₂e. Emission factors are usually in kgCO₂e per unit, so dividing by 1,000 converts to tonnes.
A38: Scope 2 (location) | B38: Electricity (MWh) × Grid EF (kgCO₂e/MWh) ÷ 1,000 = tCO₂e
A39: Scope 2 (market) | B39: Electricity (MWh) × Supplier/Residual EF (kgCO₂e/MWh) ÷ 1,000 = tCO₂e
A40: Scope 3 (spend) | B40: Supplier Spend ($) × EEIO Factor (kgCO₂e/$) ÷ 1,000 = tCO₂e | C40: This is the standard spend‑based method using Environmentally Extended Input‑Output (EEIO) factors. It’s commonly used when activity data isn’t available.
A41: Intensity (revenue) | B41: Total tCO₂e ÷ Revenue ($M) = tCO₂e per $M revenue | C41: Intensity ratios are flexible, but this is a common one.
A42: GWP conversion | B42: CH₄ mass × GWP_CH4 = CO₂e | N₂O mass × GWP_N2O = CO₂e | C42: This is exactly how methane (CH₄), nitrous oxide (N₂O), and other gases are converted to CO₂‑equivalent using IPCC global warming potentials.

Sheet Assumptions
A1: CENTRAL ASSUMPTIONS — Fill This Sheet First
A2: All other sheets reference these cells. Update here and the whole model recalculates.
A4: SECTION A — COMPANY INFORMATION
A9: Company Name | B9: Westrock Company | C9: Used in all sheet headers
A10: Industry / Sector | B10: Pulp, Paper and Packaging | C10: Affects SASB materiality and EF selection
A11: Primary Country of Operations | B11: USA | C11: Used to select default grid emission factor
A12: Reporting Year (Current) | B12: 2023 | C12: Year of primary data being analyzed
A13: Reporting Year (Prior 1) | B13: 2019 | C13: For trend analysis — enter in Trend sheet
A14: SECTION B — FINANCIAL METRICS (for Intensity Calculations)
A15: Annual Revenue (USD Millions) | C15: USD Millions | D15: Used to calculate carbon intensity per $M revenue
A16: Number of Employees (FTE) | C16: Headcount | D16: Used to calculate carbon intensity per employee
A17: Total Production Volume (units) | C17: Microsoft is a software, cloud, and services company; no consolidated production-volume metric is reported. | D17: For manufacturing companies — carbon per unit produced
A18: Floor Space / Facility Area | C18: Microsoft does not publicly disclose total facility area in aggregate. | D18: For real estate, retail — carbon per m²
A19: Revenue Unit Note | C19: Text | D19: Important: ensure revenue is in $M not $B
A21: SECTION C — GLOBAL WARMING POTENTIAL (GWP) FACTORS — IPCC AR6 (2021)
A22: These factors convert non-CO₂ gases to CO₂ equivalents. AR6 values shown (default). Change only if your regulatory regime requires AR5 or AR4.
A23: Gas | B23: Chemical | C23: AR6 GWP (100-yr) | D23: AR5 GWP (100-yr) | E23: Your Selection | F23: Source
A24: Carbon Dioxide | B24: CO₂ | C24: 1 | D24: 1 | E24: 1 | F24: IPCC AR6, 2021
A25: Methane (fossil) | B25: CH₄ | C25: 29.8 | D25: 25 | E25: 29.8 | F25: IPCC AR6 WGI Table 7.SM.7
A26: Methane (biogenic) | B26: CH₄ | C26: 27.9 | D26: 25 | E26: 27.9 | F26: IPCC AR6 WGI Table 7.SM.7
A27: Nitrous Oxide | B27: N₂O | C27: 273 | D27: 298 | E27: 273 | F27: IPCC AR6 WGI Table 7.SM.7
A28: HFC-134a (refrigerant) | B28: CH₂FCF₃ | C28: 1526 | D28: 1430 | E28: 1526 | F28: IPCC AR6
A29: SF₆ (electrical equipment) | B29: SF₆ | C29: 25200 | D29: 22800 | E29: 25200 | F29: IPCC AR6
A32: Fiscal Year | B32: Revenue (USD) | C32: Employees
A33: 2024 | B33: 245120 | C33: 228000
A34: 2023 | B34: 211980 | C34: 221000
A35: 2022 | B35: 198270 | C35: 221000
A36: 2021 | B36: 168090 | C36: 181000
A37: 2020 | B37: 143020 | C37: 163000

Sheet Emission Factors
A1: EMISSION FACTORS REFERENCE LIBRARY — EPA, DEFRA, IEA 2023
A2: Reference only — do not edit. Factors are pre-loaded into calculation sheets. Update annually.
A4: TABLE 1 — STATIONARY COMBUSTION FACTORS (EPA Center for Corporate Climate Leadership 2023)
A5: # | B5: Fuel Type | C5: Unit | D5: CO₂ EF (kgCO₂/unit) | E5: CH₄ EF (gCH₄/unit) | F5: N₂O EF (gN₂O/unit) | G5: Source
A6: 1 | B6: Natural Gas | C6: MMBtu | D6: 53.06 | E6: 1 | F6: 0.1 | G6: EPA 2023 Table 1
A7: 2 | B7: Natural Gas | C7: m³ | D7: 1.879 | E7: 0.0354 | F7: 0.00354 | G7: EPA 2023 (converted)
A8: 3 | B8: Propane | C8: Gallon | D8: 5.68 | E8: 0.226 | F8: 0.023 | G8: EPA 2023 Table 1
A9: 4 | B9: Diesel Fuel / Fuel Oil No.2 | C9: Gallon | D9: 10.21 | E9: 0.41 | F9: 0.08 | G9: EPA 2023 Table 1
A10: 5 | B10: Diesel Fuel / Fuel Oil No.2 | C10: Litre | D10: 2.663 | E10: 0.139 | F10: 0.014 | G10: EPA 2023 (converted)
A11: 6 | B11: Residual Fuel Oil (No. 6) | C11: Gallon | D11: 11.27 | E11: 0.48 | F11: 0.1 | G11: EPA 2023 Table 1
A12: 7 | B12: Residual Fuel Oil (No. 6) | C12: Litre | D12: 3.122 | E12: 0.139 | F12: 0.014 | G12: EPA 2023 (converted)
B13: Residual Fuel Oil (No. 6) | C13: MMBtu | D13: 75.1 | E13: 3 | F13: 0.6 | G13: EPA 2023 Table 1
A14: 8 | B14: LPG | C14: Gallon | D14: 5.68 | E14: 0.226 | F14: 0.023 | G14: EPA 2023 Table 1
A15: 9 | B15: LPG | C15: Litre | D15: 1.555 | E15: 0.0617 | F15: 0.0062 | G15: EPA 2023 (converted)
A16: 10 | B16: Coal — Bituminous | C16: Short Ton | D16: 2325 | E16: 274 | F16: 40 | G16: EPA 2023 Table 1
B17: Coal — Bituminous | C17: MMBtu | D17: 93.28 | E17: 11 | F17: 1.6 | G17: EPA 2023 Table 1
A18: 11 | B18: Coal — Sub-bituminous | C18: Short Ton | D18: 1676 | E18: 190 | F18: 28 | G18: EPA 2023 Table 1
A19: 12 | B19: Wood / Wood Waste | C19: Short Ton | D19: 1640 | E19: 300 | F19: 4 | G19: EPA 2023 Table 1
A20: 13 | B20: Municipal Solid Waste | C20: Short Ton | D20: 902 | E20: 318 | F20: 42 | G20: EPA 2023 Table 1
A21: 14 | B21: Biomas Fuel (Biodiesel) | C21: MMBtu | D21: 73.84 | E21: 1.1 | F21: 0.11 | G21: EPA 2023 Table 1
B22: Buinass Fuels Solid (Wood & Wood Residuals) | C22: MMBtu | D22: 93.8 | E22: 7.2 | F22: 3.6
G26: epa.gov/system/files/documents/2023-03/ghg_emission_factors_hub.pdf
A28: TABLE 2 — MOBILE COMBUSTION FACTORS (EPA 2023 / DEFRA 2023)
A29: # | B29: Fuel Type | C29: Unit | D29: CO₂ EF (kgCO₂/unit) | E29: CH₄ EF (gCH₄/unit) | F29: N₂O EF (gN₂O/unit) | G29: Source
A30: 1 | B30: Gasoline — Passenger Cars | C30: Litre | D30: 2.312 | E30: 0.339 | F30: 0.033 | G30: DEFRA 2023 / (2.35) EPA 2023
A31: 2 | B31: Gasoline — Light-Duty Trucks | C31: Litre | D31: 2.312 | E31: 0.572 | F31: 0.057 | G31: DEFRA 2023 / EPA 2023
A32: 3 | B32: Diesel — Passenger Cars | C32: Litre | D32: 2.68 | E32: 0.046 | F32: 0.184 | G32: DEFRA 2023 / (2.69) EPA
A33: 4 | B33: Diesel — Heavy-Duty Trucks | C33: Litre | D33: 2.68 | E33: 0.06 | F33: 0.252 | G33: DEFRA 2023
A34: 5 | B34: Aviation Fuel (Jet A / Jet A-1) | C34: Litre | D34: 2.553 | E34: 0 | F34: 0 | G34: DEFRA 2023 / (2.53) EPA
A35: 6 | B35: Compressed Natural Gas (CNG) | C35: GJ | D35: 50.3 | E35: 0 | F35: 0 | G35: EPA 2023 / (50.3) EPA
A36: 7 | B36: Liquefied Natural Gas (LNG) | C36: Litre | D36: 2.75 | E36: 0 | F36: 0 | G36: DEFRA 2023
A38: TABLE 3 — ELECTRICITY GRID EMISSION FACTORS (IEA 2023 / EPA eGRID 2023)
A39: # | B39: Country / Region / Grid | C39: kgCO₂e / MWh (Location-Based) | D39: Source | E39: Year | F39: Notes
A40: 1 | B40: US National Average | C40: ~380-400 | D40: EPA eGRID 2023 | E40: 2023 | F40: Covers all NERC regions
A41: 2 | B41: US — CAMX (California) | C41: 194 | D41: EPA eGRID 2023 | E41: 2023 | F41: High renewables
A42: 3 | B42: US — ERCOT (Texas) | C42: 333 | D42: EPA eGRID 2023 | E42: 2023 | F42: Natural gas heavy
A43: 4 | B43: US — RFC (PJM Interconnection) | C43: 271 | D43: EPA eGRID 2023 | E43: 2023 | F43: Northeast / Midwest
A44: 5 | B44: US — WECC (Mountain) | C44: 319 | D44: EPA eGRID 2023 | E44: 2023 | F44: Mountain states
A45: 6 | B45: Canada National Average | C45: 110-140 | D45: Environment Canada 2022 | E45: 2022 | F45: High hydro share
A46: 7 | B46: European Union Average | C46: 230-260 | D46: European Environment Agency 2022 | E46: 2022 | F46: Weighted average
A47: 8 | B47: Germany | C47: 380-420 | D47: IEA 2022 | E47: 2022 | F47: Transitioning from coal
A48: 9 | B48: France | C48: 50-70 | D48: IEA 2022 | E48: 2022 | F48: Nuclear dominant
A49: 10 | B49: United Kingdom | C49: 207 | D49: DEFRA 2023 | E49: 2023 | F49: Official UK government factor
A50: 11 | B50: Sweden | C50: 10-20 | D50: IEA 2022 | E50: 2022 | F50: Hydro + nuclear dominant
A51: 12 | B51: Poland | C51: 700-800 | D51: IEA 2022 | E51: 2022 | F51: Coal dominant
A52: 13 | B52: China | C52: 550-650 | D52: IEA 2022 | E52: 2022 | F52: High coal share
A53: 14 | B53: India | C53: 700-800 | D53: IEA 2022 | E53: 2022 | F53: High coal share
A54: 15 | B54: Japan | C54: 450-500 | D54: IEA 2022 | E54: 2022 | F54: Post-Fukushima gas shift
A55: 16 | B55: South Korea | C55: 400-500 | D55: IEA 2022 | E55: 2022 | F55: Coal + nuclear mix
A56: 17 | B56: Australia | C56: 650-750 | D56: Australian NGER 2022 | E56: 2022 | F56: High coal NEM average
A57: 18 | B57: Brazil | C57: 100-150 | D57: Brazilian EPE 2022 | E57: 2022 | F57: High hydro share
A58: 19 | B58: Mexico | C58: 400-500 | D58: IEA 2022 | E58: 2022 | F58: Natural gas growing
A59: 20 | B59: South Africa | C59: 850-950 | D59: IEA 2022 | E59: 2022 | F59: Coal dominant
B60: Steam & Heat | C60: MMBtu | D60: 66.33 | E60: 1.25 | F60: 0.125
B61: World average | C61: ~475

Sheet Scope 1 S
A1: SCOPE 1 — DIRECT GHG EMISSIONS | GHG Protocol: All sources your organization directly controls
A2: Enter activity data (fuel consumed, distance driven, refrigerant leaked). Emission factors are pre-loaded from EPA/DEFRA tables.
A4: PART A — STATIONARY COMBUSTION (Boilers, Furnaces, Generators, Turbines)
A5: # | B5: Fuel Source | C5: Activity Quantity | D5: Activity Unit | E5: CO₂ EF (kgCO₂/unit) | F5: CH₄ EF (gCH₄/unit) | G5: N₂O EF (gN₂O/unit) | H5: CO₂ (tCO₂) | I5: CH₄ (tCO₂e) | J5: N₂O (tCO₂e) | K5: Total (tCO₂e) | L5: Reporting Year
A6: 1 | B6: Natural Gas | D6: MMBtu | E6: ='Emission Factors'!$D$6 -> 53.06 | F6: ='Emission Factors'!$E$6 -> 1 | G6: ='Emission Factors'!$F$6 -> 0.1 | H6: =C6*E6/1000 -> 0 | I6: =$C6*$F6*Assumptions!$E$25/1000000 -> 0 | J6: =$C6*G6*Assumptions!$E$27/1000000 -> 0 | K6: =SUM(H6:J6) -> 0 | L6: 2019
A7: 2 | B7: Residual Fuel Oil (No. 6) | D7: MMBtu | E7: 75.1 | F7: 3 | G7: 0.6 | H7: =C7*E7/1000 -> 0 | I7: =$C7*$F7*Assumptions!$E$25/1000000 -> 0 | J7: =$C7*G7*Assumptions!$E$27/1000000 -> 0 | K7: =SUM(H7:J7) -> 0 | L7: 2019
A8: 3 | B8: Coal — Bituminous | D8: MMBtu | E8: 93.28 | F8: 11 | G8: 1.6 | H8: =C8*E8/1000 -> 0 | I8: =$C8*$F8*Assumptions!$E$25/1000000 -> 0 | J8: =$C8*G8*Assumptions!$E$27/1000000 -> 0 | K8: =SUM(H8:J8) -> 0 | L8: 2019
A9: 4 | B9: BioFuels Solid (Wood & Wood Residuals) | D9: MMBtu | E9: 93.8 | F9: 7.2 | G9: 3.6 | H9: =C9*E9/1000 -> 0 | I9: =$C9*$F9*Assumptions!$E$25/1000000 -> 0 | J9: =$C9*G9*Assumptions!$E$27/1000000 -> 0 | K9: =SUM(H9:J9) -> 0 | L9: 2019
A10: 5 | B10: Natural Gas | D10: MMBtu | E10: ='Emission Factors'!$D$6 -> 53.06 | F10: ='Emission Factors'!$E$6 -> 1 | G10: ='Emission Factors'!$F$6 -> 0.1 | H10: =C10*E10/1000 -> 0 | I10: =$C10*$F10*Assumptions!$E$25/1000000 -> 0 | J10: =$C10*G10*Assumptions!$E$27/1000000 -> 0 | K10: =SUM(H10:J10) -> 0 | L10: 2020
A11: 6 | B11: Residual Fuel Oil (No. 6) | D11: MMBtu | E11: 75.1 | F11: 3 | G11: 0.6 | H11: =C11*E11/1000 -> 0 | I11: =$C11*$F11*Assumptions!$E$25/1000000 -> 0 | J11: =$C11*G11*Assumptions!$E$27/1000000 -> 0 | K11: =SUM(H11:J11) -> 0 | L11: 2020
A12: 7 | B12: Coal — Bituminous | D12: MMBtu | E12: 93.28 | F12: 11 | G12: 1.6 | H12: =C12*E12/1000 -> 0 | I12: =$C12*$F12*Assumptions!$E$25/1000000 -> 0 | J12: =$C12*G12*Assumptions!$E$27/1000000 -> 0 | K12: =SUM(H12:J12) -> 0 | L12: 2020
A13: 8 | B13: BioFuels Solid (Wood & Wood Residuals) | D13: MMBtu | E13: 93.8 | F13: 7.2 | G13: 3.6 | H13: =C13*E13/1000 -> 0 | I13: =$C13*$F13*Assumptions!$E$25/1000000 -> 0 | J13: =$C13*G13*Assumptions!$E$27/1000000 -> 0 | K13: =SUM(H13:J13) -> 0 | L13: 2020
A14: 1 | B14: Natural Gas | D14: MMBtu | E14: ='Emission Factors'!$D$6 -> 53.06 | F14: ='Emission Factors'!$E$6 -> 1 | G14: ='Emission Factors'!$F$6 -> 0.1 | H14: =C14*E14/1000 -> 0 | I14: =$C14*$F14*Assumptions!$E$25/1000000 -> 0 | J14: =$C14*G14*Assumptions!$E$27/1000000 -> 0 | K14: =SUM(H14:J14) -> 0 | L14: 2021
A15: 2 | B15: Residual Fuel Oil (No. 6) | D15: MMBtu | E15: 75.1 | F15: 3 | G15: 0.6 | H15: =C15*E15/1000 -> 0 | I15: =$C15*$F15*Assumptions!$E$25/1000000 -> 0 | J15: =$C15*G15*Assumptions!$E$27/1000000 -> 0 | K15: =SUM(H15:J15) -> 0 | L15: 2021
A16: 3 | B16: Coal — Bituminous | D16: MMBtu | E16: 93.28 | F16: 11 | G16: 1.6 | H16: =C16*E16/1000 -> 0 | I16: =$C16*$F16*Assumptions!$E$25/1000000 -> 0 | J16: =$C16*G16*Assumptions!$E$27/1000000 -> 0 | K16: =SUM(H16:J16) -> 0 | L16: 2021
A17: 4 | B17: BioFuels Solid (Wood & Wood Residuals) | D17: MMBtu | E17: 93.8 | F17: 7.2 | G17: 3.6 | H17: =C17*E17/1000 -> 0 | I17: =$C17*$F17*Assumptions!$E$25/1000000 -> 0 | J17: =$C17*G17*Assumptions!$E$27/1000000 -> 0 | K17: =SUM(H17:J17) -> 0 | L17: 2021
A18: 5 | B18: Natural Gas | D18: MMBtu | E18: ='Emission Factors'!D2 -> 0 | F18: ='Emission Factors'!E2 -> 0 | G18: ='Emission Factors'!F2 -> 0 | H18: =C18*E18/1000 -> 0 | I18: =$C18*$F18*Assumptions!$E$25/1000000 -> 0 | J18: =$C18*G18*Assumptions!$E$27/1000000 -> 0 | K18: =SUM(H18:J18) -> 0 | L18: 2022
A19: 6 | B19: Residual Fuel Oil (No. 6) | D19: MMBtu | E19: 75.1 | F19: 3 | G19: 0.6 | H19: =C19*E19/1000 -> 0 | I19: =$C19*$F19*Assumptions!$E$25/1000000 -> 0 | J19: =$C19*G19*Assumptions!$E$27/1000000 -> 0 | K19: =SUM(H19:J19) -> 0 | L19: 2022
A20: 7 | B20: Coal — Bituminous | D20: MMBtu | E20: 93.28 | F20: 11 | G20: 1.6 | H20: =C20*E20/1000 -> 0 | I20: =$C20*$F20*Assumptions!$E$25/1000000 -> 0 | J20: =$C20*G20*Assumptions!$E$27/1000000 -> 0 | K20: =SUM(H20:J20) -> 0 | L20: 2022
A21: 8 | B21: BioFuels Solid (Wood & Wood Residuals) | D21: MMBtu | E21: 93.8 | F21: 7.2 | G21: 3.6 | H21: =C21*E21/1000 -> 0 | I21: =$C21*$F21*Assumptions!$E$25/1000000 -> 0 | J21: =$C21*G21*Assumptions!$E$27/1000000 -> 0 | K21: =SUM(H21:J21) -> 0 | L21: 2022
A22: 1 | B22: Natural Gas | C22: 11165284 | D22: MMBtu | E22: ='Emission Factors'!D6 -> 53.06 | F22: ='Emission Factors'!E6 -> 1 | G22: ='Emission Factors'!F6 -> 0.1 | H22: =C22*E22/1000 -> 592429.98 | I22: =$C22*$F22*Assumptions!$E$25/1000000 -> 332.72547 | J22: =$C22*G22*Assumptions!$E$27/1000000 -> 304.81226 | K22: =SUM(H22:J22) -> 593067.52 | L22: 2023
A23: 2 | B23: Residual Fuel Oil (No. 6) | D23: MMBtu | E23: 75.1 | F23: 3 | G23: 0.6 | H23: =C23*E23/1000 -> 0 | I23: =$C23*$F23*Assumptions!$E$25/1000000 -> 0 | J23: =$C23*G23*Assumptions!$E$27/1000000 -> 0 | K23: =SUM(H23:J23) -> 0 | L23: 2023
A24: 3 | B24: Coal — Bituminous | C24: 635037.39 | D24: MMBtu | E24: 93.28 | F24: 11 | G24: 1.6 | H24: =C24*E24/1000 -> 59236.288 | I24: =$C24*$F24*Assumptions!$E$25/1000000 -> 208.16526 | J24: =$C24*G24*Assumptions!$E$27/1000000 -> 277.38433 | K24: =SUM(H24:J24) -> 59721.837 | L24: 2023
A25: 4 | B25: BioFuels Solid (Wood & Wood Residuals) | C25: 12928224 | D25: MMBtu | E25: 93.8 | F25: 7.2 | G25: 3.6 | H25: =C25*E25/1000 -> 1212667.4 | I25: =$C25*$F25*Assumptions!$E$25/1000000 -> 2773.8797 | J25: =$C25*G25*Assumptions!$E$27/1000000 -> 12705.858 | K25: =SUM(H25:J25) -> 1228147.1 | L25: 2023
A26: 5 | B26: Natural Gas | C26: 10814592 | D26: MMBtu | E26: ='Emission Factors'!D10 -> 2.663 | F26: ='Emission Factors'!E10 -> 0.139 | G26: ='Emission Factors'!F10 -> 0.014 | H26: =C26*E26/1000 -> 28799.258 | I26: =$C26*$F26*Assumptions!$E$25/1000000 -> 44.796203 | J26: =$C26*G26*Assumptions!$E$27/1000000 -> 41.333371 | K26: =SUM(H26:J26) -> 28885.388 | L26: 2024
A27: 6 | B27: Residual Fuel Oil (No. 6) | D27: MMBtu | E27: 75.1 | F27: 3 | G27: 0.6 | H27: =C27*E27/1000 -> 0 | I27: =$C27*$F27*Assumptions!$E$25/1000000 -> 0 | J27: =$C27*G27*Assumptions!$E$27/1000000 -> 0 | K27: =SUM(H27:J27) -> 0 | L27: 2024
A28: 7 | B28: Coal — Bituminous | C28: 388604.97 | D28: MMBtu | E28: 93.28 | F28: 11 | G28: 1.6 | H28: =C28*E28/1000 -> 36249.072 | I28: =$C28*$F28*Assumptions!$E$25/1000000 -> 127.38471 | J28: =$C28*G28*Assumptions!$E$27/1000000 -> 169.74265 | K28: =SUM(H28:J28) -> 36546.199 | L28: 2024
A29: 8 | B29: BioFuels Solid (Wood & Wood Residuals) | C29: 13127265 | D29: MMBtu | E29: 93.8 | F29: 7.2 | G29: 3.6 | H29: =C29*E29/1000 -> 1231337.5 | I29: =$C29*$F29*Assumptions!$E$25/1000000 -> 2816.5861 | J29: =$C29*G29*Assumptions!$E$27/1000000 -> 12901.476 | K29: =SUM(H29:J29) -> 1247055.6 | L29: 2024
B30: SUBTOTAL — Stationary Combustion | H30: =SUM(H22:H29) -> 3160719.5 | I30: =SUM(I22:I29) -> 6303.5374 | J30: =SUM(J22:J29) -> 26400.608 | K30: =SUM(K22:K29) -> 3193423.6
A32: PART B — MOBILE COMBUSTION (Company Fleet, Owned/Leased Vehicles)
A33: # | B33: Fuel Source g | C33: Activity Quantity | D33: Activity Unit | E33: CO₂ EF (kgCO₂/unit) | F33: CH₄ EF (gCH₄/unit) | G33: N₂O EF (gN₂O/unit) | H33: CO₂ (tCO₂) | I33: CH₄ (tCO₂e) | J33: N₂O (tCO₂e) | K33: Total (tCO₂e)
A34: 1 | B34: Gasoline / Petrol (Passenger Cars) | D34: Litres | E34: 2.35 | F34: 0.1 | G34: 0.02 | H34: =C34*E34/1000 -> 0 | I34: =C34*F34/1000000*Assumptions!E25*1000 -> 0 | J34: =C34*G34/1000000*Assumptions!E27*1000 -> 0 | K34: =H34+I34+J34 -> 0
A35: 2 | B35: Gasoline / Petrol (Heavy-Duty Trucks) | D35: Litres | E35: 2.35 | F35: 0.1 | G35: 0.02 | H35: =C35*E35/1000 -> 0 | I35: =C35*F35/1000000*Assumptions!E25*1000 -> 0 | J35: =C35*G35/1000000*Assumptions!E27*1000 -> 0 | K35: =H35+I35+J35 -> 0
A36: 3 | B36: Diesel (Passenger Cars) | D36: Litres | E36: 2.69 | F36: 0.11 | G36: 0.02 | H36: =C36*E36/1000 -> 0 | I36: =C36*F36/1000000*Assumptions!E25*1000 -> 0 | J36: =C36*G36/1000000*Assumptions!E27*1000 -> 0 | K36: =H36+I36+J36 -> 0
A37: 4 | B37: Diesel (Heavy-Duty Trucks) | D37: Litres | E37: 2.69 | F37: 0.11 | G37: 0.02 | H37: =C37*E37/1000 -> 0 | I37: =C37*F37/1000000*Assumptions!E25*1000 -> 0 | J37: =C37*G37/1000000*Assumptions!E27*1000 -> 0 | K37: =H37+I37+J37 -> 0
A38: 5 | B38: Compressed Natural Gas (CNG) | D38: GJ | E38: 56.1 | F38: 0.95 | G38: 0.1 | H38: =C38*E38/1000 -> 0 | I38: =C38*F38/1000000*Assumptions!E25*1000 -> 0 | J38: =C38*G38/1000000*Assumptions!E27*1000 -> 0 | K38: =H38+I38+J38 -> 0
A39: 6 | B39: Aviation Fuel (Jet-A) | D39: Litres | E39: 2.54 | F39: 0.11 | G39: 0.02 | H39: =C39*E39/1000 -> 0 | I39: =C39*F39/1000000*Assumptions!E25*1000 -> 0 | J39: =C39*G39/1000000*Assumptions!E27*1000 -> 0 | K39: =H39+I39+J39 -> 0
A40: 7 | B40: Other / Specify | D40: Specify unit | E40: 0 | F40: 0 | G40: 0 | H40: =C40*E40/1000 -> 0 | I40: =C40*F40/1000000*Assumptions!E25*1000 -> 0 | J40: =C40*G40/1000000*Assumptions!E27*1000 -> 0 | K40: =H40+I40+J40 -> 0
B41: SUBTOTAL — Mobile Combustion | H41: =SUM(H34:H40) -> 0 | I41: =SUM(I34:I40) -> 0 | J41: =SUM(J34:J40) -> 0 | K41: =SUM(K34:K40) -> 0
A43: PART C — FUGITIVE EMISSIONS (Refrigerants, Methane Leaks, SF₆)
A44: # | B44: Refrigerant / Gas Type | C44: Quantity Leaked | D44: Unit | E44: GWP Factor h | K44: Total (tCO₂e)
A45: 1 | B45: HFC-134a (Air Conditioning) | D45: kg | E45: 1430 | K45: =C45*E45/1000 -> 0
A46: 2 | B46: HFC-410A (Air Conditioning) | D46: kg | E46: 2088 | K46: =C46*E46/1000 -> 0
A47: 3 | B47: SF₆ (Electrical Switchgear) | D47: kg | E47: 22800 | K47: =C47*E47/1000 -> 0
A48: 4 | B48: CH₄ — Natural Gas Leaks (pipeline) | D48: kg | E48: 25 | K48: =C48*E48/1000 -> 0
A49: 5 | B49: CO₂ — Fire Suppression Systems | D49: kg | E49: 1 | K49: =C49*E49/1000 -> 0
A50: 6 | B50: Other refrigerant (specify) | D50: kg | E50: 0 | K50: =C50*E50/1000 -> 0
B51: SUBTOTAL — Fugitive Emissions | K51: =SUM(K45:K50) -> 0
A53: ✦ SCOPE 1 TOTAL (tCO₂e) ✦ | K53: =K51+K41+K30 -> 3193423.6
B54: epa.gov/system/files/documents/2024-02/ghg-emission-factors-hub-2024.pdf | K54: Change cell for sum of all
B55: a EPA publishes factors per MMBtu, not per m³. These values are consistent with standard conversions from 1 m³ ≈ 0.0366 MMBtu.
B56: b CO₂: 73.96 kg/MMBtu ; CH₄: 3.0 g/MMBtu ; N₂O: 0.60 g/MMBtu --> Converted to liters (≈0.138 MMBtu/gal → 0.0365 MMBtu/L)
B57: c CO₂: 75.36 kg/MMBtu --> converted to liters
B58: d CO₂: 61.46 kg/MMBtu --> Converted to liters
B59: e CH₄: 11g/MMBtu x 24.93 MMBtu/short ton =274 g/short ton N₂O: 1.6 g/MMBtu x 24.93=40 g / short ton
B60: f EPA lists it as: CO₂: 1.64 metric tons CO₂ per short ton of wood → which is 1,640 kg CO₂/short ton
B61: g CO₂ factors- Taken from EPA fuel CO₂ factors (per gallon) and converted to kg/L: Gasoline ≈ 2.35 kg/L ; Diesel ≈ 2.69 kg/L ; Jet fuel ≈ 2.54 kg/L ; CNG: 56.1 kg CO₂/GJ is the standard natural gas combustion factor.
B62: h IPCC generation (AR4 style)

Sheet Scope 1 W
A1: SCOPE 1 — DIRECT GHG EMISSIONS | GHG Protocol: All sources your organization directly controls
A2: Enter activity data (fuel consumed, distance driven, refrigerant leaked). Emission factors are pre-loaded from EPA/DEFRA tables.
A4: PART A — STATIONARY COMBUSTION (Boilers, Furnaces, Generators, Turbines)
A5: # | B5: Fuel Source | C5: Activity Quantity | D5: Activity Unit | E5: CO₂ EF (kgCO₂/unit) | F5: CH₄ EF (gCH₄/unit) | G5: N₂O EF (gN₂O/unit) | H5: CO₂ (tCO₂) | I5: CH₄ (tCO₂e) | J5: N₂O (tCO₂e) | K5: Total (tCO₂e) | L5: Reporting Year
A6: 1 | B6: Natural Gas | D6: MMBtu | E6: ='Emission Factors'!$D$6 -> 53.06 | F6: ='Emission Factors'!$E$6 -> 1 | G6: ='Emission Factors'!$F$6 -> 0.1 | H6: =C6*E6/1000 -> 0 | I6: =$C6*$F6*Assumptions!$E$25/1000000 -> 0 | J6: =$C6*G6*Assumptions!$E$27/1000000 -> 0 | K6: =SUM(H6:J6) -> 0 | L6: 2019
A7: 2 | B7: Residual Fuel Oil (No. 6) | D7: MMBtu | E7: 75.1 | F7: 3 | G7: 0.6 | H7: =C7*E7/1000 -> 0 | I7: =$C7*$F7*Assumptions!$E$25/1000000 -> 0 | J7: =$C7*G7*Assumptions!$E$27/1000000 -> 0 | K7: =SUM(H7:J7) -> 0 | L7: 2019
A8: 3 | B8: Coal — Bituminous | D8: MMBtu | E8: 93.28 | F8: 11 | G8: 1.6 | H8: =C8*E8/1000 -> 0 | I8: =$C8*$F8*Assumptions!$E$25/1000000 -> 0 | J8: =$C8*G8*Assumptions!$E$27/1000000 -> 0 | K8: =SUM(H8:J8) -> 0 | L8: 2019
A9: 4 | B9: BioFuels Solid (Wood & Wood Residuals) | D9: MMBtu | E9: 93.8 | F9: 7.2 | G9: 3.6 | H9: =C9*E9/1000 -> 0 | I9: =$C9*$F9*Assumptions!$E$25/1000000 -> 0 | J9: =$C9*G9*Assumptions!$E$27/1000000 -> 0 | K9: =SUM(H9:J9) -> 0 | L9: 2019
A10: 5 | B10: Natural Gas | D10: MMBtu | E10: ='Emission Factors'!$D$6 -> 53.06 | F10: ='Emission Factors'!$E$6 -> 1 | G10: ='Emission Factors'!$F$6 -> 0.1 | H10: =C10*E10/1000 -> 0 | I10: =$C10*$F10*Assumptions!$E$25/1000000 -> 0 | J10: =$C10*G10*Assumptions!$E$27/1000000 -> 0 | K10: =SUM(H10:J10) -> 0 | L10: 2020
A11: 6 | B11: Residual Fuel Oil (No. 6) | D11: MMBtu | E11: 75.1 | F11: 3 | G11: 0.6 | H11: =C11*E11/1000 -> 0 | I11: =$C11*$F11*Assumptions!$E$25/1000000 -> 0 | J11: =$C11*G11*Assumptions!$E$27/1000000 -> 0 | K11: =SUM(H11:J11) -> 0 | L11: 2020
A12: 7 | B12: Coal — Bituminous | D12: MMBtu | E12: 93.28 | F12: 11 | G12: 1.6 | H12: =C12*E12/1000 -> 0 | I12: =$C12*$F12*Assumptions!$E$25/1000000 -> 0 | J12: =$C12*G12*Assumptions!$E$27/1000000 -> 0 | K12: =SUM(H12:J12) -> 0 | L12: 2020
A13: 8 | B13: BioFuels Solid (Wood & Wood Residuals) | D13: MMBtu | E13: 93.8 | F13: 7.2 | G13: 3.6 | H13: =C13*E13/1000 -> 0 | I13: =$C13*$F13*Assumptions!$E$25/1000000 -> 0 | J13: =$C13*G13*Assumptions!$E$27/1000000 -> 0 | K13: =SUM(H13:J13) -> 0 | L13: 2020
A14: 1 | B14: Natural Gas | D14: MMBtu | E14: ='Emission Factors'!$D$6 -> 53.06 | F14: ='Emission Factors'!$E$6 -> 1 | G14: ='Emission Factors'!$F$6 -> 0.1 | H14: =C14*E14/1000 -> 0 | I14: =$C14*$F14*Assumptions!$E$25/1000000 -> 0 | J14: =$C14*G14*Assumptions!$E$27/1000000 -> 0 | K14: =SUM(H14:J14) -> 0 | L14: 2021
A15: 2 | B15: Residual Fuel Oil (No. 6) | D15: MMBtu | E15: 75.1 | F15: 3 | G15: 0.6 | H15: =C15*E15/1000 -> 0 | I15: =$C15*$F15*Assumptions!$E$25/1000000 -> 0 | J15: =$C15*G15*Assumptions!$E$27/1000000 -> 0 | K15: =SUM(H15:J15) -> 0 | L15: 2021
A16: 3 | B16: Coal — Bituminous | D16: MMBtu | E16: 93.28 | F16: 11 | G16: 1.6 | H16: =C16*E16/1000 -> 0 | I16: =$C16*$F16*Assumptions!$E$25/1000000 -> 0 | J16: =$C16*G16*Assumptions!$E$27/1000000 -> 0 | K16: =SUM(H16:J16) -> 0 | L16: 2021
A17: 4 | B17: BioFuels Solid (Wood & Wood Residuals) | D17: MMBtu | E17: 93.8 | F17: 7.2 | G17: 3.6 | H17: =C17*E17/1000 -> 0 | I17: =$C17*$F17*Assumptions!$E$25/1000000 -> 0 | J17: =$C17*G17*Assumptions!$E$27/1000000 -> 0 | K17: =SUM(H17:J17) -> 0 | L17: 2021
A18: 5 | B18: Natural Gas | D18: MMBtu | E18: ='Emission Factors'!D2 -> 0 | F18: ='Emission Factors'!E2 -> 0 | G18: ='Emission Factors'!F2 -> 0 | H18: =C18*E18/1000 -> 0 | I18: =$C18*$F18*Assumptions!$E$25/1000000 -> 0 | J18: =$C18*G18*Assumptions!$E$27/1000000 -> 0 | K18: =SUM(H18:J18) -> 0 | L18: 2022
A19: 6 | B19: Residual Fuel Oil (No. 6) | D19: MMBtu | E19: 75.1 | F19: 3 | G19: 0.6 | H19: =C19*E19/1000 -> 0 | I19: =$C19*$F19*Assumptions!$E$25/1000000 -> 0 | J19: =$C19*G19*Assumptions!$E$27/1000000 -> 0 | K19: =SUM(H19:J19) -> 0 | L19: 2022
A20: 7 | B20: Coal — Bituminous | D20: MMBtu | E20: 93.28 | F20: 11 | G20: 1.6 | H20: =C20*E20/1000 -> 0 | I20: =$C20*$F20*Assumptions!$E$25/1000000 -> 0 | J20: =$C20*G20*Assumptions!$E$27/1000000 -> 0 | K20: =SUM(H20:J20) -> 0 | L20: 2022
A21: 8 | B21: BioFuels Solid (Wood & Wood Residuals) | D21: MMBtu | E21: 93.8 | F21: 7.2 | G21: 3.6 | H21: =C21*E21/1000 -> 0 | I21: =$C21*$F21*Assumptions!$E$25/1000000 -> 0 | J21: =$C21*G21*Assumptions!$E$27/1000000 -> 0 | K21: =SUM(H21:J21) -> 0 | L21: 2022
A22: 1 | B22: Natural Gas | C22: 86064639 | D22: MMBtu | E22: ='Emission Factors'!$D$6 -> 53.06 | F22: ='Emission Factors'!$E$6 -> 1 | G22: ='Emission Factors'!$F$6 -> 0.1 | H22: =C22*E22/1000 -> 4566589.7 | I22: =$C22*$F22*Assumptions!$E$25/1000000 -> 2564.7262 | J22: =$C22*G22*Assumptions!$E$27/1000000 -> 2349.5646 | K22: =SUM(H22:J22) -> 4571504 | L22: 2023
A23: 2 | B23: Residual Fuel Oil (No. 6) | C23: 1890395 | D23: MMBtu | E23: 75.1 | F23: 3 | G23: 0.6 | H23: =C23*E23/1000 -> 141968.66 | I23: =$C23*$F23*Assumptions!$E$25/1000000 -> 169.00131 | J23: =$C23*G23*Assumptions!$E$27/1000000 -> 309.6467 | K23: =SUM(H23:J23) -> 142447.31 | L23: 2023
A24: 3 | B24: Coal — Bituminous | C24: 14017876 | D24: MMBtu | E24: 93.28 | F24: 11 | G24: 1.6 | H24: =C24*E24/1000 -> 1307587.5 | I24: =$C24*$F24*Assumptions!$E$25/1000000 -> 4595.0598 | J24: =$C24*G24*Assumptions!$E$27/1000000 -> 6123.0082 | K24: =SUM(H24:J24) -> 1318305.5 | L24: 2023
A25: 4 | B25: BioFuels Solid (Wood & Wood Residuals) | C25: 166526977 | D25: MMBtu | E25: 93.8 | F25: 7.2 | G25: 3.6 | H25: =C25*E25/1000 -> 15620230 | I25: =$C25*$F25*Assumptions!$E$25/1000000 -> 35730.028 | J25: =$C25*G25*Assumptions!$E$27/1000000 -> 163662.71 | K25: =SUM(H25:J25) -> 15819623 | L25: 2023
A26: 5 | B26: Natural Gas | C26: 86013345 | D26: MMBtu | E26: ='Emission Factors'!D10 -> 2.663 | F26: ='Emission Factors'!E10 -> 0.139 | G26: ='Emission Factors'!F10 -> 0.014 | H26: =C26*E26/1000 -> 229053.54 | I26: =$C26*$F26*Assumptions!$E$25/1000000 -> 356.28448 | J26: =$C26*G26*Assumptions!$E$27/1000000 -> 328.743 | K26: =SUM(H26:J26) -> 229738.57 | L26: 2024
A27: 6 | B27: Residual Fuel Oil (No. 6) | C27: 1316148 | D27: MMBtu | E27: 75.1 | F27: 3 | G27: 0.6 | H27: =C27*E27/1000 -> 98842.715 | I27: =$C27*$F27*Assumptions!$E$25/1000000 -> 117.66363 | J27: =$C27*G27*Assumptions!$E$27/1000000 -> 215.58504 | K27: =SUM(H27:J27) -> 99175.963 | L27: 2024
A28: 7 | B28: Coal — Bituminous | C28: 9748199 | D28: MMBtu | E28: 93.28 | F28: 11 | G28: 1.6 | H28: =C28*E28/1000 -> 909312 | I28: =$C28*$F28*Assumptions!$E$25/1000000 -> 3195.4596 | J28: =$C28*G28*Assumptions!$E$27/1000000 -> 4258.0133 | K28: =SUM(H28:J28) -> 916765.48 | L28: 2024
A29: 8 | B29: BioFuels Solid (Wood & Wood Residuals) | C29: 160000000 | D29: MMBtu | E29: 93.8 | F29: 7.2 | G29: 3.6 | H29: =C29*E29/1000 -> 15008000 | I29: =$C29*$F29*Assumptions!$E$25/1000000 -> 34329.6 | J29: =$C29*G29*Assumptions!$E$27/1000000 -> 157248 | K29: =SUM(H29:J29) -> 15199578 | L29: 2024
B30: SUBTOTAL — Stationary Combustion | H30: =SUM(H22:H29) -> 37881585 | I30: =SUM(I22:I29) -> 81057.823 | J30: =SUM(J22:J29) -> 334495.27 | K30: =SUM(K22:K29) -> 38297138
A32: PART B — MOBILE COMBUSTION (Company Fleet, Owned/Leased Vehicles)
A33: # | B33: Fuel Source g | C33: Activity Quantity | D33: Activity Unit | E33: CO₂ EF (kgCO₂/unit) | F33: CH₄ EF (gCH₄/unit) | G33: N₂O EF (gN₂O/unit) | H33: CO₂ (tCO₂) | I33: CH₄ (tCO₂e) | J33: N₂O (tCO₂e) | K33: Total (tCO₂e)
A34: 1 | B34: Gasoline / Petrol (Passenger Cars) | D34: Litres | E34: 2.35 | F34: 0.1 | G34: 0.02 | H34: =C34*E34/1000 -> 0 | I34: =C34*F34/1000000*Assumptions!E25*1000 -> 0 | J34: =C34*G34/1000000*Assumptions!E27*1000 -> 0 | K34: =H34+I34+J34 -> 0
A35: 2 | B35: Gasoline / Petrol (Heavy-Duty Trucks) | D35: Litres | E35: 2.35 | F35: 0.1 | G35: 0.02 | H35: =C35*E35/1000 -> 0 | I35: =C35*F35/1000000*Assumptions!E25*1000 -> 0 | J35: =C35*G35/1000000*Assumptions!E27*1000 -> 0 | K35: =H35+I35+J35 -> 0
A36: 3 | B36: Diesel (Passenger Cars) | D36: Litres | E36: 2.69 | F36: 0.11 | G36: 0.02 | H36: =C36*E36/1000 -> 0 | I36: =C36*F36/1000000*Assumptions!E25*1000 -> 0 | J36: =C36*G36/1000000*Assumptions!E27*1000 -> 0 | K36: =H36+I36+J36 -> 0
A37: 4 | B37: Diesel (Heavy-Duty Trucks) | D37: Litres | E37: 2.69 | F37: 0.11 | G37: 0.02 | H37: =C37*E37/1000 -> 0 | I37: =C37*F37/1000000*Assumptions!E25*1000 -> 0 | J37: =C37*G37/1000000*Assumptions!E27*1000 -> 0 | K37: =H37+I37+J37 -> 0
A38: 5 | B38: Compressed Natural Gas (CNG) | D38: GJ | E38: 56.1 | F38: 0.95 | G38: 0.1 | H38: =C38*E38/1000 -> 0 | I38: =C38*F38/1000000*Assumptions!E25*1000 -> 0 | J38: =C38*G38/1000000*Assumptions!E27*1000 -> 0 | K38: =H38+I38+J38 -> 0
A39: 6 | B39: Aviation Fuel (Jet-A) | D39: Litres | E39: 2.54 | F39: 0.11 | G39: 0.02 | H39: =C39*E39/1000 -> 0 | I39: =C39*F39/1000000*Assumptions!E25*1000 -> 0 | J39: =C39*G39/1000000*Assumptions!E27*1000 -> 0 | K39: =H39+I39+J39 -> 0
A40: 7 | B40: Other / Specify | D40: Specify unit | E40: 0 | F40: 0 | G40: 0 | H40: =C40*E40/1000 -> 0 | I40: =C40*F40/1000000*Assumptions!E25*1000 -> 0 | J40: =C40*G40/1000000*Assumptions!E27*1000 -> 0 | K40: =H40+I40+J40 -> 0
B41: SUBTOTAL — Mobile Combustion | H41: =SUM(H34:H40) -> 0 | I41: =SUM(I34:I40) -> 0 | J41: =SUM(J34:J40) -> 0 | K41: =SUM(K34:K40) -> 0
A43: PART C — FUGITIVE EMISSIONS (Refrigerants, Methane Leaks, SF₆)
A44: # | B44: Refrigerant / Gas Type | C44: Quantity Leaked | D44: Unit | E44: GWP Factor h | K44: Total (tCO₂e)
A45: 1 | B45: HFC-134a (Air Conditioning) | D45: kg | E45: 1430 | K45: =C45*E45/1000 -> 0
A46: 2 | B46: HFC-410A (Air Conditioning) | D46: kg | E46: 2088 | K46: =C46*E46/1000 -> 0
A47: 3 | B47: SF₆ (Electrical Switchgear) | D47: kg | E47: 22800 | K47: =C47*E47/1000 -> 0
A48: 4 | B48: CH₄ — Natural Gas Leaks (pipeline) | D48: kg | E48: 25 | K48: =C48*E48/1000 -> 0
A49: 5 | B49: CO₂ — Fire Suppression Systems | D49: kg | E49: 1 | K49: =C49*E49/1000 -> 0
A50: 6 | B50: Other refrigerant (specify) | D50: kg | E50: 0 | K50: =C50*E50/1000 -> 0
B51: SUBTOTAL — Fugitive Emissions | K51: =SUM(K45:K50) -> 0
A53: ✦ SCOPE 1 TOTAL (tCO₂e) ✦ | K53: =K51+K41+K30 -> 38297138
B54: epa.gov/system/files/documents/2024-02/ghg-emission-factors-hub-2024.pdf | K54: Change cell for sum of all
B55: a EPA publishes factors per MMBtu, not per m³. These values are consistent with standard conversions from 1 m³ ≈ 0.0366 MMBtu.
B56: b CO₂: 73.96 kg/MMBtu ; CH₄: 3.0 g/MMBtu ; N₂O: 0.60 g/MMBtu --> Converted to liters (≈0.138 MMBtu/gal → 0.0365 MMBtu/L)
B57: c CO₂: 75.36 kg/MMBtu --> converted to liters
B58: d CO₂: 61.46 kg/MMBtu --> Converted to liters
B59: e CH₄: 11g/MMBtu x 24.93 MMBtu/short ton =274 g/short ton N₂O: 1.6 g/MMBtu x 24.93=40 g / short ton
B60: f EPA lists it as: CO₂: 1.64 metric tons CO₂ per short ton of wood → which is 1,640 kg CO₂/short ton
B61: g CO₂ factors- Taken from EPA fuel CO₂ factors (per gallon) and converted to kg/L: Gasoline ≈ 2.35 kg/L ; Diesel ≈ 2.69 kg/L ; Jet fuel ≈ 2.54 kg/L ; CNG: 56.1 kg CO₂/GJ is the standard natural gas combustion factor.
B62: h IPCC generation (AR4 style)

Sheet Scope 2 S
A1: SCOPE 2 — PURCHASED ENERGY | Dual Reporting: Market-Based AND Location-Based (GHG Protocol Required)
A2: GHG Protocol requires BOTH methods. Market-based reflects supplier contracts & RECs. Location-based uses grid averages.
A4: PART A — PURCHASED ELECTRICITY
A5: REFERENCE — Grid Emission Factors (kgCO₂e/MWh) | Source: IEA CO₂ Emissions from Fuel Combustion 2023 | CarbonFootprint.com (2025) Update annually
A6: Country/Region | B6: Grid EF (kgCO₂e/MWh)
A7: US Average | B7: 386 | C7: China | D7: 581
A8: US — California | B8: 230 | C8: India | D8: 713
A9: US — Texas (ERCOT) | B9: 430 | C9: Japan | D9: 471
A10: European Union Avg | B10: 231 | C10: Australia | D10: 680
A11: United Kingdom | B11: 207 | C11: Brazil | D11: 119
A12: Germany | B12: 380 | C12: Canada | D12: 130
A14: ELECTRICITY CONSUMPTION DATA
A15: # | B15: Facility / Region | C15: Electricity Consumed (MWh) | D15: Location-Based EF (kgCO₂/MWh) | E15: Market-Based EF (kgCO₂/MWh) | F15: RECs / PPAs (MWh covered) * | G15: Net Market- Based MWh | H15: Location-Based (tCO₂e) | I15: Market-Based (tCO₂e) | J15: Notes | K15: Reporting Year
A16: 1 | B16: Europe | C16: 0 | D16: 386 | E16: 0 | F16: 0 | G16: =MAX(C16-F16,0) -> 0 | H16: =C16*D16/1000 -> 0 | I16: =G16*E16/1000 -> 0 | J16: [Notes on EF source, REC details] | K16: 2019
A17: 2 | B17: The Americas | C17: 0 | D17: 386 | E17: 0 | F17: 0 | G17: =MAX(C17-F17,0) -> 0 | H17: =C17*D17/1000 -> 0 | I17: =G17*E17/1000 -> 0 | J17: [Notes on EF source, REC details] | K17: 2019
A18: 3 | B18: Europe | C18: 0 | D18: 386 | E18: 0 | F18: 0 | G18: =MAX(C18-F18,0) -> 0 | H18: =C18*D18/1000 -> 0 | I18: =G18*E18/1000 -> 0 | J18: [Notes on EF source, REC details] | K18: 2020
A19: 4 | B19: The Americas | C19: 0 | D19: 386 | E19: 0 | F19: 0 | G19: =MAX(C19-F19,0) -> 0 | H19: =C19*D19/1000 -> 0 | I19: =G19*E19/1000 -> 0 | J19: [Notes on EF source, REC details] | K19: 2020
A20: 1 | B20: Europe | C20: 0 | D20: 386 | E20: 0 | F20: 0 | G20: =MAX(C20-F20,0) -> 0 | H20: =C20*D20/1000 -> 0 | I20: =G20*E20/1000 -> 0 | J20: [Notes on EF source, REC details] | K20: 2021
A21: 2 | B21: The Americas | C21: 0 | D21: 386 | E21: 0 | F21: 0 | G21: =MAX(C21-F21,0) -> 0 | H21: =C21*D21/1000 -> 0 | I21: =G21*E21/1000 -> 0 | J21: [Notes on EF source, REC details] | K21: 2021
A22: 3 | B22: Europe | C22: 0 | D22: 386 | E22: 0 | F22: 0 | G22: =MAX(C22-F22,0) -> 0 | H22: =C22*D22/1000 -> 0 | I22: =G22*E22/1000 -> 0 | J22: [Notes on EF source, REC details] | K22: 2022
A23: 4 | B23: The Americas | C23: 0 | D23: 386 | E23: 0 | F23: 0 | G23: =MAX(C23-F23,0) -> 0 | H23: =C23*D23/1000 -> 0 | I23: =G23*E23/1000 -> 0 | J23: [Notes on EF source, REC details] | K23: 2022
A24: 1 | B24: Europe | C24: 0 | D24: 386 | E24: 0 | F24: 0 | G24: =MAX(C24-F24,0) -> 0 | H24: =C24*D24/1000 -> 0 | I24: =G24*E24/1000 -> 0 | J24: [Notes on EF source, REC details] | K24: 2024
A25: 2 | B25: The Americas | C25: 0 | D25: 386 | E25: 0 | F25: 0 | G25: =MAX(C25-F25,0) -> 0 | H25: =C25*D25/1000 -> 0 | I25: =G25*E25/1000 -> 0 | J25: [Notes on EF source, REC details] | K25: 2024
A26: 3 | B26: Europe | C26: 0 | D26: 386 | E26: 0 | F26: 0 | G26: =MAX(C26-F26,0) -> 0 | H26: =C26*D26/1000 -> 0 | I26: =G26*E26/1000 -> 0 | J26: [Notes on EF source, REC details] | K26: 2023
A27: 4 | B27: The Americas | C27: 0 | D27: 386 | E27: 0 | F27: 0 | G27: =MAX(C27-F27,0) -> 0 | H27: =C27*D27/1000 -> 0 | I27: =G27*E27/1000 -> 0 | J27: [Notes on EF source, REC details] | K27: 2023
A28: 5 | E28: 0 | F28: 0 | G28: =MAX(C28-F28,0) -> 0 | H28: =C28*D28/1000 -> 0 | I28: =G28*E28/1000 -> 0 | J28: [Notes on EF source, REC details]
A29: 6 | E29: 0 | F29: 0 | G29: =MAX(C29-F29,0) -> 0 | H29: =C29*D29/1000 -> 0 | I29: =G29*E29/1000 -> 0 | J29: [Notes on EF source, REC details]
A30: 7 | E30: 0 | F30: 0 | G30: =MAX(C30-F30,0) -> 0 | H30: =C30*D30/1000 -> 0 | I30: =G30*E30/1000 -> 0 | J30: [Notes on EF source, REC details]
B31: SUBTOTAL — Electricity | C31: 30207220 | F31: 29829540 | G31: =SUM(G24:G30) -> 0
A33: PART B — OTHER PURCHASED ENERGY (Steam, Heat, Cooling)
A34: # | B34: Energy Type | C34: Quantity Consumed | D34: Unit | E34: CO2 Factor (kg CO2 / mmBtu) | F34: CH4 Factor (g CH4 / mmBtu) | G34: N2O Factor (g N2O / mmBtu) | H34: Location-Based (tCO₂e) | I34: Market-Based (tCO₂e) | J34: Notes
A35: 1 | B35: Steam and Heat (Purchased) | D35: MMBtu | E35: 66.33 | F35: 1.25 | G35: 0.125 | H35: =((E35*C35)/1000)+((C35*F35*Assumptions!E25)/1000000)+(('Scope 2 S'!C35*'Scope 2 S'!G35*Assumptions!E27)/1000000) -> 0 | I35: =C35*E35/1000 -> 0 | J35: EPA Table 1
A36: 2 | B36: Steam and Heat (Sold) | D36: MMBtu | E36: 66.33 | F36: 1.25 | G36: 0.125 | H36: =C36*E36/1000 -> 0 | I36: =C36*E36/1000 -> 0 | J36: EPA Table 1
A37: 3 | C37: 0 | D37: GJ | E37: 66.4 | H37: =C37*E37/1000 -> 0 | I37: =C37*E37/1000 -> 0 | J37: [Source of emission factor]
B38: SUBTOTAL — Other Energy | H38: =((E35*C35)/1000)+((C35*F35*Assumptions!E25)/1000000)+('Scope 2 S'!C35*'Scope 2 S'!G35*Assumptions!E27)/1000000 -> 0 | I38: =SUM(I35:I37) -> 0
A40: ✦ SCOPE 2 TOTAL — LOCATION-BASED (tCO₂e) ✦ | H40: =H31+H38 -> 0
A41: ✦ SCOPE 2 TOTAL — MARKET-BASED (tCO₂e) [USE THIS FOR REPORTING] ✦ | I41: 0
A42: *(Renewable Energy Certificates) ; PPAs (Power Purchase Agreements) ; GOs (Guarantees of Origin, in Europe) ; I‑RECs (International RECs, global markets)
I44: Market | J44: Location | K44: ktons
H45: 2023 | K45: 467
H46: 2024 | K46: 479

Sheet Scope 2 W
A1: SCOPE 2 — PURCHASED ENERGY | Dual Reporting: Market-Based AND Location-Based (GHG Protocol Required)
A2: GHG Protocol requires BOTH methods. Market-based reflects supplier contracts & RECs. Location-based uses grid averages.
A4: PART A — PURCHASED ELECTRICITY
A5: REFERENCE — Grid Emission Factors (kgCO₂e/MWh) | Source: IEA CO₂ Emissions from Fuel Combustion 2023 | CarbonFootprint.com (2025) Update annually
A6: Country/Region | B6: Grid EF (kgCO₂e/MWh)
A7: US Average | B7: 386 | C7: China | D7: 581
A8: US — California | B8: 230 | C8: India | D8: 713
A9: US — Texas (ERCOT) | B9: 430 | C9: Japan | D9: 471
A10: European Union Avg | B10: 231 | C10: Australia | D10: 680
A11: United Kingdom | B11: 207 | C11: Brazil | D11: 119
A12: Germany | B12: 380 | C12: Canada | D12: 130
A14: ELECTRICITY CONSUMPTION DATA
A15: # | B15: Facility / Region | C15: Electricity Consumed (MWh) | D15: Location-Based EF (kgCO₂/MWh) | E15: Market-Based EF (kgCO₂/MWh) | F15: RECs / PPAs (MWh covered) * | G15: Net Market- Based MWh | H15: Location-Based (tCO₂e) | I15: Market-Based (tCO₂e) | J15: Notes | K15: Reporting Year
A16: 1 | B16: USA | C16: 1300000 | D16: 386 | E16: 0 | F16: 0 | G16: =MAX(C16-F16,0) -> 1300000 | H16: =C16*D16/1000 -> 501800 | I16: =G16*E16/1000 -> 0 | J16: [Notes on EF source, REC details] | K16: 2019
A17: 2 | B17: Canada | C17: 800000 | D17: 130 | E17: 0 | F17: 0 | G17: =MAX(C17-F17,0) -> 800000 | H17: =C17*D17/1000 -> 104000 | I17: =G17*E17/1000 -> 0 | J17: [Notes on EF source, REC details] | K17: 2019
A18: 3 | B18: Mexico | C18: 900000 | D18: 408 | E18: 0 | F18: 0 | G18: =MAX(C18-F18,0) -> 900000 | H18: =C18*D18/1000 -> 367200 | I18: =G18*E18/1000 -> 0 | J18: [Notes on EF source, REC details] | K18: 2019
A19: 4 | B19: Brazil | C19: 400000 | D19: 119 | E19: 0 | F19: 0 | G19: =MAX(C19-F19,0) -> 400000 | H19: =C19*D19/1000 -> 47600 | I19: =G19*E19/1000 -> 0 | J19: [Notes on EF source, REC details] | K19: 2019
A20: 5 | B20: Europe | C20: 200000 | D20: 250 | E20: 0 | F20: 0 | G20: =MAX(C20-F20,0) -> 200000 | H20: =C20*D20/1000 -> 50000 | I20: =G20*E20/1000 -> 0 | J20: [Notes on EF source, REC details] | K20: 2019
A21: 6 | B21: USA | C21: =C16*0.75 -> 975000 | D21: 386 | E21: 0 | F21: 0 | G21: =MAX(C21-F21,0) -> 975000 | H21: =C21*D21/1000 -> 376350 | I21: =G21*E21/1000 -> 0 | J21: [Notes on EF source, REC details] | K21: 2020
A22: 7 | B22: Canada | C22: =C17*0.75 -> 600000 | D22: 130 | E22: 0 | F22: 0 | G22: =MAX(C22-F22,0) -> 600000 | H22: =C22*D22/1000 -> 78000 | I22: =G22*E22/1000 -> 0 | J22: [Notes on EF source, REC details] | K22: 2020
A23: 8 | B23: Mexico | C23: =C18*0.75 -> 675000 | D23: 408 | E23: 0 | F23: 0 | G23: =MAX(C23-F23,0) -> 675000 | H23: =C23*D23/1000 -> 275400 | I23: =G23*E23/1000 -> 0 | J23: [Notes on EF source, REC details] | K23: 2020
A24: 9 | B24: Brazil | C24: =C19*0.75 -> 300000 | D24: 119 | E24: 0 | F24: 0 | G24: =MAX(C24-F24,0) -> 300000 | H24: =C24*D24/1000 -> 35700 | I24: =G24*E24/1000 -> 0 | J24: [Notes on EF source, REC details] | K24: 2020
A25: 10 | B25: Europe | C25: =C20*0.75 -> 150000 | D25: 250 | E25: 0 | F25: 0 | G25: =MAX(C25-F25,0) -> 150000 | H25: =C25*D25/1000 -> 37500 | I25: =G25*E25/1000 -> 0 | J25: [Notes on EF source, REC details] | K25: 2020
A26: 1 | B26: USA | C26: 1300000 | D26: 386 | E26: 0 | F26: 0 | G26: =MAX(C26-F26,0) -> 1300000 | H26: =C26*D26/1000 -> 501800 | I26: =G26*E26/1000 -> 0 | J26: [Notes on EF source, REC details] | K26: 2021
A27: 2 | B27: Canada | C27: 800000 | D27: 130 | E27: 0 | F27: 0 | G27: =MAX(C27-F27,0) -> 800000 | H27: =C27*D27/1000 -> 104000 | I27: =G27*E27/1000 -> 0 | J27: [Notes on EF source, REC details] | K27: 2021
A28: 3 | B28: Mexico | C28: 900000 | D28: 408 | E28: 0 | F28: 0 | G28: =MAX(C28-F28,0) -> 900000 | H28: =C28*D28/1000 -> 367200 | I28: =G28*E28/1000 -> 0 | J28: [Notes on EF source, REC details] | K28: 2021
A29: 4 | B29: Brazil | C29: 400000 | D29: 119 | E29: 0 | F29: 0 | G29: =MAX(C29-F29,0) -> 400000 | H29: =C29*D29/1000 -> 47600 | I29: =G29*E29/1000 -> 0 | J29: [Notes on EF source, REC details] | K29: 2021
A30: 5 | B30: Europe | C30: 200000 | D30: 250 | E30: 0 | F30: 0 | G30: =MAX(C30-F30,0) -> 200000 | H30: =C30*D30/1000 -> 50000 | I30: =G30*E30/1000 -> 0 | J30: [Notes on EF source, REC details] | K30: 2021
A31: 6 | B31: USA | C31: =C26*0.75 -> 975000 | D31: 386 | E31: 0 | F31: 0 | G31: =MAX(C31-F31,0) -> 975000 | H31: =C31*D31/1000 -> 376350 | I31: =G31*E31/1000 -> 0 | J31: [Notes on EF source, REC details] | K31: 2022
A32: 7 | B32: Canada | C32: =C27*0.75 -> 600000 | D32: 130 | E32: 0 | F32: 0 | G32: =MAX(C32-F32,0) -> 600000 | H32: =C32*D32/1000 -> 78000 | I32: =G32*E32/1000 -> 0 | J32: [Notes on EF source, REC details] | K32: 2022
A33: 8 | B33: Mexico | C33: =C28*0.75 -> 675000 | D33: 408 | E33: 0 | F33: 0 | G33: =MAX(C33-F33,0) -> 675000 | H33: =C33*D33/1000 -> 275400 | I33: =G33*E33/1000 -> 0 | J33: [Notes on EF source, REC details] | K33: 2022
A34: 9 | B34: Brazil | C34: =C29*0.75 -> 300000 | D34: 119 | E34: 0 | F34: 0 | G34: =MAX(C34-F34,0) -> 300000 | H34: =C34*D34/1000 -> 35700 | I34: =G34*E34/1000 -> 0 | J34: [Notes on EF source, REC details] | K34: 2022
A35: 10 | B35: Europe | C35: =C30*0.75 -> 150000 | D35: 250 | E35: 0 | F35: 0 | G35: =MAX(C35-F35,0) -> 150000 | H35: =C35*D35/1000 -> 37500 | I35: =G35*E35/1000 -> 0 | J35: [Notes on EF source, REC details] | K35: 2022
A36: 1 | B36: USA | C36: 1300000 | D36: 386 | E36: 0 | F36: 0 | G36: =MAX(C36-F36,0) -> 1300000 | H36: =C36*D36/1000 -> 501800 | I36: =G36*E36/1000 -> 0 | J36: [Notes on EF source, REC details] | K36: 2023
A37: 2 | B37: Canada | C37: 800000 | D37: 130 | E37: 0 | F37: 0 | G37: =MAX(C37-F37,0) -> 800000 | H37: =C37*D37/1000 -> 104000 | I37: =G37*E37/1000 -> 0 | J37: [Notes on EF source, REC details] | K37: 2023
A38: 3 | B38: Mexico | C38: 900000 | D38: 408 | E38: 0 | F38: 0 | G38: =MAX(C38-F38,0) -> 900000 | H38: =C38*D38/1000 -> 367200 | I38: =G38*E38/1000 -> 0 | J38: [Notes on EF source, REC details] | K38: 2023
A39: 4 | B39: Brazil | C39: 400000 | D39: 119 | E39: 0 | F39: 0 | G39: =MAX(C39-F39,0) -> 400000 | H39: =C39*D39/1000 -> 47600 | I39: =G39*E39/1000 -> 0 | J39: [Notes on EF source, REC details] | K39: 2023
A40: 5 | B40: Europe | C40: 200000 | D40: 250 | E40: 0 | F40: 0 | G40: =MAX(C40-F40,0) -> 200000 | H40: =C40*D40/1000 -> 50000 | I40: =G40*E40/1000 -> 0 | J40: [Notes on EF source, REC details] | K40: 2023
A41: 6 | B41: USA | C41: =C36*0.75 -> 975000 | D41: 386 | E41: 0 | F41: 0 | G41: =MAX(C41-F41,0) -> 975000 | H41: =C41*D41/1000 -> 376350 | I41: =G41*E41/1000 -> 0 | J41: [Notes on EF source, REC details] | K41: 2024
A42: 7 | B42: Canada | C42: =C37*0.75 -> 600000 | D42: 130 | E42: 0 | F42: 0 | G42: =MAX(C42-F42,0) -> 600000 | H42: =C42*D42/1000 -> 78000 | I42: =G42*E42/1000 -> 0 | J42: [Notes on EF source, REC details] | K42: 2024
A43: 8 | B43: Mexico | C43: =C38*0.75 -> 675000 | D43: 408 | E43: 0 | F43: 0 | G43: =MAX(C43-F43,0) -> 675000 | H43: =C43*D43/1000 -> 275400 | I43: =G43*E43/1000 -> 0 | J43: [Notes on EF source, REC details] | K43: 2024
A44: 9 | B44: Brazil | C44: =C39*0.75 -> 300000 | D44: 119 | E44: 0 | F44: 0 | G44: =MAX(C44-F44,0) -> 300000 | H44: =C44*D44/1000 -> 35700 | I44: =G44*E44/1000 -> 0 | J44: [Notes on EF source, REC details] | K44: 2024
A45: 10 | B45: Europe | C45: =C40*0.75 -> 150000 | D45: 250 | E45: 0 | F45: 0 | G45: =MAX(C45-F45,0) -> 150000 | H45: =C45*D45/1000 -> 37500 | I45: =G45*E45/1000 -> 0 | J45: [Notes on EF source, REC details] | K45: 2024
B46: SUBTOTAL — Electricity | G46: =SUM(G36:G40) -> 3600000 | H46: =SUM(H36:H45) -> 1873550
A48: PART B — OTHER PURCHASED ENERGY (Steam, Heat, Cooling)
A49: # | B49: Energy Type | C49: Quantity Consumed | D49: Unit | E49: CO2 Factor (kg CO2 / mmBtu) | F49: CH4 Factor (g CH4 / mmBtu) | G49: N2O Factor (g N2O / mmBtu) | H49: Location-Based (tCO₂e) | I49: Market-Based (tCO₂e) | J49: Notes
A50: 1 | B50: Steam and Heat (Purchased) | C50: 24007727 | D50: MMBtu | E50: 66.33 | F50: 1.25 | G50: 0.125 | H50: =((E50*C50)/1000)+((C50*F50*Assumptions!E25)/1000000)+(('Scope 2 W'!C50*'Scope 2 W'!G50*Assumptions!E27)/1000000) -> 1594146.1 | I50: =C50*E50/1000 -> 1592432.5 | J50: EPA Table 1 | K50: 2023
A51: 2 | B51: Steam and Heat (Sold) | C51: -4930723 | D51: MMBtu | E51: 66.33 | F51: 1.25 | G51: 0.125 | H51: =C51*E51/1000 -> -327054.86 | I51: =C51*E51/1000 -> -327054.86 | J51: EPA Table 1 | K51: 2023
A52: 3 | B52: Power Purchased
A53: 4 | B53: Steam and Heat (Purchased) | C53: 25167585 | D53: MMBtu | E53: 66.33 | F53: 1.25 | G53: 0.125 | H53: =((E53*C53)/1000)+((C53*F53*Assumptions!E27)/1000000)+(('Scope 2 W'!C53*'Scope 2 W'!G53*Assumptions!E29)/1000000) -> 1757232.2 | I53: =C53*E53/1000 -> 1669365.9 | J53: EPA Table 1 | K53: 2024
A54: 5 | B54: Steam and Heat (Sold) | C54: -3777351 | D54: MMBtu | E54: 66.33 | F54: 1.25 | G54: 0.125 | H54: =C54*E54/1000 -> -250551.69 | I54: =C54*E54/1000 -> -250551.69 | J54: EPA Table 1 | K54: 2024
A55: 6
B56: SUBTOTAL — Other Energy
A58: ✦ SCOPE 2 TOTAL — LOCATION-BASED (tCO₂e) ✦
A59: ✦ SCOPE 2 TOTAL — MARKET-BASED (tCO₂e) [USE THIS FOR REPORTING] ✦ | I59: 0
A60: *(Renewable Energy Certificates) ; PPAs (Power Purchase Agreements) ; GOs (Guarantees of Origin, in Europe) ; I‑RECs (International RECs, global markets)
H61: Market | I61: Location
G62: 2023 | H62: =SUM(H50:H51) -> 1267091.2 | I62: =SUM(H36:H40) -> 1070600 | J62: =SUM(H62:I62) -> 2337691.2
G63: 2024 | H63: =SUM(H53:H54) -> 1506680.6 | I63: =SUM(H41:H45) -> 802950 | J63: =SUM(H63:I63) -> 2309630.6

Sheet Scope 3 S
A1: SCOPE 3 — VALUE CHAIN EMISSIONS | Cover at least 3 of the 15 categories most material to your industry
A2: Scope 3 typically represents 70–90% of total footprint. Use spend-based method where activity data is unavailable.
A4: SCOPE 3 CATEGORY OVERVIEW — Mark which categories are material for your company (✓ = Include, N/A = Not applicable)
B5: Cat # | C5: Category Name | D5: Stream | E5: Typical Method | F5: Material for your industry? | G5: Estimated % of S3 (Reasonable Industry averages) | H5: Notes: It is NOT an official GHG Protocol requirement
B6: 1 | C6: Purchased Goods & Services | D6: Upstream | E6: Spend-based or supplier-specific | F6: High for manufacturing/retail | G6: ~40% | H6: Often true, for manufacturing, retail, food, apparel, pharma — this is usually the largest Scope 3 category.
B7: 2 | C7: Capital Goods | D7: Upstream | E7: Spend-based | F7: High for capital-intensive industries | G7: ~5% | H7: Reasonable. Higher for construction, tech hardware, automotive; lower for services.
B8: 3 | C8: Fuel & Energy-Related Activities | D8: Upstream | E8: Activity-based | F8: ALL companies | G8: ~3% | H8: Typical. Usually small unless energy use is huge.
B9: 4 | C9: Upstream Transportation & Distribution | D9: Upstream | E9: Spend/distance-based | F9: Retail, manufacturing | G9: ~5% | H9: Reasonable. Retail, manufacturing, e‑commerce often fall in this range.
B10: 5 | C10: Waste Generated in Operations | D10: Upstream | E10: Activity-based | F10: Manufacturing, food & beverage | G10: ~1% | H10: Typical. Only large for food, agriculture, chemicals.
B11: 6 | C11: Business Travel | D11: Upstream | E11: Activity-based (km × EF) | F11: Services, consulting, financial | G11: ~1% | H11: Typical. Higher for consulting, finance, tech
B12: 7 | C12: Employee Commuting | D12: Upstream | E12: Survey-based | F12: Office-heavy companies | G12: ~1% | H12: Typical. Office-heavy companies
B13: 8 | C13: Upstream Leased Assets | D13: Upstream | E13: Asset-specific | F13: Companies with leased fleet/space | G13: ~2% | H13: Depends. Only relevant if you lease equipment or space.
B14: 9 | C14: Downstream Transportation | D14: Downstream | E14: Spend/distance-based | F14: Consumer goods, e-commerce | G14: ~5% | H14: Typical. Big for consumer goods and e‑commerce.
B15: 10 | C15: Processing of Sold Products | D15: Downstream | E15: Industry-specific | F15: Chemicals, materials suppliers | G15: ~3% | H15: Industry-specific. Chemicals, materials, components.
B16: 11 | C16: Use of Sold Products | D16: Downstream | E16: Activity-based (product use) | F16: High for electronics, vehicles, appliances | G16: ~25% | H16: Very common. Electronics, appliances, vehicles — often the largest category.
... B20: 15 | C20: Investments | D20: Downstream | E20: PCAF / portfolio-based | F20: Financial institutions, banks | G20: ~30% | H20: True for finance. Banks, PE, VC — this is usually the dominant category.
A23: CATEGORY 1 — PURCHASED GOODS & SERVICES (Spend-Based Method)
A24: # | B24: Supplier / Spend Category | C24: Annual Spend (USD) | D24: EEIO Factor (kgCO₂e per $)a | E24: Typical USEEIP Range b | F24: EEIO Source | G24: Spend in $000s | H24: Notes | J24: tCO₂e | K24: Data Confidence | L24: Notes
A25: 1 | B25: Raw Materials / Commodities | C25: 0 | D25: 0.35 | E25: 0.2 - 1.20 | F25: US EPA USEEIO v2.0 | H25: Plastics material & resin manufacturing; Steel mills; Paper mills | J25: =C25*D25/1000 -> 0 | K25: Medium | L25: [Enter data source / assumption]
A26: 2 | B26: Manufactured Components / Parts | C26: 0 | D26: 0.52 | E26: 0.4 - 1.50 | F26: US EPA USEEIO v2.0 | H26: Semiconductor manufacturing; Electronic component manufacturing; Fabricated metal products | J26: =C26*D26/1000 -> 0 | K26: Medium | L26: [Enter data source / assumption]
A27: 3 | B27: Packaging Materials | C27: 0 | D27: 0.63 | E27: 0.5 -1.00 | F27: US EPA USEEIO v2.0 | H27: Paperboard container manufacturing; Plastics packaging manufacturing | J27: =C27*D27/1000 -> 0 | K27: Medium | L27: [Enter data source / assumption]
A28: 4 | B28: Information Technology / Hardware | C28: 0 | D28: 0.85 | E28: 0.7 - 1.40 | F28: US EPA USEEIO v2.0 | H28: Computer manufacturing; Electronic equipment manufacturing | J28: =C28*D28/1000 -> 0 | K28: Medium | L28: [Enter data source / assumption]
A29: 5 | B29: Professional / Business Services | C29: 0 | D29: 0.12 | E29: 0.05 - 0.20 | F29: US EPA USEEIO v2.0 | H29: Management consulting services; Legal services; Accounting services | J29: =C29*D29/1000 -> 0 | K29: Medium | L29: [Enter data source / assumption]
A30: 6 | B30: Food & Beverage (for operations) | C30: 0 | D30: 0.95 | E30: 0.8 -1.60 | F30: US EPA USEEIO v2.0 | H30: Food manufacturing; Beverage manufacturing | J30: =C30*D30/1000 -> 0 | K30: Medium | L30: [Enter data source / assumption]
A31: 7 | B31: Construction / Building Materials | C31: 0 | D31: 0.42 | E31: 0.3 - 0 70 | F31: US EPA USEEIO v2.0 | H31: Cement manufacturing; Ready‑mix concrete; Construction services | J31: =C31*D31/1000 -> 0 | K31: Medium | L31: [Enter data source / assumption]
A32: 8 | B32: Other goods/services (specify) | C32: 0 | D32: 0.25 | E32: varies | J32: =C32*D32/1000 -> 0 | K32: Medium | L32: [Enter data source / assumption]
B33: SUBTOTAL — Category 1 | C33: =SUM(C25:C32) -> 0
B34: a EEIO = Environmentally Extended Input–Output. How many kg of CO₂e are emitted per dollar spent on a product or service.
B35: b Typical range of emission intensities (kgCO₂e per dollar spent) found across sectors in the USEEIO model — the U.S. Environmentally Extended Input–Output model published by the EPA.
A36: CATEGORY 3 — FUEL & ENERGY RELATED ACTIVITIES (Upstream Emissions from Purchased Energy)
A37: # | B37: Activity | C37: Scope 2 Electricity (MWh) | D37: T&D Loss Factor c (% of consumption) | E37: Well-to-Tank EF d (kgCO₂e/MWh) DEFRA | F37: Step 1 — Calculate T&D loss electricity | G37: Step 2 — Multiply by the DEFRA upstream electricity factor | H37: Step 3 — Convert to tonnes | I37: Emission Factor (EPA e grid) for subregion e.g. Chicago | J37: tCO₂e | K37: (tCO₂e for Category 3) tCO2e | L37: Confidence | M37: Notes
A38: 1 | B38: T&D Losses — Purchased Electricity | C38: 0 | D38: 0.042 | E38: 26.5 | F38: =C38*D38 -> 0 | G38: =F38*E38 -> 0 | H38: =G38/1000 -> 0 | I38: 416 | J38: =C38*D38*E38/1000 -> 0 | K38: =I38*F38/1000 -> 0 | M38: [Enter source]
A39: 2 | B39: Well-to-Tank — Natural Gas (for Scope 1) | C39: 0 | D39: 0 | E39: 15.4 | F39: =C39*D39 -> 0 | G39: =F39*E39 -> 0 | H39: =G39/1000 -> 0 | J39: =C39*E39/1000 -> 0 | M39: [Enter source]
A40: 3 | B40: Well-to-Tank — Diesel Fuel (for Scope 1) | C40: 0 | D40: 0 | E40: 16.7 | F40: =C40*D40 -> 0 | G40: =F40*E40 -> 0 | H40: =G40/1000 -> 0 | J40: =C40*E40/1000 -> 0 | M40: [Enter source]
A41: 4 | B41: Well-to-Tank — Gasoline (for Scope 1) | C41: 0 | D41: 0 | E41: 14.8 | F41: =C41*D41 -> 0 | G41: =F41*E41 -> 0 | H41: =G41/1000 -> 0 | J41: =C41*E41/1000 -> 0 | M41: [Enter source]
B42: SUBTOTAL — Category 3 | I42: * it was provided
B43: UK DEFRA/BEIS. EPA does not publish Well‑to‑Tank (WTT) emission factors for electricity or fuels.
B44: c T&D = Transmission & Distribution.
B45: d Upstream emissions from producing, processing, and delivering the fuel before it is used.
A46: CATEGORY 6 — BUSINESS TRAVEL (Activity-Based: Distance × Emission Factor)
A47: # | B47: Travel Mode | C47: Distance Travelled | D47: Unit | E47: Class (Economy/Bus) | F47: EF (kgCO₂e/km or mile) | G47: EF Source | J47: tCO₂e | K47: Confidence | L47: Notes
A48: 1 | B48: Air Travel — Short Haul (<3hrs) Economy | C48: 0 | D48: km | E48: Economy | F48: 0.255 | G48: DEFRA 2023 | J48: =C48*F48/1000 -> 0 | L48: [Enter data source]
A49: 2 | B49: Air Travel — Long Haul (>3hrs) Economy | C49: 0 | D49: km | E49: Economy | F49: 0.195 | G49: DEFRA 2023 | J49: =C49*F49/1000 -> 0 | L49: [Enter data source]
A50: 3 | B50: Air Travel — Long Haul Business Class | C50: 0 | D50: km | E50: Business | F50: 0.429 | G50: DEFRA 2023 | J50: =C50*F50/1000 -> 0 | L50: [Enter data source]
A51: 4 | B51: Rail Travel | C51: 0 | D51: km | E51: National rail passenger | F51: 0.035 | G51: DEFRA 2023 | J51: =C51*F51/1000 -> 0 | L51: [Enter data source]
A52: 5 | B52: Hotel Stays | C52: 0 | D52: nights | E52: Hotel stay per night | F52: 20.8 | G52: DEFRA 2023 | J52: =C52*F52/1000 -> 0 | L52: [Enter data source]
A53: 6 | B53: Rental Car | C53: 0 | D53: km | E53: Rental car (Generic) | F53: 0.168 | G53: DEFRA 2023 | J53: =C53*F53/1000 -> 0 | L53: [Enter data source]
B54: SUBTOTAL — Category 6
A56: ADDITIONAL CATEGORIES — Enter other material Scope 3 categories for your industry
A57: # | B57: Category Name & Number | C57: Description | D57: Method Used | E57: Quantity | F57: EF / Factor | I57: tCO₂e | J57: Confidence | K57: Notes
A58: 1 | B58: Scope 3 – Cat. 2: Capital Goods | C58: [Enter data] | D58: [Enter data] | E58: [Enter data] | F58: [Enter data] | G58: [Enter data] | H58: [Enter data] | J58: High | K58: [Enter data]
A59: 2 | B59: Scope 3 – Cat. 3: Fuel & Energy-Related | C59: [Enter data] | D59: [Enter data] | E59: [Enter data] | F59: [Enter data] | G59: [Enter data] | H59: [Enter data] | J59: High | K59: [Enter data]
B60: Scope 3 – Cat. 4: Upstream Transport & Distribution | C60: [Enter data] | D60: [Enter data] | E60: [Enter data] | F60: [Enter data] | G60: [Enter data] | H60: [Enter data] | J60: High
B61: Scope 3 – Cat. 5: Waste in Operations | C61: [Enter data] | D61: [Enter data] | E61: [Enter data] | F61: [Enter data] | G61: [Enter data] | H61: [Enter data] | J61: High
B62: Scope 3 – Cat. 7: Employee Commuting | C62: [Enter data] | D62: [Enter data] | E62: [Enter data] | F62: [Enter data] | G62: [Enter data] | H62: [Enter data] | J62: High
B63: Scope 3 – Cat. 9: Downstream Transport & Distribution | C63: [Enter data] | D63: [Enter data] | E63: [Enter data] | F63: [Enter data] | G63: [Enter data] | H63: [Enter data] | J63: High
B64: Scope 3 – Cat. 11: Use of Sold Products | C64: [Enter data] | D64: [Enter data] | E64: [Enter data] | F64: [Enter data] | G64: [Enter data] | H64: [Enter data] | J64: High
B65: Scope 3 – Cat. 12: End-of-Life Treatment | C65: [Enter data] | D65: [Enter data] | E65: [Enter data] | F65: [Enter data] | G65: [Enter data] | H65: [Enter data] | J65: High
B66: Scope 3 – Cat. 13: Downstream Leased Assets | C66: [Enter data] | D66: [Enter data] | E66: [Enter data] | F66: [Enter data] | G66: [Enter data] | H66: [Enter data] | J66: High
A67: 5 | B67: [Enter data] | C67: [Enter data] | D67: [Enter data] | E67: [Enter data] | F67: [Enter data] | G67: [Enter data] | H67: [Enter data] | I67: =IFERROR(IF(AND(ISNUMBER(E67),ISNUMBER(F67)),E67*F67/1000,0),0) -> 0 | J67: [Enter data] | K67: [Enter data]
B68: SUBTOTAL — Additional Categories | I68: =SUM(I58:I67) -> 0
A70: ✦ SCOPE 3 TOTAL (tCO₂e) ✦ | J70: =I68+J54+J42+J33 -> 0

Sheet Scope 3 W
A1: SCOPE 3 — VALUE CHAIN EMISSIONS | Cover at least 3 of the 15 categories most material to your industry
A2: Scope 3 typically represents 70–90% of total footprint. Use spend-based method where activity data is unavailable.
A4: SCOPE 3 CATEGORY OVERVIEW — Mark which categories are material for your company (✓ = Include, N/A = Not applicable)
B5: Cat # | C5: Category Name | D5: Stream | E5: Typical Method | F5: Material for your industry? | G5: Estimated % of S3 (Reasonable Industry averages) | H5: Notes: It is NOT an official GHG Protocol requirement
B6: 1 | C6: Purchased Goods & Services | D6: Upstream | E6: Spend-based or supplier-specific | F6: High for manufacturing/retail | G6: ~40% | H6: Often true, for manufacturing, retail, food, apparel, pharma — this is usually the largest Scope 3 category.
B7: 2 | C7: Capital Goods | D7: Upstream | E7: Spend-based | F7: High for capital-intensive industries | G7: ~5% | H7: Reasonable. Higher for construction, tech hardware, automotive; lower for services.
B8: 3 | C8: Fuel & Energy-Related Activities | D8: Upstream | E8: Activity-based | F8: ALL companies | G8: ~3% | H8: Typical. Usually small unless energy use is huge.
B9: 4 | C9: Upstream Transportation & Distribution | D9: Upstream | E9: Spend/distance-based | F9: Retail, manufacturing | G9: ~5% | H9: Reasonable. Retail, manufacturing, e‑commerce often fall in this range.
B10: 5 | C10: Waste Generated in Operations | D10: Upstream | E10: Activity-based | F10: Manufacturing, food & beverage | G10: ~1% | H10: Typical. Only large for food, agriculture, chemicals.
B11: 6 | C11: Business Travel | D11: Upstream | E11: Activity-based (km × EF) | F11: Services, consulting, financial | G11: ~1% | H11: Typical. Higher for consulting, finance, tech
B12: 7 | C12: Employee Commuting | D12: Upstream | E12: Survey-based | F12: Office-heavy companies | G12: ~1% | H12: Typical. Office-heavy companies
B13: 8 | C13: Upstream Leased Assets | D13: Upstream | E13: Asset-specific | F13: Companies with leased fleet/space | G13: ~2% | H13: Depends. Only relevant if you lease equipment or space.
B14: 9 | C14: Downstream Transportation | D14: Downstream | E14: Spend/distance-based | F14: Consumer goods, e-commerce | G14: ~5% | H14: Typical. Big for consumer goods and e‑commerce.
B15: 10 | C15: Processing of Sold Products | D15: Downstream | E15: Industry-specific | F15: Chemicals, materials suppliers | G15: ~3% | H15: Industry-specific. Chemicals, materials, components.
B16: 11 | C16: Use of Sold Products | D16: Downstream | E16: Activity-based (product use) | F16: High for electronics, vehicles, appliances | G16: ~25% | H16: Very common. Electronics, appliances, vehicles — often the largest category.
... B20: 15 | C20: Investments | D20: Downstream | E20: PCAF / portfolio-based | F20: Financial institutions, banks | G20: ~30% | H20: True for finance. Banks, PE, VC — this is usually the dominant category.
A23: CATEGORY 1 — PURCHASED GOODS & SERVICES (Spend-Based Method)
A24: # | B24: Supplier / Spend Category | C24: Annual Spend (USD) | D24: EEIO Factor (kgCO₂e per $)a | E24: Typical USEEIP Range b | F24: EEIO Source | G24: Spend in $000s | H24: Notes | J24: tCO₂e | K24: Data Confidence | L24: Notes
A25: 1 | B25: Raw Materials / Commodities | C25: 0 | D25: 0.35 | E25: 0.2 - 1.20 | F25: US EPA USEEIO v2.0 | H25: Plastics material & resin manufacturing; Steel mills; Paper mills | J25: =C25*D25/1000 -> 0 | K25: Medium | L25: [Enter data source / assumption]
A26: 2 | B26: Manufactured Components / Parts | C26: 0 | D26: 0.52 | E26: 0.4 - 1.50 | F26: US EPA USEEIO v2.0 | H26: Semiconductor manufacturing; Electronic component manufacturing; Fabricated metal products | J26: =C26*D26/1000 -> 0 | K26: Medium | L26: [Enter data source / assumption]
A27: 3 | B27: Packaging Materials | C27: 0 | D27: 0.63 | E27: 0.5 -1.00 | F27: US EPA USEEIO v2.0 | H27: Paperboard container manufacturing; Plastics packaging manufacturing | J27: =C27*D27/1000 -> 0 | K27: Medium | L27: [Enter data source / assumption]
A28: 4 | B28: Information Technology / Hardware | C28: 0 | D28: 0.85 | E28: 0.7 - 1.40 | F28: US EPA USEEIO v2.0 | H28: Computer manufacturing; Electronic equipment manufacturing | J28: =C28*D28/1000 -> 0 | K28: Medium | L28: [Enter data source / assumption]
A29: 5 | B29: Professional / Business Services | C29: 0 | D29: 0.12 | E29: 0.05 - 0.20 | F29: US EPA USEEIO v2.0 | H29: Management consulting services; Legal services; Accounting services | J29: =C29*D29/1000 -> 0 | K29: Medium | L29: [Enter data source / assumption]
A30: 6 | B30: Food & Beverage (for operations) | C30: 0 | D30: 0.95 | E30: 0.8 -1.60 | F30: US EPA USEEIO v2.0 | H30: Food manufacturing; Beverage manufacturing | J30: =C30*D30/1000 -> 0 | K30: Medium | L30: [Enter data source / assumption]
A31: 7 | B31: Construction / Building Materials | C31: 0 | D31: 0.42 | E31: 0.3 - 0 70 | F31: US EPA USEEIO v2.0 | H31: Cement manufacturing; Ready‑mix concrete; Construction services | J31: =C31*D31/1000 -> 0 | K31: Medium | L31: [Enter data source / assumption]
A32: 8 | B32: Other goods/services (specify) | C32: 0 | D32: 0.25 | E32: varies | J32: =C32*D32/1000 -> 0 | K32: Medium | L32: [Enter data source / assumption]
B33: SUBTOTAL — Category 1 | C33: =SUM(C25:C32) -> 0
B34: a EEIO = Environmentally Extended Input–Output. How many kg of CO₂e are emitted per dollar spent on a product or service.
B35: b Typical range of emission intensities (kgCO₂e per dollar spent) found across sectors in the USEEIO model — the U.S. Environmentally Extended Input–Output model published by the EPA.
A36: CATEGORY 3 — FUEL & ENERGY RELATED ACTIVITIES (Upstream Emissions from Purchased Energy)
A37: # | B37: Activity | C37: Scope 2 Electricity (MWh) | D37: T&D Loss Factor c (% of consumption) | E37: Well-to-Tank EF d (kgCO₂e/MWh) DEFRA | F37: Step 1 — Calculate T&D loss electricity | G37: Step 2 — Multiply by the DEFRA upstream electricity factor | H37: Step 3 — Convert to tonnes | I37: Emission Factor (EPA e grid) for subregion e.g. Chicago | J37: tCO₂e | K37: (tCO₂e for Category 3) tCO2e | L37: Confidence | M37: Notes
A38: 1 | B38: T&D Losses — Purchased Electricity | C38: 0 | D38: 0.042 | E38: 26.5 | F38: =C38*D38 -> 0 | G38: =F38*E38 -> 0 | H38: =G38/1000 -> 0 | I38: 416 | J38: =C38*D38*E38/1000 -> 0 | K38: =I38*F38/1000 -> 0 | M38: [Enter source]
A39: 2 | B39: Well-to-Tank — Natural Gas (for Scope 1) | C39: 0 | D39: 0 | E39: 15.4 | F39: =C39*D39 -> 0 | G39: =F39*E39 -> 0 | H39: =G39/1000 -> 0 | J39: =C39*E39/1000 -> 0 | M39: [Enter source]
A40: 3 | B40: Well-to-Tank — Diesel Fuel (for Scope 1) | C40: 0 | D40: 0 | E40: 16.7 | F40: =C40*D40 -> 0 | G40: =F40*E40 -> 0 | H40: =G40/1000 -> 0 | J40: =C40*E40/1000 -> 0 | M40: [Enter source]
A41: 4 | B41: Well-to-Tank — Gasoline (for Scope 1) | C41: 0 | D41: 0 | E41: 14.8 | F41: =C41*D41 -> 0 | G41: =F41*E41 -> 0 | H41: =G41/1000 -> 0 | J41: =C41*E41/1000 -> 0 | M41: [Enter source]
B42: SUBTOTAL — Category 3 | I42: * it was provided
B43: UK DEFRA/BEIS. EPA does not publish Well‑to‑Tank (WTT) emission factors for electricity or fuels.
B44: c T&D = Transmission & Distribution.
B45: d Upstream emissions from producing, processing, and delivering the fuel before it is used.
A46: CATEGORY 6 — BUSINESS TRAVEL (Activity-Based: Distance × Emission Factor)
A47: # | B47: Travel Mode | C47: Distance Travelled | D47: Unit | E47: Class (Economy/Bus) | F47: EF (kgCO₂e/km or mile) | G47: EF Source | J47: tCO₂e | K47: Confidence | L47: Notes
A48: 1 | B48: Air Travel — Short Haul (<3hrs) Economy | C48: 0 | D48: km | E48: Economy | F48: 0.255 | G48: DEFRA 2023 | J48: =C48*F48/1000 -> 0 | L48: [Enter data source]
A49: 2 | B49: Air Travel — Long Haul (>3hrs) Economy | C49: 0 | D49: km | E49: Economy | F49: 0.195 | G49: DEFRA 2023 | J49: =C49*F49/1000 -> 0 | L49: [Enter data source]
A50: 3 | B50: Air Travel — Long Haul Business Class | C50: 0 | D50: km | E50: Business | F50: 0.429 | G50: DEFRA 2023 | J50: =C50*F50/1000 -> 0 | L50: [Enter data source]
A51: 4 | B51: Rail Travel | C51: 0 | D51: km | E51: National rail passenger | F51: 0.035 | G51: DEFRA 2023 | J51: =C51*F51/1000 -> 0 | L51: [Enter data source]
A52: 5 | B52: Hotel Stays | C52: 0 | D52: nights | E52: Hotel stay per night | F52: 20.8 | G52: DEFRA 2023 | J52: =C52*F52/1000 -> 0 | L52: [Enter data source]
A53: 6 | B53: Rental Car | C53: 0 | D53: km | E53: Rental car (Generic) | F53: 0.168 | G53: DEFRA 2023 | J53: =C53*F53/1000 -> 0 | L53: [Enter data source]
B54: SUBTOTAL — Category 6
A56: ADDITIONAL CATEGORIES — Enter other material Scope 3 categories for your industry
A57: # | B57: Category Name & Number | C57: Description | D57: Method Used | E57: Quantity | F57: EF / Factor | I57: tCO₂e | J57: Confidence | K57: Notes
A58: 1 | B58: Scope 3 – Cat. 2: Capital Goods | C58: [Enter data] | D58: [Enter data] | E58: [Enter data] | F58: [Enter data] | G58: [Enter data] | H58: [Enter data] | J58: High | K58: [Enter data]
A59: 2 | B59: Scope 3 – Cat. 3: Fuel & Energy-Related | C59: [Enter data] | D59: [Enter data] | E59: [Enter data] | F59: [Enter data] | G59: [Enter data] | H59: [Enter data] | J59: High | K59: [Enter data]
B60: Scope 3 – Cat. 4: Upstream Transport & Distribution | C60: [Enter data] | D60: [Enter data] | E60: [Enter data] | F60: [Enter data] | G60: [Enter data] | H60: [Enter data] | J60: High
B61: Scope 3 – Cat. 5: Waste in Operations | C61: [Enter data] | D61: [Enter data] | E61: [Enter data] | F61: [Enter data] | G61: [Enter data] | H61: [Enter data] | J61: High
B62: Scope 3 – Cat. 7: Employee Commuting | C62: [Enter data] | D62: [Enter data] | E62: [Enter data] | F62: [Enter data] | G62: [Enter data] | H62: [Enter data] | J62: High
B63: Scope 3 – Cat. 9: Downstream Transport & Distribution | C63: [Enter data] | D63: [Enter data] | E63: [Enter data] | F63: [Enter data] | G63: [Enter data] | H63: [Enter data] | J63: High
B64: Scope 3 – Cat. 11: Use of Sold Products | C64: [Enter data] | D64: [Enter data] | E64: [Enter data] | F64: [Enter data] | G64: [Enter data] | H64: [Enter data] | J64: High
B65: Scope 3 – Cat. 12: End-of-Life Treatment | C65: [Enter data] | D65: [Enter data] | E65: [Enter data] | F65: [Enter data] | G65: [Enter data] | H65: [Enter data] | J65: High
B66: Scope 3 – Cat. 13: Downstream Leased Assets | C66: [Enter data] | D66: [Enter data] | E66: [Enter data] | F66: [Enter data] | G66: [Enter data] | H66: [Enter data] | J66: High
A67: 5 | B67: [Enter data] | C67: [Enter data] | D67: [Enter data] | E67: [Enter data] | F67: [Enter data] | G67: [Enter data] | H67: [Enter data] | I67: =IFERROR(IF(AND(ISNUMBER(E67),ISNUMBER(F67)),E67*F67/1000,0),0) -> 0 | J67: [Enter data] | K67: [Enter data]
B68: SUBTOTAL — Additional Categories | I68: =SUM(I58:I67) -> 0
A70: ✦ SCOPE 3 TOTAL (tCO₂e) ✦ | J70: =I68+J54+J42+J33 -> 0

Sheet Summary & Intensity
B1: CARBON FOOTPRINT SUMMARY & INTENSITY RATIOS
B2: All values pull automatically from Scope 1, 2, and 3 sheets. Review after completing data entry.
A4: SECTION 1 — SCOPE TOTALS (tCO₂e)
A5: Business | B5: Scope | C5: Description | D5: tCO₂e | E5: % of Total (S1+S2+S3) | F5: % of Total (S1+S2 only) | G5: Compared to Prior Year | H5: Target | I5: Notes
A6: WR 2019 | B6: Scope 1 | C6: Direct Emissions (combustion, fleet, fugitive)
A7: WR 2019 | B7: Scope 2 (Market-Based) | C7: Purchased Energy — Market-Based [PRIMARY]
A8: WR 2019 | B8: Scope 2 (Location-Based) | C8: Purchased Energy — Location-Based [SECONDARY]
A9: WR 2019 | B9: Scope 3 | C9: Value Chain Emissions (all categories)
A10: SK 2019 | B10: Scope 1 | C10: Direct Emissions (combustion, fleet, fugitive)
A11: SK 2019 | B11: Scope 2 (Market-Based) | C11: Purchased Energy — Market-Based [PRIMARY]
A12: SK 2019 | B12: Scope 2 (Location-Based) | C12: Purchased Energy — Location-Based [SECONDARY]
A13: SK 2019 | B13: Scope 3 | C13: Value Chain Emissions (all categories)
A14: WR 2020 | B14: Scope 1 | C14: Direct Emissions (combustion, fleet, fugitive)
A15: WR 2020 | B15: Scope 2 (Market-Based) | C15: Purchased Energy — Market-Based [PRIMARY]
A16: WR 2020 | B16: Scope 2 (Location-Based) | C16: Purchased Energy — Location-Based [SECONDARY]
A17: WR 2020 | B17: Scope 3 | C17: Value Chain Emissions (all categories)
... A37: SK 2022 | B37: Scope 3 | C37: Value Chain Emissions (all categories)
A38: WR 2023 | B38: Scope 1 | C38: Direct Emissions (combustion, fleet, fugitive) | D38: =SUM('Scope 1 W'!K22:K24)+'Scope 1 W'!K25 -> 21851880 | E38: =D38/SUM($D$38:$D$41) -> 0.9029992 | F38: =D38/SUM($D$38:$D$40) -> 0.90335954
A39: WR 2023 | B39: Scope 2 (Market-Based) | C39: Purchased Energy — Market-Based [PRIMARY] | D39: ='Scope 2 W'!H62 -> 1267091.2 | E39: =D39/SUM($D$38:$D$41) -> 0.05236082 | F39: =D39/SUM($D$38:$D$40) -> 0.052381715
A40: WR 2023 | B40: Scope 2 (Location-Based) | C40: Purchased Energy — Location-Based [SECONDARY] | D40: ='Scope 2 W'!I62 -> 1070600 | E40: =D40/SUM($D$38:$D$41) -> 0.044241088 | F40: =D40/SUM($D$38:$D$40) -> 0.044258742
A41: WR 2023 | B41: Scope 3 | C41: Value Chain Emissions (all categories) | D41: 9653 | E41: =D41/SUM($D$38:$D$41) -> 0.00039889708
A42: SK 2023 | B42: Scope 1 | C42: Direct Emissions (combustion, fleet, fugitive) | D42: =2415000+4000000 -> 6415000 | E42: =D42/SUM($D$42:$D$45) -> 0.93214182 | F42: =D42/SUM($D$42:$D$44) -> 0.93214182
A43: SK 2023 | B43: Scope 2 (Market-Based) | C43: Purchased Energy — Market-Based [PRIMARY] | D43: 0 | E43: =D43/SUM($D$42:$D$45) -> 0 | F43: =D43/SUM($D$42:$D$44) -> 0
A44: SK 2023 | B44: Scope 2 (Location-Based) | C44: Purchased Energy — Location-Based [SECONDARY] | D44: 467000 | E44: =D44/SUM($D$42:$D$45) -> 0.067858181 | F44: =D44/SUM($D$42:$D$44) -> 0.067858181
A45: SK 2023 | B45: Scope 3 | C45: Value Chain Emissions (all categories) | D45: 0 | E45: =D45/SUM($D$42:$D$45) -> 0
A46: WR 2024 | B46: Scope 1 | C46: Direct Emissions (combustion, fleet, fugitive) | D46: =SUM('Scope 1 W'!K26:K28)+'Scope 1 W'!K29 -> 16445258 | E46: =D46/SUM($D$46:$D$49) -> 0.87641012 | F46: =D46/SUM($D$46:$D$48) -> 0.87685181
A47: WR 2024 | B47: Scope 2 (Market-Based) | C47: Purchased Energy — Market-Based [PRIMARY] | D47: ='Scope 2 W'!H63 -> 1506680.6 | E47: =D47/SUM($D$46:$D$49) -> 0.080294886 | F47: =D47/SUM($D$46:$D$48) -> 0.080335353
A48: WR 2024 | B48: Scope 2 (Location-Based) | C48: Purchased Energy — Location-Based [SECONDARY] | D48: ='Scope 2 W'!I63 -> 802950 | E48: =D48/SUM($D$46:$D$49) -> 0.042791273 | F48: =D48/SUM($D$46:$D$48) -> 0.042812839
A49: WR 2024 | B49: Scope 3 | C49: Value Chain Emissions (all categories) | D49: 9452 | E49: =D49/SUM($D$46:$D$49) -> 0.00050372142
A50: SK 2024 | B50: Scope 1 | C50: Direct Emissions (combustion, fleet, fugitive) | D50: =2473000+3989000 -> 6462000 | E50: =D50/SUM($D$50:$D$53) -> 0.93098977 | F50: =D50/SUM($D$50:$D$52) -> 0.93098977
A51: SK 2024 | B51: Scope 2 (Market-Based) | C51: Purchased Energy — Market-Based [PRIMARY] | D51: 0 | E51: =D51/SUM($D$50:$D$53) -> 0 | F51: =D51/SUM($D$50:$D$52) -> 0
A52: SK 2024 | B52: Scope 2 (Location-Based) | C52: Purchased Energy — Location-Based [SECONDARY] | D52: 479000 | E52: =D52/SUM($D$50:$D$53) -> 0.069010229 | F52: =D52/SUM($D$50:$D$52) -> 0.069010229
A53: SK 2024 | B53: Scope 3 | C53: Value Chain Emissions (all categories) | D53: 0 | E53: =D53/SUM($D$50:$D$53) -> 0
B54: Total S1 +S2 +S3 Westrock 2023 | D54: =SUM(D38:D41) -> 24199224
B55: Total S1 +S2 +S3 Westrock 2024 | D55: =SUM(D46:D49) -> 18764340
B56: Total S1 +S2 +S3 Smurfit Kappa 2023 | D56: =SUM(D42:D45) -> 6882000
B57: Total S1 +S2 +S3 Smurfit Kappa 2024 | D57: =SUM(D50:D53) -> 6941000
B59: 1
B60: Intensity Metric | C60: Formula | D60: Current Year (tCO₂e / unit) | E60: Prior Year (tCO₂e / unit) | F60: Change (%) | G60: Industry Benchmark | H60: vs. Benchmark | I60: Unit
B61: Carbon Intensity — Revenue | C61: tCO₂e per $M revenue | D61: =IFERROR(D54/Assumptions!B15,0) -> 0 | E61: =G54/211915 -> 0 | F61: =IFERROR((D61-E61)/ABS(E61),0) -> 0 | G61: [Industry benchmark] | H61: =IFERROR((D61-G61)/ABS(G61),0) -> 0 | I61: tCO₂e / $M revenue
B62: Carbon Intensity — Employee | C62: tCO₂e per FTE employee | D62: =IFERROR(D54/Assumptions!B16,0) -> 0 | E62: =G54/221000 -> 0 | F62: =IFERROR((D62-E62)/ABS(E62),0) -> 0 | G62: [Industry benchmark] | H62: =IFERROR((D62-G62)/ABS(G62),0) -> 0 | I62: tCO₂e / employee
B63: Carbon Intensity — Production | C63: tCO₂e per unit of output (N/A) | D63: =IFERROR(D54/Assumptions!B17,0) -> 0 | E63: 0 | F63: =IFERROR((D63-E63)/ABS(E63),0) -> 0 | G63: [Industry benchmark] | H63: =IFERROR((D63-G63)/ABS(G63),0) -> 0 | I63: tCO₂e / unit
B64: Scope 1 Intensity — Revenue | C64: Scope 1 tCO₂e per $M revenue | D64: =IFERROR(#REF!/Assumptions!B15,0) -> 0 | E64: ='Trend Analysis'!C7/211915 -> 0 | F64: =IFERROR((D64-E64)/ABS(E64),0) -> 0 | G64: [Industry benchmark] | H64: =IFERROR((D64-G64)/ABS(G64),0) -> 0 | I64: tCO₂e / $M revenue
B65: Scope 2 MB Intensity — Revenue | C65: Scope 2 tCO₂e per $M revenue | D65: =IFERROR('Scope 2 W'!I59/Assumptions!B15,0) -> 0 | E65: ='Reduction Trajectory'!F19/211915 -> 0 | F65: =IFERROR((D65-E65)/ABS(E65),0) -> 0 | G65: [Industry benchmark] | H65: =IFERROR((D65-G65)/ABS(G65),0) -> 0 | I65: tCO₂e / $M revenue
B66: Scope 3 Intensity — Revenue | C66: Scope 3 tCO₂e per $M revenue | D66: =IFERROR('Scope 3 W'!J70/Assumptions!B15,0) -> 0 | E66: ='Reduction Trajectory'!F21/211915 -> 0 | F66: =IFERROR((D66-E66)/ABS(E66),0) -> 0 | G66: [Industry benchmark] | H66: =IFERROR((D66-G66)/ABS(G66),0) -> 0 | I66: tCO₂e / $M revenue
B67: % Renewable Energy | C67: RECs as % of total electricity | D67: ='Scope 2 W'!F46/'Scope 2 W'!C46 -> #DIV/0! | E67: =23567502/24007868 -> 0.98165743 | F67: =IFERROR((D67-E67)/ABS(E67),0) -> 0 | G67: [Industry benchmark] | H67: =IFERROR((D67-G67)/ABS(G67),0) -> 0 | I67: %
B69: SECTION 3 — SCOPE BREAKDOWN (% of Total S1+S2+S3)
B70: Scope | C70: tCO₂e | D70: % Share | E70: GHG Protocol Guidance | F70: Best Practice Target
B71: Scope 1 | D71: =IFERROR(C71/C74,0) -> 0 | E71: Reduce through fuel switching & efficiency
B72: Scope 2 (Market-Based) | D72: =IFERROR(C72/C74,0) -> 0 | E72: Reduce through RECs, PPAs, on-site renewables
B73: Scope 3 | D73: =IFERROR(C73/C74,0) -> 0 | E73: Reduce through supply chain engagement & product design
B74: TOTAL | C74: =C71+C72+C73 -> 0 | D74: 100%

Sheet Trend Analysis
A1: EMISSIONS TREND ANALYSIS — 3-Year Historical Data & Chart
A2: Enter prior years manually. Current year pulls from Scope sheets automatically. Chart updates automatically.
A4: ABSOLUTE EMISSIONS TREND (tCO₂e) — Enter prior years | Current year auto-calculates
A5: Metric | B5: Year -2 (oldest) | C5: Year -1 | D5: Current Year (auto) | E5: YoY Change (yr-2 to yr-1) | F5: YoY Change (yr-1 to curr) | G5: 3-Year Cumulative Change | H5: Notes / Targets
A6: Reporting Year | B6: 2022 | C6: 2023 | D6: 2024
A7: Scope 1 Total (tCO₂e) | B7: ='Reduction Trajectory'!E17 -> 0 | C7: ='Reduction Trajectory'!F17 -> 0 | D7: ='Scope 1 W'!K53 -> 38297138 | E7: =IFERROR((C7-B7)/ABS(B7),0) -> 0 | F7: =IFERROR((D7-C7)/ABS(C7),0) -> 0 | G7: =IFERROR((D7-B7)/ABS(B7),0) -> 0 | H7: [Target or benchmark]
A8: Scope 2 Location-Based (tCO₂e) | B8: ='Reduction Trajectory'!E18 -> 0 | C8: ='Reduction Trajectory'!F18 -> 0 | D8: ='Scope 2 W'!H58 -> 0 | E8: =IFERROR((C8-B8)/ABS(B8),0) -> 0 | F8: =IFERROR((D8-C8)/ABS(C8),0) -> 0 | G8: =IFERROR((D8-B8)/ABS(B8),0) -> 0 | H8: [Target or benchmark]
A9: Scope 2 Market-Based (tCO₂e) | B9: ='Reduction Trajectory'!E19 -> 0 | C9: ='Reduction Trajectory'!F19 -> 0 | D9: ='Scope 2 W'!I59 -> 0 | E9: =IFERROR((C9-B9)/ABS(B9),0) -> 0 | F9: =IFERROR((D9-C9)/ABS(C9),0) -> 0 | G9: =IFERROR((D9-B9)/ABS(B9),0) -> 0 | H9: [Target or benchmark]
A10: Scope 3 Total (tCO₂e) | B10: ='Reduction Trajectory'!E21 -> 0 | C10: ='Reduction Trajectory'!F21 -> 0 | D10: ='Scope 3 W'!J70 -> 0 | E10: =IFERROR((C10-B10)/ABS(B10),0) -> 0 | F10: =IFERROR((D10-C10)/ABS(C10),0) -> 0 | G10: =IFERROR((D10-B10)/ABS(B10),0) -> 0 | H10: [Target or benchmark]
A11: TOTAL (S1+S2MB+S3) (tCO₂e) | B11: ='Reduction Trajectory'!E22 -> 16343000 | C11: ='Reduction Trajectory'!F22 -> 16935000 | D11: ='Scope 1 W'!K53+'Scope 2 W'!I59+'Scope 3 W'!J70 -> 38297138 | E11: =IFERROR((C11-B11)/ABS(B11),0) -> 0.03622346 | F11: =IFERROR((D11-C11)/ABS(C11),0) -> 1.2614194 | G11: =IFERROR((D11-B11)/ABS(B11),0) -> 1.3433358 | H11: [Target or benchmark]
A12: Carbon Intensity — Revenue (tCO₂e/$M) | B12: =B11/Assumptions!B35 -> 82.428002 | C12: =C11/Assumptions!B34 -> 79.889612 | D12: =IFERROR((#REF!+'Scope 2 W'!I59+'Scope 3 W'!J70)/Assumptions!B15,0) -> 0 | E12: =IFERROR((C12-B12)/ABS(B12),0) -> -0.030795239 | F12: =IFERROR((D12-C12)/ABS(C12),0) -> -1 | G12: =IFERROR((D12-B12)/ABS(B12),0) -> -1 | H12: [Target or benchmark]
A13: Carbon Intensity — Employee (tCO₂e/FTE) | B13: =B11/Assumptions!C35 -> 73.950226 | C13: =C11/Assumptions!C34 -> 76.628959 | D13: =IFERROR((#REF!+'Scope 2 W'!I59+'Scope 3 W'!J70)/Assumptions!B16,0) -> 0 | E13: =IFERROR((C13-B13)/ABS(B13),0) -> 0.03622346 | F13: =IFERROR((D13-C13)/ABS(C13),0) -> -1 | G13: =IFERROR((D13-B13)/ABS(B13),0) -> -1 | H13: [Target or benchmark]
A14: Renewable Energy % of Electricity | B14: 0 | C14: 0 | D14: =IFERROR(SUM('Scope 2 W'!F36:F40)/SUM('Scope 2 W'!C36:C40),0) -> 0 | E14: =IFERROR((C14-B14)/ABS(B14),0) -> 0 | F14: =IFERROR((D14-C14)/ABS(C14),0) -> 0 | G14: =IFERROR((D14-B14)/ABS(B14),0) -> 0 | H14: [Target or benchmark]
A16: REDUCTION TARGETS — Enter company-stated targets for chart overlay
A17: Target | B17: Target Year | C17: Baseline Year | D17: Baseline Value (tCO₂e) | E17: % Reduction Required | F17: Target Value (tCO₂e) | G17: Annual reductions | H17: Target Type | I17: Source
A18: Socpe 1 and 2 - 27.5% Reduction | B18: 2030 | C18: 2019 | D18: =6411167+1863185+2968004 -> 11242356 | E18: 0.275 | F18: =D18*(1-E18) -> 8150708.1 | G18: =(D18-F18)/(B18-C18) -> 281058.9 | H18: Target scope 1+2 | I18: Sustainability Report 2023
A19: Scope 3 Reduction Target | B19: 2030 | C19: 2019 | D19: 11399031 | E19: 0.275 | F19: =D19*(1-E19) -> 8264297.5 | G19: =(D19-F19)/(B19-C19) -> 284975.78 | H19: Target scope 3 | I19: Sustainability Report 2023

Sheet Reduction Trajectory
B2: Emission Trajectory Chart
B3: Enter your data in the yellow input cells below · The chart updates automatically · GHG Protocol Framework
B5: 📥 INPUT TABLE — Type your values in the YELLOW cells (tCO₂e or MtCO₂e — be consistent)
B6: 🟡 Yellow = enter your data | E6: 🔵 Blue = auto-calculated formula | H6: Growth assumed | I6: CAGR | J6: Report based info previous year
B7: Category / Year → | C7: 2024 | D7: 2025 | E7: 2026 | F7: 2027 | G7: 2028 | H7: 2029 | I7: 2030
B8: Business as usual | C8: =C9 -> 11242356 | D8: =H22 -> 16456070 | E8: =I22 -> 17422778 | F8: =J22 -> 18446275 | G8: =K22 -> 19529898 | H8: =L22 -> 20677178 | I8: =M22 -> 21891855
B9: ='Trend Analysis'!A18 -> Socpe 1 and 2 - 27.5% Reduction | C9: ='Trend Analysis'!D18 -> 11242356 | D9: =C9-'Trend Analysis'!G18 -> 10961297 | E9: =D9-'Trend Analysis'!G18 -> 10680238 | F9: =E9-'Trend Analysis'!G18 -> 10399179 | G9: =F9-'Trend Analysis'!G18 -> 10118120 | H9: =G9-'Trend Analysis'!G18 -> 9837061.5 | I9: =H9-'Trend Analysis'!G18 -> 9556002.6
B10: ='Trend Analysis'!#REF! -> #REF! | C10: ='Trend Analysis'!#REF! -> #REF! | D10: =C10-'Trend Analysis'!#REF! -> #REF! | E10: =D10-'Trend Analysis'!#REF! -> #REF! | F10: =E10-'Trend Analysis'!#REF! -> #REF! | G10: =F10-'Trend Analysis'!#REF! -> #REF! | H10: =G10-'Trend Analysis'!#REF! -> #REF! | I10: =H10-'Trend Analysis'!#REF! -> #REF!
B11: ='Trend Analysis'!A19 -> Scope 3 Reduction Target | C11: ='Trend Analysis'!D19 -> 11399031 | D11: =C11-'Trend Analysis'!G19 -> 11114055 | E11: =D11-'Trend Analysis'!G19 -> 10829079 | F11: =E11-'Trend Analysis'!G19 -> 10544104 | G11: =F11-'Trend Analysis'!G19 -> 10259128 | H11: =G11-'Trend Analysis'!G19 -> 9974152.1 | I11: =H11-'Trend Analysis'!G19 -> 9689176.3
B15: 📊 SCOPE BREAKDOWN INPUT — Decompose your Residual Emissions by Scope (mtCO2e) Prediction with CAGR: =(FY2024/FY2020)^(1/4)-1 → then each year = previous_year × (1+CAGR)
B16: Scope / Year → | C16: 2020 | D16: 2021 | E16: 2022 | F16: 2023 | G16: 2024 | H16: 2025 | I16: 2026 | J16: 2027 | K16: 2028 | L16: 2029 | M16: 2030
B17: 🌿 Scope 1 — Direct Emissions | I17: 158197 | J17: 166095 | K17: 174387 | L17: 183093 | M17: 192234
B18: ⚡ Scope 2 — Purchased Energy (location based) | I18: =('Trend Analysis'!F8+1)*H18 -> 0 | J18: =('Trend Analysis'!F8+1)*I18 -> 0 | K18: =('Trend Analysis'!F8+1)*J18 -> 0 | L18: =('Trend Analysis'!F8+1)*K18 -> 0 | M18: =('Trend Analysis'!F8+1)*L18 -> 0
B19: ⚡ Scope 2 — Purchased Energy (market based) | I19: 195271 | J19: 169524 | K19: 147172 | L19: 127767 | M19: 110921
B20: Subtotal (Scope 1 + 2 Market-based) | I20: 337110 | J20: 308476 | K20: 282274 | L20: 258297 | M20: 236357
B21: 🔗 Scope 3 — Value Chain | I21: 17152263 | J21: 18256571 | K21: 19431977 | L21: 20683059 | M21: 22014689
B22: 📊 TOTAL (S1+S2+S3) | C22: 12370000 | D22: 14129000 | E22: 16343000 | F22: 16935000 | G22: 15543000 | H22: 16456070 | I22: 17422778 | J22: 18446275 | K22: 19529898 | L22: 20677178 | M22: 21891855
B24: 🏁 MILESTONES — Label key points on your pathway (shown as annotations on chart)
B25: Year | C25: Label / Commitment | D25: Target Value (tCO₂e) | E25: Notes
B26: 2030 | C26: Net-Zero Commitment | D26: ='Trend Analysis'!F18 -> 8150708.1 | E26: ='Trend Analysis'!H18 -> Target scope 1+2
B27: 2030 | C27: Near-Term SBTi (Scope 1+2) | D27: ='Trend Analysis'!#REF! -> #REF! | E27: ='Trend Analysis'!#REF! -> #REF!
B28: 2030 | C28: Scope 3 Reduction Target | D28: ='Trend Analysis'!F19 -> 8264297.5 | E28: ='Trend Analysis'!H19 -> Target scope 3
C29: [Enter milestone year] | E29: [Enter note]
C30: [Enter milestone year] | E30: [Enter note]
B33: 📈 NET ZERO PATHWAY CHART — Auto-generated from your inputs above
B58: Note: Trajectory slope can change depend on company pace, new technologies and strategic actions
B59: 📊 SCOPE 1 / 2 / 3 BREAKDOWN CHART — build

Sheet Documentation
A1: METHODOLOGY DOCUMENTATION (ASSUMPTIONS LOG)
A2: Document EVERY emission factor, boundary decision, and methodology choice here. This becomes your report's Methodology section.
A4: EMISSION FACTOR LOG — Document every factor used in your calculations
A5: # | B5: Scope / Category | C5: Fuel/Energy Type | D5: EF Value Used | E5: EF Unit | F5: EF Source | G5: Year of EF | H5: Rationale / Notes
A6: 1 | B6: Scope 1 — Stationary | C6: Natural Gas | D6: 53.06 kgCO₂/MMBtu | E6: kgCO₂/MMBtu | F6: EPA CCCL 2023 | G6: 2023 | H6: Used EPA Table 1 national average. Update if company uses a regional specific factor.
A7: 2 | B7: Scope 1 — Stationary | C7: Diesel Fuel | D7: 2.698 kgCO₂/litre | E7: kgCO₂/litre | F7: EPA CCCL 2023 | G7: 2023 | H7: Converted from gallon-based factor. Verify unit consistency with fuel bills.
A8: 3 | B8: Scope 1 — Mobile | C8: Gasoline (fleet) | D8: 2.312 kgCO₂/litre | E8: kgCO₂/litre | F8: DEFRA 2023 | G8: 2023 | H8: DEFRA UK government conversion factors — appropriate for global use.
A9: 4 | B9: Scope 1 — Fugitive | C9: HFC-134a | D9: 1526 kgCO₂e/kg | E9: kgCO₂e/kg | F9: IPCC AR6 2021 | G9: 2021 | H9: GWP from IPCC AR6. Quantity from maintenance records or refrigerant purchase data.
A10: 5 | B10: Scope 2 — Electricity | C10: Grid EF — [specify region] | D10: [Enter value] kgCO₂e/MWh | E10: kgCO₂e/MWh | F10: [Enter source — IEA/EPA/DEFRA] | G10: [Enter year] | H10: [Enter rationale for choosing this regional factor]
A11: 6 | B11: Scope 2 — Market-Based | C11: Supplier/Residual EF | D11: [Enter value] kgCO₂e/MWh | E11: kgCO₂e/MWh | F11: [Enter source] | G11: [Enter year] | H11: [Explain if company holds RECs, PPAs, or uses utility supplier factor]
A12: 7 | B12: Scope 3 — Cat 1 | C12: EEIO Factor — [spend category] | D12: [Enter value] kgCO₂e/$ | E12: kgCO₂e/USD | F12: US EPA USEEIO v2.0 | G12: 2022 | H12: Spend-based method used due to lack of primary supplier data. Uncertainty range ±30-50%.
A13: 8 | B13: Scope 3 — Cat 3 | C13: T&D Loss Factor — Electricity | D13: 5% loss factor | E13: % | F13: IEA / Local utility | G13: [Enter year] | H13: Applied to total purchased electricity to estimate upstream T&D emissions.
A14: 9 | B14: Scope 3 — Cat 6 | C14: Business Travel — Air EF | D14: 0.255 kgCO₂e/km (short haul) | E14: kgCO₂e/km | F14: DEFRA 2023 | G14: 2023 | H14: Economy class assumed unless company travel data specifies class breakdown.
A15: 10 | B15: [Enter] | C15: [Enter] | D15: [Enter] | E15: [Enter] | F15: [Enter] | G15: [Enter] | H15: [Enter]
A16: 11 | B16: [Enter] | C16: [Enter] | D16: [Enter] | E16: [Enter] | F16: [Enter] | G16: [Enter] | H16: [Enter]
A17: 12 | B17: [Enter] | C17: [Enter] | D17: [Enter] | E17: [Enter] | F17: [Enter] | G17: [Enter] | H17: [Enter]
... A22: 17 | B22: [Enter] | C22: [Enter] | D22: [Enter] | E22: [Enter] | F22: [Enter] | G22: [Enter] | H22: [Enter]
A25: BOUNDARY & METHODOLOGY DECISIONS
A26: Decision Area | B26: Your Choice
A27: Organizational boundary method | B27: [Which part of the company are included in the inventory: Operational Control / Equity Share / Financial Control]
A28: Geographic boundary | B28: [Global / EMEA / Americas / specify]. It prevents mixing unrelated regions and ensures the correct electricity factors, fuel types, and supply‑chain assumptions.
A29: Scope 2 accounting method primary | B29: [Market-Based]. Companies must report electricity emissions in two ways: - Location‑based → Grid average - Market‑based → Supplier‑specific, RECs, PPAs, green tariff. Distinguish actual procurement choices from physical grid emissions.
A30: GWP version used | B30: [AR6 2021 / AR5 2014 / AR4 2007] Which one.
A31: Scope 3 categories selected | B31: [List cat numbers included: e.g. 1, 3, 6] You must disclose which categories are included so stakeholders understand coverage and gaps.
A32: Estimation method for gaps | B32: [Spend-based / Industry average / Linear interpolation]
A33: Base year | B33: [e.g. 2019 — pre-COVID baseline]

Sheet EF hubs
B2: Emission Factors for Greenhouse Gas Inventories
F3: Last Modified: January 15, 2025
C4: Blue text indicates an update from the 2024 version of this document.
C5: Typically, greenhouse gas emissions are reported in units of carbon dioxide equivalent (CO2e). Gases are converted to CO2e by multiplying by their global warming potential (GWP). In most cases, the emission factors listed in this document generally have not been converted to CO2e. To do so, multiply the emissions by the corresponding GWP listed in the table below.
C7: Gas | D7: 100-Year GWP
C8: CH4 | D8: 28
C9: N2O | D9: 265
C10: Source: Intergovernmental Panel on Climate Change (IPCC), Fifth Assessment Report (AR5), 2013. See the source note to Table 11 for further explanation.
B12: Table 1 | C12: Stationary Combustion
C14: Fuel Type | D14: Heat Content (HHV) | E14: CO2 Factor | F14: CH4 Factor | G14: N2O Factor | H14: CO2 Factor | I14: CH4 Factor | J14: N2O Factor
D15: mmBtu per short ton | E15: kg CO2 per mmBtu | F15: g CH4 per mmBtu | G15: g N2O per mmBtu | H15: kg CO2 per short ton | I15: g CH4 per short ton | J15: g N2O per short ton
C16: Coal and Coke
C17: Anthracite | D17: 25.09 | E17: 103.69 | F17: 11 | G17: 1.6 | H17: 2602 | I17: 276 | J17: 40
C18: Bituminous | D18: 24.93 | E18: 93.28 | F18: 11 | G18: 1.6 | H18: 2325 | I18: 274 | J18: 40
C19: Sub-bituminous | D19: 17.25 | E19: 97.17 | F19: 11 | G19: 1.6 | H19: 1676 | I19: 190 | J19: 28
C20: Lignite | D20: 14.21 | E20: 97.72 | F20: 11 | G20: 1.6 | H20: 1389 | I20: 156 | J20: 23
C21: Mixed (Commercial Sector) | D21: 21.39 | E21: 94.27 | F21: 11 | G21: 1.6 | H21: 2016 | I21: 235 | J21: 34
C22: Mixed (Electric Power Sector) | D22: 19.73 | E22: 95.52 | F22: 11 | G22: 1.6 | H22: 1885 | I22: 217 | J22: 32
C23: Mixed (Industrial Coking) | D23: 26.28 | E23: 93.9 | F23: 11 | G23: 1.6 | H23: 2468 | I23: 289 | J23: 42
C24: Mixed (Industrial Sector) | D24: 22.35 | E24: 94.67 | F24: 11 | G24: 1.6 | H24: 2116 | I24: 246 | J24: 36
C25: Coal Coke | D25: 24.8 | E25: 113.67 | F25: 11 | G25: 1.6 | H25: 2819 | I25: 273 | J25: 40
C26: Other Fuels - Solid
C27: Municipal Solid Waste | D27: 9.95 | E27: 90.7 | F27: 32 | G27: 4.2 | H27: 902 | I27: 318 | J27: 42
C28: Petroleum Coke (Solid) | D28: 30 | E28: 102.41 | F28: 32 | G28: 4.2 | H28: 3072 | I28: 960 | J28: 126
C29: Plastics | D29: 38 | E29: 75 | F29: 32 | G29: 4.2 | H29: 2850 | I29: 1216 | J29: 160
C30: Tires | D30: 28 | E30: 85.97 | F30: 32 | G30: 4.2 | H30: 2407 | I30: 896 | J30: 118
C31: Biomass Fuels - Solid
C32: Agricultural Byproducts | D32: 8.25 | E32: 118.17 | F32: 32 | G32: 4.2 | H32: 975 | I32: 264 | J32: 35
C33: Peat | D33: 8 | E33: 111.84 | F33: 32 | G33: 4.2 | H33: 895 | I33: 256 | J33: 34
C34: Solid Byproducts | D34: 10.39 | E34: 105.51 | F34: 32 | G34: 4.2 | H34: 1096 | I34: 332 | J34: 44
C35: Wood and Wood Residuals | D35: 17.48 | E35: 93.8 | F35: 7.2 | G35: 3.6 | H35: 1640 | I35: 126 | J35: 63
D36: mmBtu per scf | E36: kg CO2 per mmBtu | F36: g CH4 per mmBtu | G36: g N2O per mmBtu | H36: kg CO2 per scf | I36: g CH4 per scf | J36: g N2O per scf
C37: Natural Gas
C38: Natural Gas | D38: 0.001026 | E38: 53.06 | F38: 1 | G38: 0.1 | H38: 0.05444 | I38: 0.00103 | J38: 0.0001
C39: Other Fuels - Gaseous
C40: Blast Furnace Gas | D40: 9.2e-05 | E40: 274.32 | F40: 0.022 | G40: 0.1 | H40: 0.02524 | I40: 2e-06 | J40: 9e-06
C41: Coke Oven Gas | D41: 0.000599 | E41: 46.85 | F41: 0.48 | G41: 0.1 | H41: 0.02806 | I41: 0.000288 | J41: 6e-05
C42: Fuel Gas | D42: 0.001388 | E42: 59 | F42: 3 | G42: 0.6 | H42: 0.08189 | I42: 0.004164 | J42: 0.000833
C43: Propane Gas | D43: 0.002516 | E43: 61.46 | F43: 3 | G43: 0.6 | H43: 0.15463 | I43: 0.007548 | J43: 0.00151
C44: Biomass Fuels - Gaseous
C45: Landfill Gas | D45: 0.000485 | E45: 52.07 | F45: 3.2 | G45: 0.63 | H45: 0.025254 | I45: 0.001552 | J45: 0.000306
C46: Other Biomass Gases | D46: 0.000655 | E46: 52.07 | F46: 3.2 | G46: 0.63 | H46: 0.034106 | I46: 0.002096 | J46: 0.000413
D47: mmBtu per gallon | E47: kg CO2 per mmBtu | F47: g CH4 per mmBtu | G47: g N2O per mmBtu | H47: kg CO2 per gallon | I47: g CH4 per gallon | J47: g N2O per gallon
C48: Petroleum Products
C49: Asphalt and Road Oil | D49: 0.158 | E49: 75.36 | F49: 3 | G49: 0.6 | H49: 11.91 | I49: 0.47 | J49: 0.09
C50: Aviation Gasoline | D50: 0.12 | E50: 69.25 | F50: 3 | G50: 0.6 | H50: 8.31 | I50: 0.36 | J50: 0.07
C51: Butane | D51: 0.103 | E51: 64.77 | F51: 3 | G51: 0.6 | H51: 6.67 | I51: 0.31 | J51: 0.06
C52: Butylene | D52: 0.105 | E52: 68.72 | F52: 3 | G52: 0.6 | H52: 7.22 | I52: 0.32 | J52: 0.06
C53: Crude Oil | D53: 0.138 | E53: 74.54 | F53: 3 | G53: 0.6 | H53: 10.29 | I53: 0.41 | J53: 0.08
C54: Distillate Fuel Oil No. 1 | D54: 0.139 | E54: 73.25 | F54: 3 | G54: 0.6 | H54: 10.18 | I54: 0.42 | J54: 0.08
C55: Distillate Fuel Oil No. 2 | D55: 0.138 | E55: 73.96 | F55: 3 | G55: 0.6 | H55: 10.21 | I55: 0.41 | J55: 0.08
C56: Distillate Fuel Oil No. 4 | D56: 0.146 | E56: 75.04 | F56: 3 | G56: 0.6 | H56: 10.96 | I56: 0.44 | J56: 0.09
C57: Ethane | D57: 0.068 | E57: 59.6 | F57: 3 | G57: 0.6 | H57: 4.05 | I57: 0.2 | J57: 0.04
C58: Ethylene | D58: 0.058 | E58: 65.96 | F58: 3 | G58: 0.6 | H58: 3.83 | I58: 0.17 | J58: 0.03
C59: Heavy Gas Oils | D59: 0.148 | E59: 74.92 | F59: 3 | G59: 0.6 | H59: 11.09 | I59: 0.44 | J59: 0.09
C60: Isobutane | D60: 0.099 | E60: 64.94 | F60: 3 | G60: 0.6 | H60: 6.43 | I60: 0.3 | J60: 0.06
... C78: Used Oil | D78: 0.138 | E78: 74 | F78: 3 | G78: 0.6 | H78: 10.21 | I78: 0.41 | J78: 0.08
C79: Biomass Fuels - Liquid
C80: Biodiesel (100%) | D80: 0.128 | E80: 73.84 | F80: 1.1 | G80: 0.11 | H80: 9.45 | I80: 0.14 | J80: 0.01
C81: Ethanol (100%) | D81: 0.084 | E81: 68.44 | F81: 1.1 | G81: 0.11 | H81: 5.75 | I81: 0.09 | J81: 0.01
C82: Rendered Animal Fat | D82: 0.125 | E82: 71.06 | F82: 1.1 | G82: 0.11 | H82: 8.88 | I82: 0.14 | J82: 0.01
C83: Vegetable Oil | D83: 0.12 | E83: 81.55 | F83: 1.1 | G83: 0.11 | H83: 9.79 | I83: 0.13 | J83: 0.01
C84: Biomass Fuels - Kraft Pulping Liquor, by Wood Furnish
C85: North American Softwood | E85: 94.4 | F85: 1.9 | G85: 0.42
C86: North American Hardwood | E86: 93.7 | F86: 1.9 | G86: 0.42
C87: Bagasse | E87: 95.5 | F87: 1.9 | G87: 0.42
C88: Bamboo | E88: 93.7 | F88: 1.9 | G88: 0.42
C89: Straw | E89: 95.1 | F89: 1.9 | G89: 0.42
C90: Source:
C91: Federal Register EPA; 40 CFR Part 98; e-CFR, (see link below). Table C-1 and Table C-2 (78 FR 71950, Nov. 29, 2013, as amended at 81 FR 89252, Dec. 9, 2016), Table AA-1 (78 FR 71965, Nov. 29, 2013).
C92: https://www.ecfr.gov/current/title-40/chapter-I/subchapter-C/part-98
C93: Notes:
C94: Emission factors are per unit of heat content using higher heating values (HHV). If heat content is available from the fuel supplier, it is preferable to use that value. If not, default heat contents are provided.
C95: All CO2 emission factors assume that 100 percent of the carbon content of the fuel is oxidized to CO2, as is recommended by the Intergovernmental Panel on Climate Change (IPCC).
C96: The CH4 and N2O emission factors provided represent emissions in terms of fuel type and by end-use sector (i.e., residential, commercial, industrial, electricity generation).
C97: Please see the Center for Corporate Climate Leadership's guidance document on Direct Emissions from Stationary Combustion Sources for guidance on how to include biomass fuels in an organization's greenhouse gas inventory.
C98: https://www.epa.gov/sites/default/files/2020-12/documents/stationaryemissions.pdf
C99: The factors represented in the table above represent combustion emissions only and do not represent upstream emissions.
B101: Table 2 | C101: Mobile Combustion CO2
C103: Fuel Type | D103: kg CO2 per unit | E103: Unit
C104: Aviation Gasoline | D104: 8.31 | E104: gallon
C105: Biodiesel (100%) | D105: 9.45 | E105: gallon
C106: Compressed Natural Gas (CNG) | D106: 0.05444 | E106: scf
C107: Diesel Fuel | D107: 10.21 | E107: gallon
C108: Ethanol (100%) | D108: 5.75 | E108: gallon
C109: Kerosene-Type Jet Fuel | D109: 9.75 | E109: gallon
C110: Liquefied Natural Gas (LNG) | D110: 4.5 | E110: gallon
C111: Liquefied Petroleum Gases (LPG) | D111: 5.68 | E111: gallon
C112: Motor Gasoline | D112: 8.78 | E112: gallon
C113: Residual Fuel Oil | D113: 11.27 | E113: gallon
C114: Source:
C115: Federal Register EPA; 40 CFR Part 98; e-CFR, (see link below). Table C-1 (78 FR 71950, Nov. 29, 2013, as amended at 81 FR 89252, Dec. 9, 2016)
C116: https://www.ecfr.gov/current/title-40/chapter-I/subchapter-C/part-98
C117: Notes:
C118: LNG: The factor was developed based on the CO2 factor (kg CO2 per mmBtu) for Natural Gas from Table 1 and the higher heating value (HHV) LNG fuel density factor (btu/gallon) from the R&D GREET1 2024 Model, Argonne National Laboratory published January 10, 2025 (Fuel_Specs worksheet).
C119: More information on GREET can be found here: https://greet.anl.gov/
C120: Please see the Center for Corporate Climate Leadership's guidance document on Direct Emissions from Stationary Combustion Sources for guidance on how to include biomass fuels in an organization's greenhouse gas inventory.
C121: https://www.epa.gov/sites/default/files/2020-12/documents/stationaryemissions.pdf
C122: The factors represented in the table above represent combustion emissions only (tank-to-wheel) and do not represent upstream emissions or well-to-wheel emissions.
B124: Table 3 | C124: Mobile Combustion CH4 and N2O for On-Road Gasoline Vehicles
...

Sheet 📊 Dashboard
B2: 🌍 CARBON FOOTPRINT EXECUTIVE DASHBOARD
B3: GHG Protocol Framework · All figures link live to Scope 1, 2, 3 & Assumptions sheets
B6: SCOPE 1 DIRECT | D6: SCOPE 2 MARKET-BASED | F6: SCOPE 3 VALUE CHAIN | H6: TOTAL S1 + S2 + S3
B7: =#REF! -> #REF! | D7: ='Scope 2 W'!I59 -> 0 | F7: ='Scope 3 W'!J70 -> 0 | H7: ='Summary & Intensity'!D54 -> 24199224
B8: tCO₂e | D8: tCO₂e | F8: tCO₂e | H8: tCO₂e
B9: Combustion · Fleet · Fugitive | D9: Purchased electricity (primary) | F9: Upstream & downstream emissions | H9: Combined GHG inventory
B11: 📊 SCOPE BREAKDOWN — Linked live from Summary & Intensity sheet
B12: Scope | C12: Description | D12: tCO₂e | E12: % of Total | F12: Location-Based | G12: Mkt-Based | H12: Target | I12: Status
B13: Scope 1 | C13: Direct Emissions | D13: ='Summary & Intensity'!D38 -> 21851880 | E13: =IFERROR(D13/'Summary & Intensity'!D54,0) -> 0.9029992 | F13: — | G13: ='Scope 2 W'!H58 -> 0 | H13: =#REF! -> #REF! | I13: 🟡 Input needed
B14: Scope 2 | C14: Purchased Energy | D14: ='Summary & Intensity'!D39 -> 1267091.2 | E14: =IFERROR(D14/'Summary & Intensity'!D54,0) -> 0.05236082 | F14: ='Scope 2 W'!H58 -> 0 | G14: ='Scope 2 W'!I59 -> 0 | H14: =#REF! -> #REF! | I14: 🟡 Input needed
B15: Scope 3 | C15: Value Chain Emissions | D15: ='Summary & Intensity'!D41 -> 9653 | E15: =IFERROR(D15/'Summary & Intensity'!D54,0) -> 0.00039889708 | F15: — | G15: — | H15: =#REF! -> #REF! | I15: 🟡 Input needed
B16: TOTAL (S1+S2+S3) | C16: Combined Inventory | D16: ='Summary & Intensity'!D54 -> 24199224 | E16: =IFERROR(D16/'Summary & Intensity'!D54,0) -> 1 | F16: — | G16: — | H16: — | I16: ✅ Calculated
B18: 🎯 REDUCTION TARGETS — Linked live from Trend Analysis sheet
B19: Target | C19: Target Year | D19: Baseline Year | E19: Baseline (tCO₂e) | F19: % Required | G19: Target (tCO₂e) | H19: Annual Reduction | I19: Type
B20: ='Trend Analysis'!A18 -> Socpe 1 and 2 - 27.5% Reduction | C20: ='Trend Analysis'!B18 -> 2030 | D20: ='Trend Analysis'!C18 -> 2019 | E20: ='Trend Analysis'!D18 -> 11242356 | F20: ='Trend Analysis'!E18 -> 0.275 | G20: ='Trend Analysis'!F18 -> 8150708.1 | H20: ='Trend Analysis'!G18 -> 281058.9 | I20: ='Trend Analysis'!H18 -> Target scope 1+2
B21: ='Trend Analysis'!#REF! -> #REF! | C21: ='Trend Analysis'!#REF! -> #REF! | D21: ='Trend Analysis'!#REF! -> #REF! | E21: ='Trend Analysis'!#REF! -> #REF! | F21: ='Trend Analysis'!#REF! -> #REF! | G21: ='Trend Analysis'!#REF! -> #REF! | H21: ='Trend Analysis'!#REF! -> #REF! | I21: ='Trend Analysis'!#REF! -> #REF!
B22: ='Trend Analysis'!A19 -> Scope 3 Reduction Target | C22: ='Trend Analysis'!B19 -> 2030 | D22: ='Trend Analysis'!C19 -> 2019 | E22: ='Trend Analysis'!D19 -> 11399031 | F22: ='Trend Analysis'!E19 -> 0.275 | G22: ='Trend Analysis'!F19 -> 8264297.5 | H22: ='Trend Analysis'!G19 -> 284975.78 | I22: ='Trend Analysis'!H19 -> Target scope 3
B24: 📐 CARBON INTENSITY RATIOS — Linked live from Summary & Intensity sheet
B25: Metric | C25: Formula | D25: Current Year | E25: Prior Year | F25: Change (%) | G25: Industry Benchmark | H25: vs Benchmark | I25: Unit
B26: Carbon Intensity — Revenue | C26: tCO₂e / $M revenue | D26: ='Summary & Intensity'!D60 -> Current Year (tCO₂e / unit) | E26: ='Summary & Intensity'!E60 -> Prior Year (tCO₂e / unit) | F26: ='Summary & Intensity'!F60 -> Change (%) | G26: ='Summary & Intensity'!G60 -> Industry Benchmark | H26: ='Summary & Intensity'!H60 -> vs. Benchmark | I26: tCO₂e/$M
B27: Carbon Intensity — Employee | C27: tCO₂e / FTE | D27: ='Summary & Intensity'!D61 -> 0 | E27: ='Summary & Intensity'!E61 -> 0 | F27: ='Summary & Intensity'!F61 -> 0 | G27: ='Summary & Intensity'!G61 -> [Industry benchmark] | H27: ='Summary & Intensity'!H61 -> 0 | I27: tCO₂e/FTE
B28: % Renewable Energy | C28: RECs / Total elec. | D28: ='Summary & Intensity'!D67 -> #DIV/0! | E28: ='Summary & Intensity'!E67 -> 0.98165743 | F28: ='Summary & Intensity'!F67 -> 0 | G28: ='Summary & Intensity'!G67 -> [Industry benchmark] | H28: ='Summary & Intensity'!H67 -> 0 | I28: %
B29: Scope 1 Intensity | C29: S1 / $M revenue | D29: ='Summary & Intensity'!D64 -> 0 | E29: ='Summary & Intensity'!E64 -> 0 | F29: ='Summary & Intensity'!F64 -> 0 | G29: ='Summary & Intensity'!G64 -> [Industry benchmark] | H29: ='Summary & Intensity'!H64 -> 0 | I29: tCO₂e/$M
B30: Scope 2 MB Intensity | C30: S2MB / $M revenue | D30: ='Summary & Intensity'!D65 -> 0 | E30: ='Summary & Intensity'!E65 -> 0 | F30: ='Summary & Intensity'!F65 -> 0 | G30: ='Summary & Intensity'!G65 -> [Industry benchmark] | H30: ='Summary & Intensity'!H65 -> 0 | I30: tCO₂e/$M
B31: Scope 3 Intensity | C31: S3 / $M revenue | D31: ='Summary & Intensity'!D66 -> 0 | E31: ='Summary & Intensity'!E66 -> 0 | F31: ='Summary & Intensity'!F66 -> 0 | G31: ='Summary & Intensity'!G66 -> [Industry benchmark] | H31: ='Summary & Intensity'!H66 -> 0 | I31: tCO₂e/$M
B33: ⚙️ COMPANY INFORMATION — Linked live from Assumptions sheet
B34: Field | C34: Value | D34: Notes | E34: Status
B35: Company Name | C35: =Assumptions!B9 -> Westrock Company | D35: =Assumptions!C9 -> Used in all sheet headers | E35: —
B36: Industry / Sector | C36: =Assumptions!B10 -> Pulp, Paper and Packaging | D36: =Assumptions!C10 -> Affects SASB materiality and EF selection | E36: —
B37: Country of Operations | C37: =Assumptions!B11 -> USA | D37: =Assumptions!C11 -> Used to select default grid emission factor | E37: —
B38: Reporting Year | C38: =Assumptions!B12 -> 2023 | D38: =Assumptions!C12 -> Year of primary data being analyzed | E38: —
B39: Annual Revenue ($M) | C39: =Assumptions!B15 -> 0 | D39: =Assumptions!C15 -> USD Millions | E39: Required for intensity ratios
B40: Employees (FTE) | C40: =Assumptions!B16 -> 0 | D40: =Assumptions!C16 -> Headcount | E40: Required for intensity ratios
B42: All KPIs update automatically when activity data is entered in Scope 1, 2, 3 and Assumptions sheets · GHG Protocol Corporate Standard
